Workbook

Sheet Business Rules
A1: IREI Underwriting Template Prototype
A3: Business Rules Organized by Epics and User Stories
A5: 1. Purpose of the Model
A7: The model is designed to convert non-profit / Indigenous / mission-driven housing organization data into a standardized, auditable underwriting structure.
A9: It has two purposes:
A11: 1. Current use: underwrite NGO B’s portfolio using the existing live Excel calculation engine.
A13: 2. Future platform use: establish the data architecture and business rules for an AI / analyst-assisted IREI underwriting platform.
A15: The model is not yet a fully automated platform engine. The current financial calculations still rely on legacy NGO B tabs, while the new DATA and OUT layers define the future standardized model structure.
A19: Epic 1 — Workbook Navigation and User Control
A21: Business Objective
A23: Ensure analysts and AI agents understand where to enter data, where formulas live, what not to overwrite, and how to follow the workbook structure.
A25: Key Tabs
... A1167: BR-16.5 — Any future audit-summary change must be logged in 00_CHANGE_LOG.

Sheet 00_PLATFORM_INDEX
A1: IREI PLATFORM TEMPLATE LAYER — v10 colour-controlled working master
A2: Purpose | B2: Adds platform-ready bridge, authoritative classification, capital-flow separation, property-level traceability, reconciliation controls, and a live investor summary while preserving live calculations.
A3: Core rule | B3: Future NGOs provide messy source files; IREI/AI maps them into canonical DATA sheets, then model outputs are generated.
A4: Layer | B4: Sheet | C4: Role | D4: Live / Manual | E4: Status | G4: COLOUR / EDITING STANDARD — v10
A5: 1 Intake | B5: STG_SOURCE_INTAKE | C5: Log source files and review status. | D5: Manual / future AI-populated | E5: New | G5: Style | H5: Meaning | I5: Control Rule | J5: Example | K5: Owner
A6: 2 Mapping | B6: MAP_FIELD_MAPPING | C6: Translate messy source fields into IREI canonical fields. | D6: Standard / AI-assisted | E6: New | G6: Blue fill / blue font | H6: Analyst / AI input cell | I6: Allowed to write only in mapped input ranges | J6: STG_SOURCE_INTAKE rows | K6: Analyst / AI
A7: 3 Property master | B7: DATA_PROPERTY_MASTER | C7: One row per property linked to current model. | D7: Live formulas | E7: New | G7: Black font | H7: Live formula / calculated output | I7: Do not overwrite | J7: DATA_CAPITAL_FLOW formulas | K7: Model / Excel
A8: 4 Classification | B8: DATA_ASSET_CLASSIFICATION | C8: Classify every property once using formula-driven rules and controlled override governance. | D8: Live formulas / controlled manual override | E8: New in v4 | G8: Purple fill / tab | H8: Generated or normalized DATA layer | I8: Generated from current model today; future AI/Python output | J8: DATA_PROPERTY_MASTER | K8: AI / model generator
A9: 5 Debt master | B9: DATA_DEBT_MASTER | C9: One row per property debt profile. | D9: Live formulas | E9: New | G9: Orange fill | H9: Warning / required review | I9: Resolve before external use | J9: DATA_QUALITY_CHECKS | K9: Analyst reviewer
A10: 6 Metric long table | B10: DATA_METRIC_LONG | C10: Property-year-metric rows linked to BLD_* tabs. | D10: Live formulas | E10: New | G10: Grey tab / grey header | H10: Legacy NGO B calculation engine | I10: Do not edit unless rebuilding the engine | J10: BLD_* tabs | K10: Model maintainer
A11: 7 Checks | B11: DATA_QUALITY_CHECKS | C11: Live platform-readiness checks. | D11: Live formulas | E11: New | G11: Green tab/header | H11: Output / summary page | I11: Output only; formulas should source from authority layers | J11: 00_INVESTOR SUMMARY | K11: Reader / reviewer
A12: 8 Output | B12: OUT_PLATFORM_READINESS | C12: Dashboard for migration readiness. | D12: Live formulas | E12: New
A14: Total properties | B14: =COUNTA(DATA_PROPERTY_MASTER!$A$5:$A$21) -> 17
A15: Included properties | B15: =COUNTIF(DATA_PROPERTY_MASTER!$E$5:$E$21,"Yes") -> 16
A16: Metric rows | B16: =COUNTA(DATA_METRIC_LONG!$A$5:$A$10000) -> 816
A17: 9 Capital-flow authority | B17: DATA_CAPITAL_FLOW | C17: Separates operating cash, debt service, refinance surplus, and residual funding gap into live canonical rows. | D17: Live formulas from existing rollup | E17: New in v5
A18: 10 Capital-flow output | B18: OUT_CAPITAL_FLOW_SUMMARY | C18: Provides clean year-by-year output and reconciliation against the legacy rollup total. | D18: Live formulas from existing rollup | E18: New in v5
A19: 11 Aggregation audit | B19: DATA_AGGREGATION_AUDIT | C19: Tracks included/excluded source errors suppressed by guarded rollup aggregation formulas. | D19: Live formulas | E19: New in v6
A20: 12 Property-level capital-flow | B20: DATA_CAPITAL_FLOW | C20: Adds Level = Property rows by BLD_ID/year/metric, linked to property tabs and scope-adjusted to reconcile to portfolio totals. | D20: Live formulas from BLD_* tabs | E20: New in v7
A21: 13 Capital-flow reconciliation | B21: DATA_CAPITAL_FLOW_RECON | C21: Checks that property-level sums equal the portfolio-level capital-flow rows for each year and metric. | D21: Live SUMIFS formulas | E21: New in v7
A22: 8 Output | B22: 00_INVESTOR SUMMARY | C22: Investor-facing summary rebuilt from DATA_ASSET_CLASSIFICATION, DATA_CAPITAL_FLOW, and DATA_CAPITAL_FLOW_RECON. | D22: Live formulas | E22: New in v8
A23: v9 governance additions
A24: INPUT_CONTROL_MAP | B24: Human/AI write map | C24: Centralized map of writable inputs, generated outputs, and legacy engine zones. | D24: Active | E24: Use this as analyst/AI operating guide.
A25: MAP_FIELD_MAPPING | B25: Current-vs-future field map | C25: Updated to distinguish live current sources from future canonical target tables. | D25: Active | E25: Prevents the map from promising non-live tables.
A26: DATA_AGGREGATION_AUDIT | B26: Dynamic audit formulas | C26: Removed chained BLD_AB + BLD_AC style formulas; now references DATA_PROPERTY_MASTER dynamically. | D26: Active | E26: Better survives changing property counts.
A27: Remaining manual scaling item | B27: Underlying engine | C27: 01/02/BLD tabs remain NGO B-specific calculation engine. | D27: Open | E27: Future Python should generate/replace engine from canonical DATA tables.
A28: 11 Colour control | B28: INPUT_CONTROL_MAP / 00_PLATFORM_INDEX | C28: Adds explicit colour/editing convention: blue inputs, black formulas, purple generated data, orange warnings, grey legacy engine, green outputs. | D28: Visual governance | E28: New in v10
A30: v11 Canonical input layer
A31: Layer | B31: Sheet | C31: Role | D31: Live / Manual | E31: Status
A32: Canonical input | B32: DATA_UNIT_MIX | C32: Unit mix and affordability/rent restriction evidence | D32: Blue inputs + live formula checks | E32: New in v11
A33: Canonical input | B33: DATA_RENT_ROLL | C33: Unit-level or summarized rent roll evidence | D33: Blue inputs + live formula checks | E33: New in v11
A34: Canonical input | B34: DATA_OPERATING_ACTUALS | C34: Long-format operating actual/budget/projection rows | D34: Blue inputs + live formula checks | E34: New in v11
A35: Canonical input | B35: DATA_AGREEMENTS | C35: Legal/funding/affordability restriction evidence | D35: Blue inputs + live formula checks | E35: New in v11
A36: Canonical input | B36: DATA_CAPITAL_NEEDS | C36: Capital needs, fixed assets, funded/unfunded gap | D36: Blue inputs + live formula checks | E36: New in v11

Sheet INPUT_CONTROL_MAP
A1: INPUT_CONTROL_MAP — v11 analyst / AI write map
A2: Purpose | B2: One centralized instruction layer showing where humans or AI may write, what is generated, and what remains legacy NGO B calculation engine.
A3: Rule | B3: Do not write into generated DATA/OUT tabs except in designated override/input columns. Future AI ingestion should write to intake/canonical input zones first, then generate the model.
A5: Zone | B5: Tab | C5: Range / Columns | D5: Field / Purpose | E5: Write Permission | F5: Table Exists? | G5: Engine Repoint Status / Feeds To | H5: Notes
A6: PRIMARY INPUT | B6: STG_SOURCE_INTAKE | C6: A5:H25 | D6: Source file log: NGO files, Yardi/CSV exports, fiscal year, received status | E6: Human / AI may write | F6: Yes | G6: Feeds evidence tracking and future ingestion | H6: This is the first place analysts should document files received.
A7: PRIMARY INPUT | B7: 00_MODEL_CONTROL | C7: A5:E21; B31 | D7: Property ID, inclusion flag, selected current year | E7: Human / AI may write controlled cells | F7: Yes | G7: Feeds rollup scope, property master, classification | H7: Do not manually edit generated columns F:H.
A8: CONTROLLED OVERRIDE | B8: DATA_ASSET_CLASSIFICATION | C8: T8:T24 and Y8:Y24 | D8: Human classification override and required reason | E8: Human / AI may write only if justified | F8: Yes | G8: Feeds final classification U and all summaries | H8: If T is used, Y must be filled; QC flags missing reasons.
A9: GENERATED DATA | B9: DATA_PROPERTY_MASTER | C9: A5:O21 | D9: Canonical property master bridge | E9: Do not manually edit | F9: Yes | G9: Generated from current model; future generated from AI/source files | H9: Rows are still sized to NGO B; future Python should extend rows.
A10: GENERATED DATA | B10: DATA_DEBT_MASTER | C10: A5:L21 | D10: Canonical debt bridge | E10: Do not manually edit | F10: Yes | G10: Generated from current 02_Debt Engine / property tabs | H10: Not yet the source of calculations.
A11: GENERATED DATA | B11: DATA_METRIC_LONG | C11: A5:H10000 | D11: Long-format property metrics | E11: Do not manually edit | F11: Yes | G11: Generated from BLD_* tabs | H11: Future engine should generate directly from canonical data tables.
A12: GENERATED DATA | B12: DATA_CAPITAL_FLOW | C12: A5:Q5206 | D12: Portfolio and property-level capital flow | E12: Do not manually edit | F12: Yes | G12: Generated from rollup + property tabs | H12: Property-level rows reconcile to portfolio-level rows.
A13: GENERATED DATA | B13: DATA_CAPITAL_FLOW_RECON | C13: A5:H400 | D13: Capital flow reconciliation | E13: Do not manually edit | F13: Yes | G13: Generated from DATA_CAPITAL_FLOW | H13: Use to catch drift between property and portfolio totals.
A14: GENERATED DATA | B14: DATA_AGGREGATION_AUDIT | C14: A6:Y80 | D14: Suppressed source-error audit | E14: Do not manually edit | F14: Yes | G14: Generated from DATA_PROPERTY_MASTER + BLD_* tabs | H14: v9 formulas are dynamic; no BLD_AB + BLD_AC chaining.
A15: OUTPUT | B15: 00_INVESTOR SUMMARY | C15: A1:L60 | D15: Investor/funder-facing summary | E15: Do not manually edit core formulas | F15: Yes | G15: Generated from DATA_ASSET_CLASSIFICATION, DATA_CAPITAL_FLOW, audit/recon | H15: Text edits should be handled carefully; formula cells stay live.
A16: OUTPUT | B16: OUT_CAPITAL_FLOW_SUMMARY | C16: A1:R35 | D16: Capital-flow summary | E16: Do not manually edit | F16: Yes | G16: Generated from DATA_CAPITAL_FLOW | H16: Clean output view.
... A29: PRIMARY CANONICAL INPUT | B29: DATA_CAPITAL_NEEDS | C29: DATA_CAPITAL_NEEDS!B7:S206 | D29: Capital repairs, lifecycle, deferred maintenance, funding source | E29: Human / AI may write blue cells | F29: Yes - table exists | G29: Not repointed; future feed to capital plan and funding-gap analysis | H29: Canonical table exists in v11; not yet read by capital-flow engine.
A83: COLOUR / EDITING STANDARD — v10
A84: Style | B84: Meaning | C84: Where Used | D84: Who Can Edit | E84: Formula Rule | F84: Notes | G84: Status | H84: Version
A85: Blue | B85: Hardcoded input / controlled override | C85: STG_SOURCE_INTAKE; 00_MODEL_CONTROL A:E/B31; DATA_ASSET_CLASSIFICATION T/Y | D85: Analyst / AI | E85: Not formula-driven | F85: Only mapped blue cells should be written to. | G85: Live | H85: v10
A86: Black | B86: Formula / calculated output | C86: DATA/OUT sheets and generated fields | D86: Do not edit | E86: Formula cells remain black font | F86: Overwrite only if intentionally rebuilding the model. | G86: Live | H86: v10
A87: Purple | B87: Generated / normalized DATA layer | C87: DATA_PROPERTY_MASTER, DATA_DEBT_MASTER, DATA_METRIC_LONG, DATA_CAPITAL_FLOW | D87: Model / future AI generator | E87: May contain formulas today | F87: Future Python engine should generate these tables directly. | G87: Live bridge | H87: v10
A88: Orange | B88: Warning / review required | C88: DATA_QUALITY_CHECKS, DATA_ASSET_CLASSIFICATION X, recon/audit status fields | D88: Analyst reviewer | E88: May be formula-driven | F88: Resolve before external sharing. | G88: Live | H88: v10
A89: Grey | B89: Legacy NGO B engine / do-not-edit zone | C89: 01_/02_/BLD_* and legacy outputs | D89: Model maintainer only | E89: Existing formulas preserved | F89: Still bespoke to NGO B until canonical engines replace it. | G89: Open roadmap | H89: v10
A90: Green | B90: Output only | C90: 00_INVESTOR SUMMARY, OUT_PLATFORM_READINESS, OUT_CAPITAL_FLOW_SUMMARY | D90: Do not edit | E90: Formula-linked to authority layers | F90: Use for review, not input. | G90: Live | H90: v10
A92: PRIMARY CANONICAL INPUT | B92: DATA_UNIT_MIX | C92: B7:U206 | D92: Unit mix, rent restriction, source confidence and review fields | E92: Human / AI may write blue cells | F92: Yes | G92: Feeds future rent / affordability engine; not yet repointed | H92: Formula columns A,C,M,N,V remain live.
A93: PRIMARY CANONICAL INPUT | B93: DATA_RENT_ROLL | C93: B7:V206 | D93: Unit-level or summarized rent roll | E93: Human / AI may write blue cells | F93: Yes | G93: Feeds future rent engine; not yet repointed | H93: Formula columns A,C,P:R,W remain live.
A94: PRIMARY CANONICAL INPUT | B94: DATA_OPERATING_ACTUALS | C94: B7:Q206 | D94: Operating actuals / budget / projection long-format rows | E94: Human / AI may write blue cells | F94: Yes | G94: Feeds future base-year inputs and operating engine; not yet repointed | H94: Formula columns A,C,P,R remain live.
A95: PRIMARY CANONICAL INPUT | B95: DATA_AGREEMENTS | C95: B7:T206 | D95: Agreements, restrictions, subsidy and mission-protection evidence | E95: Human / AI may write blue cells | F95: Yes | G95: Feeds future classification/agreement risk logic; not yet repointed | H95: Formula columns A,C,S,U remain live.
A96: PRIMARY CANONICAL INPUT | B96: DATA_CAPITAL_NEEDS | C96: B7:S206 | D96: Capital needs, funded/unfunded gap, fixed asset/depreciation link | E96: Human / AI may write blue cells | F96: Yes | G96: Feeds future capital plan / capital flow; not yet repointed | H96: Formula columns A,C,J,R,T remain live.

Sheet STG_SOURCE_INTAKE
A1: STG_SOURCE_INTAKE
A2: Purpose | B2: Tracks source files received before AI extraction and human validation.
A3: Rule | B3: Does not change calculations until source data is mapped into DATA sheets.
A4: Source_File_ID | B4: NGO / Entity | C4: File Name / Export | D4: Source System | E4: File Type | F4: Fiscal Year / Period | G4: Received Status | H4: AI Extraction Status | I4: Human Review Status | J4: Maps To | K4: Notes
A5: SRC-001 | B5: Future NGO | C5: Yardi rent roll export | D5: Yardi | E5: CSV | F5: YYYY-MM | G5: Not Provided | H5: Not Started | I5: Not Started | J5: DATA_UNIT_MIX / DATA_RENT_ROLL | K5: Example only
A6: SRC-002 | B6: Future NGO | C6: General ledger export | D6: Yardi / Sage / QuickBooks | E6: CSV/XLSX | F6: YYYY | G6: Not Provided | H6: Not Started | I6: Not Started | J6: DATA_OPERATING_ACTUALS | K6: Example only
A7: SRC-003 | B7: Future NGO | C7: Debt schedule | D7: Bank / lender / internal | E7: XLSX/PDF | F7: As of date | G7: Not Provided | H7: Not Started | I7: Not Started | J7: DATA_DEBT_MASTER | K7: Example only
A8: SRC-004 | B8: Future NGO | C8: Property summary workbook | D8: Internal Excel | E8: XLSX | F8: Current | G8: Not Provided | H8: Not Started | I8: Not Started | J8: DATA_PROPERTY_MASTER | K8: Example only
A9: SRC-005 | B9: Future NGO | C9: Operating agreements / covenants | D9: Legal / funder | E9: PDF/DOCX | F9: Active | G9: Not Provided | H9: Not Started | I9: Not Started | J9: DATA_AGREEMENTS | K9: Example only
A102: v11 source-type note | B102: Classify source files as Operating Projection, Rent Roll/Yardi, Operating Actuals/GL, Agreement/Restriction, Capital Needs/FCA, Debt/Amortization, or Capital Product/Bond before mapping to canonical DATA tabs.

Sheet MAP_FIELD_MAPPING
A1: MAP_FIELD_MAPPING — v11 canonical input map
A2: Purpose | B2: Shows what the workbook actually uses today, plus the future canonical source-table target. Prevents the mapping table from promising a system that is not yet wired.
A3: Rule | B3: Current calculation source remains authoritative until the engine is repointed. Canonical tables may exist before they feed calculations; track table existence separately from repoint status.
A5: Source Field / Concept | B5: Current Calculation Source / Live Today | C5: Current Range | D5: Generated Target / Canonical Table | E5: Canonical Field | F5: Write Permission | G5: Repoint Status | H5: Notes
A6: Property ID | B6: 00_MODEL_CONTROL / 01_Property Summary | C6: 00_MODEL_CONTROL!A5:A21; 01_Property Summary!B4:R4 | D6: DATA_PROPERTY_MASTER | E6: Property_ID | F6: Generated from current model | G6: Live bridge | H6: Future NGO: AI should generate DATA_PROPERTY_MASTER rows first.
A7: Property Name | B7: 01_Property Summary | C7: 01_Property Summary!B5:R5 | D7: DATA_PROPERTY_MASTER | E7: Property_Name | F7: Generated from current model | G7: Live bridge | H7: Do not retype names in output tabs.
A8: Included in Model | B8: 00_MODEL_CONTROL | C8: 00_MODEL_CONTROL!E5:E21 | D8: DATA_PROPERTY_MASTER | E8: Included_In_Model | F8: Human / AI input control | G8: Live bridge | H8: This is a controlled input today.
A9: Asset Classification | B9: DATA_ASSET_CLASSIFICATION | C9: DATA_ASSET_CLASSIFICATION!U8:U24 | D9: DATA_ASSET_CLASSIFICATION | E9: Final_Classification | F9: Generated, with controlled override | G9: Live | H9: Human override only via T + Y reason.
A10: Register Bucket | B10: DATA_ASSET_CLASSIFICATION mapping | C10: DATA_ASSET_CLASSIFICATION!AA:AB -> 00_PORTFOLIO_REGISTER!J5:J21 | D10: DATA_ASSET_CLASSIFICATION | E10: Register_Bucket | F10: Generated | G10: Live | H10: Register is no longer an independent source.
A11: Unit Count | B11: 01_Property Summary | C11: 01_Property Summary!B6:R6 | D11: DATA_UNIT_MIX | E11: Unit_Count | F11: Human / AI may write blue cells | G11: Table exists; not engine-repointed | H11: v11 canonical DATA_UNIT_MIX exists; 01_Property Summary still drives calculations.
A12: Rent Roll | B12: BLD_* property tabs / 02_Rent Engine | C12: BLD_* rows 13:36; 02_Rent Engine | D12: DATA_RENT_ROLL | E12: Rent / Occupancy / Program Unit Fields | F12: Human / AI may write blue cells | G12: Table exists; not engine-repointed | H12: v11 canonical DATA_RENT_ROLL exists; rent engine/property tabs still drive calculations.
A13: Operating Actuals | B13: 01_Base Yr. Inputs / BLD_* tabs | C13: 01_Base Yr. Inputs; BLD_* rows 41:55 | D13: DATA_OPERATING_ACTUALS | E13: Revenue / Expense / NOI / AFFO | F13: Human / AI may write blue cells | G13: Table exists; not engine-repointed | H13: v11 canonical DATA_OPERATING_ACTUALS exists; calculations remain property-tab driven.
A14: Debt Terms | B14: 02_Debt Engine / 02A_Debt Schedule | C14: 02_Debt Engine; 02A_Debt Schedule | D14: DATA_DEBT_MASTER | E14: Loan Terms / Maturity / Balance / DS | F14: Generated from current model | G14: Live bridge | H14: Debt master is a bridge, not yet the source engine.
A15: Agreements / Covenants | B15: 01_Property Summary / manual notes | C15: Agreement expiry/status fields where available | D15: DATA_AGREEMENTS | E15: Agreement Type / Expiry / Restriction | F15: Human / AI may write blue cells | G15: Table exists; not engine-repointed | H15: v11 canonical DATA_AGREEMENTS exists; source evidence and downstream logic not fully wired yet.
A16: Capital Needs | B16: 00_CAPITAL_PLAN / BLD_* tabs | C16: 00_CAPITAL_PLAN; BLD_* capital rows where applicable | D16: DATA_CAPITAL_NEEDS | E16: Capex Item / Year / Amount / Funding Source | F16: Human / AI may write blue cells | G16: Table exists; not engine-repointed | H16: v11 canonical DATA_CAPITAL_NEEDS exists; not yet fed to capital plan/capital-flow engine.
... A106: Capital needs / fixed assets | B106: Current model uses capital plan and property/debt outputs | C106: 00_CAPITAL_PLAN; ENF amortization/FCA source files | D106: DATA_CAPITAL_NEEDS | E106: Estimated_Cost, Funded_Amount, Unfunded_Amount, Year_Needed | F106: Human / AI blue input | G106: Canonical table created; not repointed | H106: Connects future capital needs to capital-flow layer.

Sheet DATA_UNIT_MIX
A1: DATA_UNIT_MIX — canonical unit-mix intake
A2: Purpose | B2: One row per property/unit group. Supports NGO-level summaries or AI/Yardi normalized unit mix.
A3: Rule | B3: Created as a canonical intake table only; existing NGO B calculations are not repointed in v11.
A4: Input colour | B4: Blue cells are the only analyst / AI write zones. Black-font cells are live formulas and should not be overwritten.
A6: Record_ID | B6: Property_ID | C6: Property_Name | D6: Unit_Group_ID | E6: Bedroom_Type | F6: Unit_Type | G6: Unit_Count | H6: Affordable_Units | I6: Market_Units | J6: Supportive_Units | K6: Avg_Current_Rent | L6: Avg_Market_Rent | M6: Monthly_Rent_Potential | N6: Below_Market_% | O6: Rent_Restriction_Type | P6: Program_Type | Q6: Rent_Source | R6: Source_File_ID | S6: Source_Confidence | T6: Review_Status | U6: Notes | V6: Row_Status
A7: =IF($B7="","","UM-"&TEXT(ROW()-6,"0000")) | C7: =IFERROR(INDEX(DATA_PROPERTY_MASTER!$B:$B,MATCH($B7,DATA_PROPERTY_MASTER!$A:$A,0)),"") | M7: =IFERROR($G7*$K7,"") -> 0 | N7: =IFERROR(IF($L7>0,1-($K7/$L7),""),"") | V7: =IF($B7="","Blank",IF(OR($G7="",$K7=""),"Review","OK")) -> Blank
A8: =IF($B8="","","UM-"&TEXT(ROW()-6,"0000")) | C8: =IFERROR(INDEX(DATA_PROPERTY_MASTER!$B:$B,MATCH($B8,DATA_PROPERTY_MASTER!$A:$A,0)),"") | M8: =IFERROR($G8*$K8,"") -> 0 | N8: =IFERROR(IF($L8>0,1-($K8/$L8),""),"") | V8: =IF($B8="","Blank",IF(OR($G8="",$K8=""),"Review","OK")) -> Blank
A9: =IF($B9="","","UM-"&TEXT(ROW()-6,"0000")) | C9: =IFERROR(INDEX(DATA_PROPERTY_MASTER!$B:$B,MATCH($B9,DATA_PROPERTY_MASTER!$A:$A,0)),"") | M9: =IFERROR($G9*$K9,"") -> 0 | N9: =IFERROR(IF($L9>0,1-($K9/$L9),""),"") | V9: =IF($B9="","Blank",IF(OR($G9="",$K9=""),"Review","OK")) -> Blank
A10: =IF($B10="","","UM-"&TEXT(ROW()-6,"0000")) | C10: =IFERROR(INDEX(DATA_PROPERTY_MASTER!$B:$B,MATCH($B10,DATA_PROPERTY_MASTER!$A:$A,0)),"") | M10: =IFERROR($G10*$K10,"") -> 0 | N10: =IFERROR(IF($L10>0,1-($K10/$L10),""),"") | V10: =IF($B10="","Blank",IF(OR($G10="",$K10=""),"Review","OK")) -> Blank
A11: =IF($B11="","","UM-"&TEXT(ROW()-6,"0000")) | C11: =IFERROR(INDEX(DATA_PROPERTY_MASTER!$B:$B,MATCH($B11,DATA_PROPERTY_MASTER!$A:$A,0)),"") | M11: =IFERROR($G11*$K11,"") -> 0 | N11: =IFERROR(IF($L11>0,1-($K11/$L11),""),"") | V11: =IF($B11="","Blank",IF(OR($G11="",$K11=""),"Review","OK")) -> Blank
A12: =IF($B12="","","UM-"&TEXT(ROW()-6,"0000")) | C12: =IFERROR(INDEX(DATA_PROPERTY_MASTER!$B:$B,MATCH($B12,DATA_PROPERTY_MASTER!$A:$A,0)),"") | M12: =IFERROR($G12*$K12,"") -> 0 | N12: =IFERROR(IF($L12>0,1-($K12/$L12),""),"") | V12: =IF($B12="","Blank",IF(OR($G12="",$K12=""),"Review","OK")) -> Blank
A13: =IF($B13="","","UM-"&TEXT(ROW()-6,"0000")) | C13: =IFERROR(INDEX(DATA_PROPERTY_MASTER!$B:$B,MATCH($B13,DATA_PROPERTY_MASTER!$A:$A,0)),"") | M13: =IFERROR($G13*$K13,"") -> 0 | N13: =IFERROR(IF($L13>0,1-($K13/$L13),""),"") | V13: =IF($B13="","Blank",IF(OR($G13="",$K13=""),"Review","OK")) -> Blank
A14: =IF($B14="","","UM-"&TEXT(ROW()-6,"0000")) | C14: =IFERROR(INDEX(DATA_PROPERTY_MASTER!$B:$B,MATCH($B14,DATA_PROPERTY_MASTER!$A:$A,0)),"") | M14: =IFERROR($G14*$K14,"") -> 0 | N14: =IFERROR(IF($L14>0,1-($K14/$L14),""),"") | V14: =IF($B14="","Blank",IF(OR($G14="",$K14=""),"Review","OK")) -> Blank
A15: =IF($B15="","","UM-"&TEXT(ROW()-6,"0000")) | C15: =IFERROR(INDEX(DATA_PROPERTY_MASTER!$B:$B,MATCH($B15,DATA_PROPERTY_MASTER!$A:$A,0)),"") | M15: =IFERROR($G15*$K15,"") -> 0 | N15: =IFERROR(IF($L15>0,1-($K15/$L15),""),"") | V15: =IF($B15="","Blank",IF(OR($G15="",$K15=""),"Review","OK")) -> Blank
A16: =IF($B16="","","UM-"&TEXT(ROW()-6,"0000")) | C16: =IFERROR(INDEX(DATA_PROPERTY_MASTER!$B:$B,MATCH($B16,DATA_PROPERTY_MASTER!$A:$A,0)),"") | M16: =IFERROR($G16*$K16,"") -> 0 | N16: =IFERROR(IF($L16>0,1-($K16/$L16),""),"") | V16: =IF($B16="","Blank",IF(OR($G16="",$K16=""),"Review","OK")) -> Blank
A17: =IF($B17="","","UM-"&TEXT(ROW()-6,"0000")) | C17: =IFERROR(INDEX(DATA_PROPERTY_MASTER!$B:$B,MATCH($B17,DATA_PROPERTY_MASTER!$A:$A,0)),"") | M17: =IFERROR($G17*$K17,"") -> 0 | N17: =IFERROR(IF($L17>0,1-($K17/$L17),""),"") | V17: =IF($B17="","Blank",IF(OR($G17="",$K17=""),"Review","OK")) -> Blank
A18: =IF($B18="","","UM-"&TEXT(ROW()-6,"0000")) | C18: =IFERROR(INDEX(DATA_PROPERTY_MASTER!$B:$B,MATCH($B18,DATA_PROPERTY_MASTER!$A:$A,0)),"") | M18: =IFERROR($G18*$K18,"") -> 0 | N18: =IFERROR(IF($L18>0,1-($K18/$L18),""),"") | V18: =IF($B18="","Blank",IF(OR($G18="",$K18=""),"Review","OK")) -> Blank
... A206: =IF($B206="","","UM-"&TEXT(ROW()-6,"0000")) | C206: =IFERROR(INDEX(DATA_PROPERTY_MASTER!$B:$B,MATCH($B206,DATA_PROPERTY_MASTER!$A:$A,0)),"") | M206: =IFERROR($G206*$K206,"") -> 0 | N206: =IFERROR(IF($L206>0,1-($K206/$L206),""),"") | V206: =IF($B206="","Blank",IF(OR($G206="",$K206=""),"Review","OK")) -> Blank

Sheet DATA_RENT_ROLL
A1: DATA_RENT_ROLL — canonical rent-roll intake
A2: Purpose | B2: Captures either unit-level rent roll or summarized rent by unit group.
A3: Rule | B3: Optional/recommended canonical table; if unavailable, DATA_UNIT_MIX and operating revenue can still support the model.
A4: Input colour | B4: Blue cells are the only analyst / AI write zones. Black-font cells are live formulas and should not be overwritten.
A6: Record_ID | B6: Property_ID | C6: Property_Name | D6: Rent_Record_Level | E6: Unit_ID_or_Group | F6: Bedroom_Type | G6: Unit_Type | H6: Unit_Count | I6: Tenant_Status | J6: Vacancy_Status | K6: Current_Monthly_Rent | L6: Market_Monthly_Rent | M6: Subsidy_Amount | N6: Utility_Allowance | O6: Effective_Date | P6: Annual_Current_Rent | Q6: Annual_Market_Rent | R6: Below_Market_% | S6: Source_File_ID | T6: Source_Confidence | U6: Review_Status | V6: Notes | W6: Row_Status
A7: =IF($B7="","","RR-"&TEXT(ROW()-6,"0000")) | C7: =IFERROR(INDEX(DATA_PROPERTY_MASTER!$B:$B,MATCH($B7,DATA_PROPERTY_MASTER!$A:$A,0)),"") | P7: =IFERROR($H7*$K7*12,"") -> 0 | Q7: =IFERROR($H7*$L7*12,"") -> 0 | R7: =IFERROR(IF($L7>0,1-($K7/$L7),""),"") | W7: =IF($B7="","Blank",IF(OR($K7="",$H7=""),"Review","OK")) -> Blank
A8: =IF($B8="","","RR-"&TEXT(ROW()-6,"0000")) | C8: =IFERROR(INDEX(DATA_PROPERTY_MASTER!$B:$B,MATCH($B8,DATA_PROPERTY_MASTER!$A:$A,0)),"") | P8: =IFERROR($H8*$K8*12,"") -> 0 | Q8: =IFERROR($H8*$L8*12,"") -> 0 | R8: =IFERROR(IF($L8>0,1-($K8/$L8),""),"") | W8: =IF($B8="","Blank",IF(OR($K8="",$H8=""),"Review","OK")) -> Blank
A9: =IF($B9="","","RR-"&TEXT(ROW()-6,"0000")) | C9: =IFERROR(INDEX(DATA_PROPERTY_MASTER!$B:$B,MATCH($B9,DATA_PROPERTY_MASTER!$A:$A,0)),"") | P9: =IFERROR($H9*$K9*12,"") -> 0 | Q9: =IFERROR($H9*$L9*12,"") -> 0 | R9: =IFERROR(IF($L9>0,1-($K9/$L9),""),"") | W9: =IF($B9="","Blank",IF(OR($K9="",$H9=""),"Review","OK")) -> Blank
A10: =IF($B10="","","RR-"&TEXT(ROW()-6,"0000")) | C10: =IFERROR(INDEX(DATA_PROPERTY_MASTER!$B:$B,MATCH($B10,DATA_PROPERTY_MASTER!$A:$A,0)),"") | P10: =IFERROR($H10*$K10*12,"") -> 0 | Q10: =IFERROR($H10*$L10*12,"") -> 0 | R10: =IFERROR(IF($L10>0,1-($K10/$L10),""),"") | W10: =IF($B10="","Blank",IF(OR($K10="",$H10=""),"Review","OK")) -> Blank
A11: =IF($B11="","","RR-"&TEXT(ROW()-6,"0000")) | C11: =IFERROR(INDEX(DATA_PROPERTY_MASTER!$B:$B,MATCH($B11,DATA_PROPERTY_MASTER!$A:$A,0)),"") | P11: =IFERROR($H11*$K11*12,"") -> 0 | Q11: =IFERROR($H11*$L11*12,"") -> 0 | R11: =IFERROR(IF($L11>0,1-($K11/$L11),""),"") | W11: =IF($B11="","Blank",IF(OR($K11="",$H11=""),"Review","OK")) -> Blank
A12: =IF($B12="","","RR-"&TEXT(ROW()-6,"0000")) | C12: =IFERROR(INDEX(DATA_PROPERTY_MASTER!$B:$B,MATCH($B12,DATA_PROPERTY_MASTER!$A:$A,0)),"") | P12: =IFERROR($H12*$K12*12,"") -> 0 | Q12: =IFERROR($H12*$L12*12,"") -> 0 | R12: =IFERROR(IF($L12>0,1-($K12/$L12),""),"") | W12: =IF($B12="","Blank",IF(OR($K12="",$H12=""),"Review","OK")) -> Blank
A13: =IF($B13="","","RR-"&TEXT(ROW()-6,"0000")) | C13: =IFERROR(INDEX(DATA_PROPERTY_MASTER!$B:$B,MATCH($B13,DATA_PROPERTY_MASTER!$A:$A,0)),"") | P13: =IFERROR($H13*$K13*12,"") -> 0 | Q13: =IFERROR($H13*$L13*12,"") -> 0 | R13: =IFERROR(IF($L13>0,1-($K13/$L13),""),"") | W13: =IF($B13="","Blank",IF(OR($K13="",$H13=""),"Review","OK")) -> Blank
A14: =IF($B14="","","RR-"&TEXT(ROW()-6,"0000")) | C14: =IFERROR(INDEX(DATA_PROPERTY_MASTER!$B:$B,MATCH($B14,DATA_PROPERTY_MASTER!$A:$A,0)),"") | P14: =IFERROR($H14*$K14*12,"") -> 0 | Q14: =IFERROR($H14*$L14*12,"") -> 0 | R14: =IFERROR(IF($L14>0,1-($K14/$L14),""),"") | W14: =IF($B14="","Blank",IF(OR($K14="",$H14=""),"Review","OK")) -> Blank
A15: =IF($B15="","","RR-"&TEXT(ROW()-6,"0000")) | C15: =IFERROR(INDEX(DATA_PROPERTY_MASTER!$B:$B,MATCH($B15,DATA_PROPERTY_MASTER!$A:$A,0)),"") | P15: =IFERROR($H15*$K15*12,"") -> 0 | Q15: =IFERROR($H15*$L15*12,"") -> 0 | R15: =IFERROR(IF($L15>0,1-($K15/$L15),""),"") | W15: =IF($B15="","Blank",IF(OR($K15="",$H15=""),"Review","OK")) -> Blank
A16: =IF($B16="","","RR-"&TEXT(ROW()-6,"0000")) | C16: =IFERROR(INDEX(DATA_PROPERTY_MASTER!$B:$B,MATCH($B16,DATA_PROPERTY_MASTER!$A:$A,0)),"") | P16: =IFERROR($H16*$K16*12,"") -> 0 | Q16: =IFERROR($H16*$L16*12,"") -> 0 | R16: =IFERROR(IF($L16>0,1-($K16/$L16),""),"") | W16: =IF($B16="","Blank",IF(OR($K16="",$H16=""),"Review","OK")) -> Blank
A17: =IF($B17="","","RR-"&TEXT(ROW()-6,"0000")) | C17: =IFERROR(INDEX(DATA_PROPERTY_MASTER!$B:$B,MATCH($B17,DATA_PROPERTY_MASTER!$A:$A,0)),"") | P17: =IFERROR($H17*$K17*12,"") -> 0 | Q17: =IFERROR($H17*$L17*12,"") -> 0 | R17: =IFERROR(IF($L17>0,1-($K17/$L17),""),"") | W17: =IF($B17="","Blank",IF(OR($K17="",$H17=""),"Review","OK")) -> Blank
A18: =IF($B18="","","RR-"&TEXT(ROW()-6,"0000")) | C18: =IFERROR(INDEX(DATA_PROPERTY_MASTER!$B:$B,MATCH($B18,DATA_PROPERTY_MASTER!$A:$A,0)),"") | P18: =IFERROR($H18*$K18*12,"") -> 0 | Q18: =IFERROR($H18*$L18*12,"") -> 0 | R18: =IFERROR(IF($L18>0,1-($K18/$L18),""),"") | W18: =IF($B18="","Blank",IF(OR($K18="",$H18=""),"Review","OK")) -> Blank
... A206: =IF($B206="","","RR-"&TEXT(ROW()-6,"0000")) | C206: =IFERROR(INDEX(DATA_PROPERTY_MASTER!$B:$B,MATCH($B206,DATA_PROPERTY_MASTER!$A:$A,0)),"") | P206: =IFERROR($H206*$K206*12,"") -> 0 | Q206: =IFERROR($H206*$L206*12,"") -> 0 | R206: =IFERROR(IF($L206>0,1-($K206/$L206),""),"") | W206: =IF($B206="","Blank",IF(OR($K206="",$H206=""),"Review","OK")) -> Blank

Sheet DATA_OPERATING_ACTUALS
A1: DATA_OPERATING_ACTUALS — canonical operating actuals / budget / projection intake
A2: Purpose | B2: Long-format operating data by property, year, period, scenario, and standardized IREI category.
A3: Rule | B3: This is the future replacement path for 01_Base Yr. Inputs; v11 does not repoint the live engine yet.
A4: Input colour | B4: Blue cells are the only analyst / AI write zones. Black-font cells are live formulas and should not be overwritten.
A6: Record_ID | B6: Property_ID | C6: Property_Name | D6: Fiscal_Year | E6: Period | F6: Scenario | G6: Actual_Budget_Projection | H6: Source_Line_Item | I6: IREI_Category | J6: Amount | K6: Cash_or_Accrual | L6: Source_File_ID | M6: Source_Confidence | N6: Mapping_Confidence | O6: Review_Status | P6: Standardized_Key | Q6: Notes | R6: Row_Status
A7: =IF($B7="","","OA-"&TEXT(ROW()-6,"0000")) | C7: =IFERROR(INDEX(DATA_PROPERTY_MASTER!$B:$B,MATCH($B7,DATA_PROPERTY_MASTER!$A:$A,0)),"") | P7: =IF($B7="","",$B7&"|"&$D7&"|"&$F7&"|"&$I7) | R7: =IF($B7="","Blank",IF(OR($D7="",$I7="",$J7=""),"Review","OK")) -> Blank
A8: =IF($B8="","","OA-"&TEXT(ROW()-6,"0000")) | C8: =IFERROR(INDEX(DATA_PROPERTY_MASTER!$B:$B,MATCH($B8,DATA_PROPERTY_MASTER!$A:$A,0)),"") | P8: =IF($B8="","",$B8&"|"&$D8&"|"&$F8&"|"&$I8) | R8: =IF($B8="","Blank",IF(OR($D8="",$I8="",$J8=""),"Review","OK")) -> Blank
A9: =IF($B9="","","OA-"&TEXT(ROW()-6,"0000")) | C9: =IFERROR(INDEX(DATA_PROPERTY_MASTER!$B:$B,MATCH($B9,DATA_PROPERTY_MASTER!$A:$A,0)),"") | P9: =IF($B9="","",$B9&"|"&$D9&"|"&$F9&"|"&$I9) | R9: =IF($B9="","Blank",IF(OR($D9="",$I9="",$J9=""),"Review","OK")) -> Blank
A10: =IF($B10="","","OA-"&TEXT(ROW()-6,"0000")) | C10: =IFERROR(INDEX(DATA_PROPERTY_MASTER!$B:$B,MATCH($B10,DATA_PROPERTY_MASTER!$A:$A,0)),"") | P10: =IF($B10="","",$B10&"|"&$D10&"|"&$F10&"|"&$I10) | R10: =IF($B10="","Blank",IF(OR($D10="",$I10="",$J10=""),"Review","OK")) -> Blank
A11: =IF($B11="","","OA-"&TEXT(ROW()-6,"0000")) | C11: =IFERROR(INDEX(DATA_PROPERTY_MASTER!$B:$B,MATCH($B11,DATA_PROPERTY_MASTER!$A:$A,0)),"") | P11: =IF($B11="","",$B11&"|"&$D11&"|"&$F11&"|"&$I11) | R11: =IF($B11="","Blank",IF(OR($D11="",$I11="",$J11=""),"Review","OK")) -> Blank
A12: =IF($B12="","","OA-"&TEXT(ROW()-6,"0000")) | C12: =IFERROR(INDEX(DATA_PROPERTY_MASTER!$B:$B,MATCH($B12,DATA_PROPERTY_MASTER!$A:$A,0)),"") | P12: =IF($B12="","",$B12&"|"&$D12&"|"&$F12&"|"&$I12) | R12: =IF($B12="","Blank",IF(OR($D12="",$I12="",$J12=""),"Review","OK")) -> Blank
A13: =IF($B13="","","OA-"&TEXT(ROW()-6,"0000")) | C13: =IFERROR(INDEX(DATA_PROPERTY_MASTER!$B:$B,MATCH($B13,DATA_PROPERTY_MASTER!$A:$A,0)),"") | P13: =IF($B13="","",$B13&"|"&$D13&"|"&$F13&"|"&$I13) | R13: =IF($B13="","Blank",IF(OR($D13="",$I13="",$J13=""),"Review","OK")) -> Blank
A14: =IF($B14="","","OA-"&TEXT(ROW()-6,"0000")) | C14: =IFERROR(INDEX(DATA_PROPERTY_MASTER!$B:$B,MATCH($B14,DATA_PROPERTY_MASTER!$A:$A,0)),"") | P14: =IF($B14="","",$B14&"|"&$D14&"|"&$F14&"|"&$I14) | R14: =IF($B14="","Blank",IF(OR($D14="",$I14="",$J14=""),"Review","OK")) -> Blank
A15: =IF($B15="","","OA-"&TEXT(ROW()-6,"0000")) | C15: =IFERROR(INDEX(DATA_PROPERTY_MASTER!$B:$B,MATCH($B15,DATA_PROPERTY_MASTER!$A:$A,0)),"") | P15: =IF($B15="","",$B15&"|"&$D15&"|"&$F15&"|"&$I15) | R15: =IF($B15="","Blank",IF(OR($D15="",$I15="",$J15=""),"Review","OK")) -> Blank
A16: =IF($B16="","","OA-"&TEXT(ROW()-6,"0000")) | C16: =IFERROR(INDEX(DATA_PROPERTY_MASTER!$B:$B,MATCH($B16,DATA_PROPERTY_MASTER!$A:$A,0)),"") | P16: =IF($B16="","",$B16&"|"&$D16&"|"&$F16&"|"&$I16) | R16: =IF($B16="","Blank",IF(OR($D16="",$I16="",$J16=""),"Review","OK")) -> Blank
A17: =IF($B17="","","OA-"&TEXT(ROW()-6,"0000")) | C17: =IFERROR(INDEX(DATA_PROPERTY_MASTER!$B:$B,MATCH($B17,DATA_PROPERTY_MASTER!$A:$A,0)),"") | P17: =IF($B17="","",$B17&"|"&$D17&"|"&$F17&"|"&$I17) | R17: =IF($B17="","Blank",IF(OR($D17="",$I17="",$J17=""),"Review","OK")) -> Blank
A18: =IF($B18="","","OA-"&TEXT(ROW()-6,"0000")) | C18: =IFERROR(INDEX(DATA_PROPERTY_MASTER!$B:$B,MATCH($B18,DATA_PROPERTY_MASTER!$A:$A,0)),"") | P18: =IF($B18="","",$B18&"|"&$D18&"|"&$F18&"|"&$I18) | R18: =IF($B18="","Blank",IF(OR($D18="",$I18="",$J18=""),"Review","OK")) -> Blank
... A206: =IF($B206="","","OA-"&TEXT(ROW()-6,"0000")) | C206: =IFERROR(INDEX(DATA_PROPERTY_MASTER!$B:$B,MATCH($B206,DATA_PROPERTY_MASTER!$A:$A,0)),"") | P206: =IF($B206="","",$B206&"|"&$D206&"|"&$F206&"|"&$I206) | R206: =IF($B206="","Blank",IF(OR($D206="",$I206="",$J206=""),"Review","OK")) -> Blank

Sheet DATA_AGREEMENTS
A1: DATA_AGREEMENTS — canonical agreements / restrictions intake
A2: Purpose | B2: Captures operating agreements, covenants, affordability restrictions, subsidies, leases, and mission-protection constraints.
A3: Rule | B3: This is a key IREI table; v11 creates the evidence structure without repointing calculations.
A4: Input colour | B4: Blue cells are the only analyst / AI write zones. Black-font cells are live formulas and should not be overwritten.
A6: Agreement_ID | B6: Property_ID | C6: Property_Name | D6: Agreement_Type | E6: Counterparty | F6: Start_Date | G6: End_Date | H6: Affordability_Requirement | I6: Rent_Restriction | J6: Use_Restriction | K6: Refinance_Restriction | L6: Disposition_Restriction | M6: Subsidy_Linked | N6: Renewal_Risk | O6: Mission_Protection_Flag | P6: Source_File_ID | Q6: Source_Confidence | R6: Review_Status | S6: Agreement_Status | T6: Notes | U6: Row_Status
A7: =IF($B7="","","AGR-"&TEXT(ROW()-6,"0000")) | C7: =IFERROR(INDEX(DATA_PROPERTY_MASTER!$B:$B,MATCH($B7,DATA_PROPERTY_MASTER!$A:$A,0)),"") | S7: =IF($B7="","",IF($G7="","No end date",IF($G7<TODAY(),"Expired / Review","Active / Future"))) | U7: =IF($B7="","Blank",IF(OR($D7="",$H7=""),"Review","OK")) -> Blank
A8: =IF($B8="","","AGR-"&TEXT(ROW()-6,"0000")) | C8: =IFERROR(INDEX(DATA_PROPERTY_MASTER!$B:$B,MATCH($B8,DATA_PROPERTY_MASTER!$A:$A,0)),"") | S8: =IF($B8="","",IF($G8="","No end date",IF($G8<TODAY(),"Expired / Review","Active / Future"))) | U8: =IF($B8="","Blank",IF(OR($D8="",$H8=""),"Review","OK")) -> Blank
A9: =IF($B9="","","AGR-"&TEXT(ROW()-6,"0000")) | C9: =IFERROR(INDEX(DATA_PROPERTY_MASTER!$B:$B,MATCH($B9,DATA_PROPERTY_MASTER!$A:$A,0)),"") | S9: =IF($B9="","",IF($G9="","No end date",IF($G9<TODAY(),"Expired / Review","Active / Future"))) | U9: =IF($B9="","Blank",IF(OR($D9="",$H9=""),"Review","OK")) -> Blank
A10: =IF($B10="","","AGR-"&TEXT(ROW()-6,"0000")) | C10: =IFERROR(INDEX(DATA_PROPERTY_MASTER!$B:$B,MATCH($B10,DATA_PROPERTY_MASTER!$A:$A,0)),"") | S10: =IF($B10="","",IF($G10="","No end date",IF($G10<TODAY(),"Expired / Review","Active / Future"))) | U10: =IF($B10="","Blank",IF(OR($D10="",$H10=""),"Review","OK")) -> Blank
A11: =IF($B11="","","AGR-"&TEXT(ROW()-6,"0000")) | C11: =IFERROR(INDEX(DATA_PROPERTY_MASTER!$B:$B,MATCH($B11,DATA_PROPERTY_MASTER!$A:$A,0)),"") | S11: =IF($B11="","",IF($G11="","No end date",IF($G11<TODAY(),"Expired / Review","Active / Future"))) | U11: =IF($B11="","Blank",IF(OR($D11="",$H11=""),"Review","OK")) -> Blank
A12: =IF($B12="","","AGR-"&TEXT(ROW()-6,"0000")) | C12: =IFERROR(INDEX(DATA_PROPERTY_MASTER!$B:$B,MATCH($B12,DATA_PROPERTY_MASTER!$A:$A,0)),"") | S12: =IF($B12="","",IF($G12="","No end date",IF($G12<TODAY(),"Expired / Review","Active / Future"))) | U12: =IF($B12="","Blank",IF(OR($D12="",$H12=""),"Review","OK")) -> Blank
A13: =IF($B13="","","AGR-"&TEXT(ROW()-6,"0000")) | C13: =IFERROR(INDEX(DATA_PROPERTY_MASTER!$B:$B,MATCH($B13,DATA_PROPERTY_MASTER!$A:$A,0)),"") | S13: =IF($B13="","",IF($G13="","No end date",IF($G13<TODAY(),"Expired / Review","Active / Future"))) | U13: =IF($B13="","Blank",IF(OR($D13="",$H13=""),"Review","OK")) -> Blank
A14: =IF($B14="","","AGR-"&TEXT(ROW()-6,"0000")) | C14: =IFERROR(INDEX(DATA_PROPERTY_MASTER!$B:$B,MATCH($B14,DATA_PROPERTY_MASTER!$A:$A,0)),"") | S14: =IF($B14="","",IF($G14="","No end date",IF($G14<TODAY(),"Expired / Review","Active / Future"))) | U14: =IF($B14="","Blank",IF(OR($D14="",$H14=""),"Review","OK")) -> Blank
A15: =IF($B15="","","AGR-"&TEXT(ROW()-6,"0000")) | C15: =IFERROR(INDEX(DATA_PROPERTY_MASTER!$B:$B,MATCH($B15,DATA_PROPERTY_MASTER!$A:$A,0)),"") | S15: =IF($B15="","",IF($G15="","No end date",IF($G15<TODAY(),"Expired / Review","Active / Future"))) | U15: =IF($B15="","Blank",IF(OR($D15="",$H15=""),"Review","OK")) -> Blank
A16: =IF($B16="","","AGR-"&TEXT(ROW()-6,"0000")) | C16: =IFERROR(INDEX(DATA_PROPERTY_MASTER!$B:$B,MATCH($B16,DATA_PROPERTY_MASTER!$A:$A,0)),"") | S16: =IF($B16="","",IF($G16="","No end date",IF($G16<TODAY(),"Expired / Review","Active / Future"))) | U16: =IF($B16="","Blank",IF(OR($D16="",$H16=""),"Review","OK")) -> Blank
A17: =IF($B17="","","AGR-"&TEXT(ROW()-6,"0000")) | C17: =IFERROR(INDEX(DATA_PROPERTY_MASTER!$B:$B,MATCH($B17,DATA_PROPERTY_MASTER!$A:$A,0)),"") | S17: =IF($B17="","",IF($G17="","No end date",IF($G17<TODAY(),"Expired / Review","Active / Future"))) | U17: =IF($B17="","Blank",IF(OR($D17="",$H17=""),"Review","OK")) -> Blank
A18: =IF($B18="","","AGR-"&TEXT(ROW()-6,"0000")) | C18: =IFERROR(INDEX(DATA_PROPERTY_MASTER!$B:$B,MATCH($B18,DATA_PROPERTY_MASTER!$A:$A,0)),"") | S18: =IF($B18="","",IF($G18="","No end date",IF($G18<TODAY(),"Expired / Review","Active / Future"))) | U18: =IF($B18="","Blank",IF(OR($D18="",$H18=""),"Review","OK")) -> Blank
... A206: =IF($B206="","","AGR-"&TEXT(ROW()-6,"0000")) | C206: =IFERROR(INDEX(DATA_PROPERTY_MASTER!$B:$B,MATCH($B206,DATA_PROPERTY_MASTER!$A:$A,0)),"") | S206: =IF($B206="","",IF($G206="","No end date",IF($G206<TODAY(),"Expired / Review","Active / Future"))) | U206: =IF($B206="","Blank",IF(OR($D206="",$H206=""),"Review","OK")) -> Blank

Sheet DATA_CAPITAL_NEEDS
A1: DATA_CAPITAL_NEEDS — canonical capital needs / fixed-asset intake
A2: Purpose | B2: Captures repairs, replacements, deferred maintenance, redevelopment, fixed-asset additions, and funded/unfunded capital needs.
A3: Rule | B3: Created as canonical intake; future versions can feed DATA_CAPITAL_FLOW and capital planning outputs.
A4: Input colour | B4: Blue cells are the only analyst / AI write zones. Black-font cells are live formulas and should not be overwritten.
A6: Capital_Item_ID | B6: Property_ID | C6: Property_Name | D6: Capital_Item | E6: Capital_Category | F6: Required_or_Discretionary | G6: Year_Needed | H6: Estimated_Cost | I6: Funded_Amount | J6: Unfunded_Amount | K6: Funding_Source | L6: Deferred_Maintenance_Flag | M6: Development_Related | N6: Fixed_Asset_or_Depreciation_Link | O6: Source_File_ID | P6: Source_Confidence | Q6: Review_Status | R6: Funding_Gap_Flag | S6: Notes | T6: Row_Status
A7: =IF($B7="","","CN-"&TEXT(ROW()-6,"0000")) | C7: =IFERROR(INDEX(DATA_PROPERTY_MASTER!$B:$B,MATCH($B7,DATA_PROPERTY_MASTER!$A:$A,0)),"") | J7: =IFERROR(MAX($H7-$I7,0),"") -> 0 | R7: =IF($B7="","",IF($J7>0,"Funding Gap","Funded / No Gap")) | T7: =IF($B7="","Blank",IF(OR($D7="",$G7="",$H7=""),"Review","OK")) -> Blank
A8: =IF($B8="","","CN-"&TEXT(ROW()-6,"0000")) | C8: =IFERROR(INDEX(DATA_PROPERTY_MASTER!$B:$B,MATCH($B8,DATA_PROPERTY_MASTER!$A:$A,0)),"") | J8: =IFERROR(MAX($H8-$I8,0),"") -> 0 | R8: =IF($B8="","",IF($J8>0,"Funding Gap","Funded / No Gap")) | T8: =IF($B8="","Blank",IF(OR($D8="",$G8="",$H8=""),"Review","OK")) -> Blank
A9: =IF($B9="","","CN-"&TEXT(ROW()-6,"0000")) | C9: =IFERROR(INDEX(DATA_PROPERTY_MASTER!$B:$B,MATCH($B9,DATA_PROPERTY_MASTER!$A:$A,0)),"") | J9: =IFERROR(MAX($H9-$I9,0),"") -> 0 | R9: =IF($B9="","",IF($J9>0,"Funding Gap","Funded / No Gap")) | T9: =IF($B9="","Blank",IF(OR($D9="",$G9="",$H9=""),"Review","OK")) -> Blank
A10: =IF($B10="","","CN-"&TEXT(ROW()-6,"0000")) | C10: =IFERROR(INDEX(DATA_PROPERTY_MASTER!$B:$B,MATCH($B10,DATA_PROPERTY_MASTER!$A:$A,0)),"") | J10: =IFERROR(MAX($H10-$I10,0),"") -> 0 | R10: =IF($B10="","",IF($J10>0,"Funding Gap","Funded / No Gap")) | T10: =IF($B10="","Blank",IF(OR($D10="",$G10="",$H10=""),"Review","OK")) -> Blank
A11: =IF($B11="","","CN-"&TEXT(ROW()-6,"0000")) | C11: =IFERROR(INDEX(DATA_PROPERTY_MASTER!$B:$B,MATCH($B11,DATA_PROPERTY_MASTER!$A:$A,0)),"") | J11: =IFERROR(MAX($H11-$I11,0),"") -> 0 | R11: =IF($B11="","",IF($J11>0,"Funding Gap","Funded / No Gap")) | T11: =IF($B11="","Blank",IF(OR($D11="",$G11="",$H11=""),"Review","OK")) -> Blank
A12: =IF($B12="","","CN-"&TEXT(ROW()-6,"0000")) | C12: =IFERROR(INDEX(DATA_PROPERTY_MASTER!$B:$B,MATCH($B12,DATA_PROPERTY_MASTER!$A:$A,0)),"") | J12: =IFERROR(MAX($H12-$I12,0),"") -> 0 | R12: =IF($B12="","",IF($J12>0,"Funding Gap","Funded / No Gap")) | T12: =IF($B12="","Blank",IF(OR($D12="",$G12="",$H12=""),"Review","OK")) -> Blank
A13: =IF($B13="","","CN-"&TEXT(ROW()-6,"0000")) | C13: =IFERROR(INDEX(DATA_PROPERTY_MASTER!$B:$B,MATCH($B13,DATA_PROPERTY_MASTER!$A:$A,0)),"") | J13: =IFERROR(MAX($H13-$I13,0),"") -> 0 | R13: =IF($B13="","",IF($J13>0,"Funding Gap","Funded / No Gap")) | T13: =IF($B13="","Blank",IF(OR($D13="",$G13="",$H13=""),"Review","OK")) -> Blank
A14: =IF($B14="","","CN-"&TEXT(ROW()-6,"0000")) | C14: =IFERROR(INDEX(DATA_PROPERTY_MASTER!$B:$B,MATCH($B14,DATA_PROPERTY_MASTER!$A:$A,0)),"") | J14: =IFERROR(MAX($H14-$I14,0),"") -> 0 | R14: =IF($B14="","",IF($J14>0,"Funding Gap","Funded / No Gap")) | T14: =IF($B14="","Blank",IF(OR($D14="",$G14="",$H14=""),"Review","OK")) -> Blank
A15: =IF($B15="","","CN-"&TEXT(ROW()-6,"0000")) | C15: =IFERROR(INDEX(DATA_PROPERTY_MASTER!$B:$B,MATCH($B15,DATA_PROPERTY_MASTER!$A:$A,0)),"") | J15: =IFERROR(MAX($H15-$I15,0),"") -> 0 | R15: =IF($B15="","",IF($J15>0,"Funding Gap","Funded / No Gap")) | T15: =IF($B15="","Blank",IF(OR($D15="",$G15="",$H15=""),"Review","OK")) -> Blank
A16: =IF($B16="","","CN-"&TEXT(ROW()-6,"0000")) | C16: =IFERROR(INDEX(DATA_PROPERTY_MASTER!$B:$B,MATCH($B16,DATA_PROPERTY_MASTER!$A:$A,0)),"") | J16: =IFERROR(MAX($H16-$I16,0),"") -> 0 | R16: =IF($B16="","",IF($J16>0,"Funding Gap","Funded / No Gap")) | T16: =IF($B16="","Blank",IF(OR($D16="",$G16="",$H16=""),"Review","OK")) -> Blank
A17: =IF($B17="","","CN-"&TEXT(ROW()-6,"0000")) | C17: =IFERROR(INDEX(DATA_PROPERTY_MASTER!$B:$B,MATCH($B17,DATA_PROPERTY_MASTER!$A:$A,0)),"") | J17: =IFERROR(MAX($H17-$I17,0),"") -> 0 | R17: =IF($B17="","",IF($J17>0,"Funding Gap","Funded / No Gap")) | T17: =IF($B17="","Blank",IF(OR($D17="",$G17="",$H17=""),"Review","OK")) -> Blank
A18: =IF($B18="","","CN-"&TEXT(ROW()-6,"0000")) | C18: =IFERROR(INDEX(DATA_PROPERTY_MASTER!$B:$B,MATCH($B18,DATA_PROPERTY_MASTER!$A:$A,0)),"") | J18: =IFERROR(MAX($H18-$I18,0),"") -> 0 | R18: =IF($B18="","",IF($J18>0,"Funding Gap","Funded / No Gap")) | T18: =IF($B18="","Blank",IF(OR($D18="",$G18="",$H18=""),"Review","OK")) -> Blank
... A206: =IF($B206="","","CN-"&TEXT(ROW()-6,"0000")) | C206: =IFERROR(INDEX(DATA_PROPERTY_MASTER!$B:$B,MATCH($B206,DATA_PROPERTY_MASTER!$A:$A,0)),"") | J206: =IFERROR(MAX($H206-$I206,0),"") -> 0 | R206: =IF($B206="","",IF($J206>0,"Funding Gap","Funded / No Gap")) | T206: =IF($B206="","Blank",IF(OR($D206="",$G206="",$H206=""),"Review","OK")) -> Blank

Sheet 01_Property Summary
B2: PROPERTY SUMMARY (2026) — RAW DATA (USER-TOGGLE)
B3: Property | I3: Ownership / Operating Agreements | L3: Mortgage | S3: Unit Count
B4: Tab ID | C4: Property | D4: Address | E4: City | F4: Start Yr. (Current Yr. if Active) | G4: Status | I4: Lease Type | J4: Lease Expiry | K4: Operating Agreement Expiry | L4: Mortgage | M4: Interest Rate | N4: Term Date (Month/Yr.) | O4: Amortizing Years | P4: Annual Mortgage Payment | Q4: Annual Mortgage Subsidy | R4: Mortgage Balance Outstanding 2025 | S4: Total Units | T4: Studios | U4: 1 Bedroom | V4: 2 Bedroom | W4: 3 Bedroom | X4: 4 Bedroom
B5: BLD_AB | C5: Alma Blackwell | D5: 1656 Adanac Street | E5: Vancouver | F5: 2025 | G5: Active | I5: Owned | J5: N/A | K5: 2027 | L5: N/A | S5: 46 | T5: 0 | U5: 6 | V5: 24 | W5: 14 | X5: 2
B6: BLD_AC | C6: Antkiw Court | D6: 1534 E. 4th Avenue | E6: Vancouver | F6: 2025 | G6: Active | I6: Owned | J6: N/A | K6: 2028 | L6: BCHMC/NPAT | M6: 0.04024 | N6: 49461 | O6: 22 | P6: 54330.12 | Q6: 54330.12 | R6: 794745.17 | S6: 21 | T6: 0 | U6: 0 | V6: 13 | W6: 6 | X6: 2
B7: BLD_BT | C7: Beatrice Terrace | D7: 1877 E. Georgia Street | E7: Vancouver | F7: 2025 | G7: Active | I7: Owned | J7: N/A | K7: 2028 | L7: BCHMC/NPAT | M7: 0.04024 | N7: 49491 | O7: 22 | P7: 110563.68 | Q7: 110563.68 | R7: 1617334.9 | S7: 18 | T7: 0 | U7: 0 | V7: 9 | W7: 9 | X7: 0
B8: BLD_CH | C8: Capilano House | D8: 1551 Bridgman Avenue | E8: DNV | F8: 2025 | G8: Active | I8: DNV | J8: 2048 | K8: 2027 | L8: N/A | S8: 64 | T8: 63 | U8: 1 | V8: 0 | W8: 0 | X8: 0
B9: BLD_CC | C9: Constance Court | D9: 2518 E. Hastings Street | E9: Vancouver | F9: 2025 | G9: Active | I9: Vancity | J9: 2032 | K9: 2027 | L9: BCHMC | M9: 0.0423 | N9: 46419 | O9: 3 | P9: 178507.8 | Q9: 178507.8 | R9: 274036.81 | S9: 34 | T9: 0 | U9: 18 | V9: 14 | W9: 2 | X9: 0
B10: BLD_EA | C10: Evergreen Apartments | D10: 815 5th Avenue | E10: New Westminster | F10: 2025 | G10: Active | I10: Owned | J10: N/A | K10: N/A | L10: Vancity | M10: 0.0421 | N10: 48976 | O10: 35 | P10: 297840 | Q10: 0 | R10: 5475821.3 | S10: 61 | T10: 3 | U10: 48 | V10: 7 | W10: 3 | X10: 0
B11: BLD_EE | C11: Evelyn Estates | D11: 9155 136A Street | E11: Surrey | F11: 2025 | G11: Active | I11: Owned | J11: N/A | K11: 2028 | L11: BCHMC | M11: 0.0374 | N11: 46844 | O11: 4 | P11: 244376.04 | Q11: 0 | R11: 639949.69 | S11: 36 | T11: 0 | U11: 0 | V11: 18 | W11: 14 | X11: 4
B12: BLD_JP | C12: Jessica Place | D12: 9883 140th Street | E12: Surrey | F12: 2025 | G12: Active | I12: Owned | J12: N/A | K12: 2026 | L12: BCHMC | M12: 0.0101 | N12: 46143 | O12: 4 | P12: 176698.83 | Q12: 0 | R12: 176698.83 | S12: 40 | T12: 0 | U12: 0 | V12: 17 | W12: 17 | X12: 6
B13: BLD_MH | C13: Margaret Heights | D13: 1800 Rufus Drive | E13: CNV | F13: 2025 | G13: Active | I13: CNV | J13: 2046 | K13: 2026 | L13: BCHMC | M13: 0.0101 | N13: 46266 | O13: 5 | P13: 125540.52 | Q13: 0 | R13: 145670.52 | S13: 19 | T13: 0 | U13: 0 | V13: 10 | W13: 5 | X13: 4
B14: BLD_MM | C14: Murray Manor | D14: 6435 Royal Oak Avenue | E14: Burnaby | F14: 2025 | G14: Active | I14: Owned | J14: N/A | K14: N/A | L14: Vancity | M14: 0.0421 | N14: 48976 | O14: 35 | P14: 271563.84 | Q14: 0 | R14: 4992966 | S14: 47 | T14: 6 | U14: 28 | V14: 13 | W14: 0 | X14: 0
B15: BLD_NT | C15: Natalia Terrace | D15: 3550 S.E. Marine Drive | E15: Vancouver | F15: 2025 | G15: Active | I15: Vancity | J15: 2051 | K15: 2027 | L15: BCHMC | M15: 0.0424 | N15: 46508 | O15: 3 | P15: 274351.8 | Q15: 0 | R15: 485006.87 | S15: 40 | T15: 0 | U15: 0 | V15: 24 | W15: 12 | X15: 4
B16: BLD_NG | C16: Newton Green | D16: 12725 63rd Avenue | E16: Surrey | F16: 2025 | G16: Active | I16: BCH | J16: 2058 | K16: 2026 | L16: CMLS | M16: 0.04465 | N16: 49096 | O16: 9 | P16: 443187 | Q16: 0 | R16: 3432387.1 | S16: 49 | T16: 0 | U16: 0 | V16: 22 | W16: 25 | X16: 2
B17: BLD_RG | C17: Rosemary Green | D17: 2880 152nd Street | E17: Surrey | F17: 2025 | G17: Active | I17: Surrey | J17: 2054 | K17: 2054 | L17: Peoples Group | M17: 0.024 | N17: 46143 | O17: 10 | P17: 291146.28 | Q17: 0 | R17: 1976761.2 | S17: 38 | T17: 0 | U17: 0 | V17: 18 | W17: 16 | X17: 4
B18: BLD_AS | C18: 1656 Adanac Street | D18: 1656 Adanac Street | E18: Vancouver | F18: 2028 | G18: New Dev | I18: Owned | J18: 2058 | K18: 2058 | L18: BCH CHF | S18: 97 | T18: 6 | U18: 42 | V18: 33 | W18: 14 | X18: 2
B19: BLD_PS | C19: 450 Pacific Street | D19: 450 Pacific Street | E19: Vancouver | F19: 2028 | G19: New Dev | I19: Owned | J19: 2058 | K19: 2058 | L19: BCH CHF | S19: 91 | T19: 32 | U19: 25 | V19: 23 | W19: 11 | X19: 0
B20: BLD_PM | C20: The Creek, Port Moody | D20: 300 Angela Drive | E20: Port Moody | F20: 2027 | G20: New Dev | I20: Owned | J20: 2057 | K20: 2057 | L20: CMHC | S20: 328 | T20: 0 | U20: 72 | V20: 140 | W20: 116 | X20: 0
B21: BLD_CD | C21: 800 Commercial Drive | D21: 800 Commercial Drive | E21: Vancouver | F21: 2029 | G21: New Dev | I21: Owned | J21: 2059 | K21: 2059 | L21: BCH CHF | S21: 93 | T21: 26 | U21: 29 | V21: 26 | W21: 12 | X21: 0
B23: Notes:
B24: Source: shared by NGO B operator.
B31: Property
B32: Tab ID | C32: Property | D32: Address | E32: City | F32: Start Yr. (Current Yr. if Active) | G32: Status | I32: 2025 | J32: 2026 | K32: 2027 | L32: 2028 | M32: 2029 | N32: 2030 | O32: 2031 | P32: 2032 | Q32: 2033 | R32: 2034 | S32: 2035 | T32: 2036 | U32: 2037 | V32: 2038 | W32: 2039 | X32: 2040 | Y32: 2041 | Z32: 2042 | AA32: 2043 | AB32: 2044 | AC32: 2045
B33: BLD_AB | C33: Alma Blackwell | D33: 1656 Adanac Street | E33: Vancouver | F33: 2025 | G33: Active | I33: =INDEX(BLD_AB!$E$41:$Y$41,MATCH(I$32,BLD_AB!$E$12:$Y$12,0)) -> 436078.4 | J33: =INDEX(BLD_AB!$E$41:$Y$41,MATCH(J$32,BLD_AB!$E$12:$Y$12,0)) -> 441788.59 | K33: =INDEX(BLD_AB!$E$41:$Y$41,MATCH(K$32,BLD_AB!$E$12:$Y$12,0)) -> 608477.74 | L33: =INDEX(BLD_AB!$E$41:$Y$41,MATCH(L$32,BLD_AB!$E$12:$Y$12,0)) -> 617390.19 | M33: =INDEX(BLD_AB!$E$41:$Y$41,MATCH(M$32,BLD_AB!$E$12:$Y$12,0)) -> 626350.6 | N33: =INDEX(BLD_AB!$E$41:$Y$41,MATCH(N$32,BLD_AB!$E$12:$Y$12,0)) -> 635354.73 | O33: =INDEX(BLD_AB!$E$41:$Y$41,MATCH(O$32,BLD_AB!$E$12:$Y$12,0)) -> 644398.02 | P33: =INDEX(BLD_AB!$E$41:$Y$41,MATCH(P$32,BLD_AB!$E$12:$Y$12,0)) -> 653475.62 | ... AC33: =INDEX(BLD_AB!$E$41:$Y$41,MATCH(AC$32,BLD_AB!$E$12:$Y$12,0)) -> 820464.84
B34: BLD_AC | C34: Antkiw Court | D34: 1534 E. 4th Avenue | E34: Vancouver | F34: 2025 | G34: Active | I34: =INDEX(BLD_AC!$E$41:$Y$41,MATCH(I$32,BLD_AC!$E$12:$Y$12,0)) -> 172856.48 | J34: =INDEX(BLD_AC!$E$41:$Y$41,MATCH(J$32,BLD_AC!$E$12:$Y$12,0)) -> 172215.63 | K34: =INDEX(BLD_AC!$E$41:$Y$41,MATCH(K$32,BLD_AC!$E$12:$Y$12,0)) -> 171441.5 | L34: =INDEX(BLD_AC!$E$41:$Y$41,MATCH(L$32,BLD_AC!$E$12:$Y$12,0)) -> 245496.04 | M34: =INDEX(BLD_AC!$E$41:$Y$41,MATCH(M$32,BLD_AC!$E$12:$Y$12,0)) -> 245931.96 | N34: =INDEX(BLD_AC!$E$41:$Y$41,MATCH(N$32,BLD_AC!$E$12:$Y$12,0)) -> 246241.11 | O34: =INDEX(BLD_AC!$E$41:$Y$41,MATCH(O$32,BLD_AC!$E$12:$Y$12,0)) -> 246415.53 | P34: =INDEX(BLD_AC!$E$41:$Y$41,MATCH(P$32,BLD_AC!$E$12:$Y$12,0)) -> 246446.88 | ... AC34: =INDEX(BLD_AC!$E$41:$Y$41,MATCH(AC$32,BLD_AC!$E$12:$Y$12,0)) -> 223647.95
B35: BLD_BT | C35: Beatrice Terrace | D35: 1877 E. Georgia Street | E35: Vancouver | F35: 2025 | G35: Active | I35: =INDEX(BLD_BT!$E$41:$Y$41,MATCH(I$32,BLD_BT!$E$12:$Y$12,0)) -> 259166.84 | J35: =INDEX(BLD_BT!$E$41:$Y$41,MATCH(J$32,BLD_BT!$E$12:$Y$12,0)) -> 259732.11 | K35: =INDEX(BLD_BT!$E$41:$Y$41,MATCH(K$32,BLD_BT!$E$12:$Y$12,0)) -> 260212.4 | L35: =INDEX(BLD_BT!$E$41:$Y$41,MATCH(L$32,BLD_BT!$E$12:$Y$12,0)) -> 320850.32 | M35: =INDEX(BLD_BT!$E$41:$Y$41,MATCH(M$32,BLD_BT!$E$12:$Y$12,0)) -> 322348.73 | N35: =INDEX(BLD_BT!$E$41:$Y$41,MATCH(N$32,BLD_BT!$E$12:$Y$12,0)) -> 323768.81 | O35: =INDEX(BLD_BT!$E$41:$Y$41,MATCH(O$32,BLD_BT!$E$12:$Y$12,0)) -> 325104.68 | P35: =INDEX(BLD_BT!$E$41:$Y$41,MATCH(P$32,BLD_BT!$E$12:$Y$12,0)) -> 326350.13 | ... AC35: =INDEX(BLD_BT!$E$41:$Y$41,MATCH(AC$32,BLD_BT!$E$12:$Y$12,0)) -> 259261.36
B36: BLD_CH | C36: Capilano House | D36: 1551 Bridgman Avenue | E36: DNV | F36: 2025 | G36: Active | I36: =INDEX(BLD_CH!$E$41:$Y$41,MATCH(I$32,BLD_CH!$E$12:$Y$12,0)) -> 225686.19 | J36: =INDEX(BLD_CH!$E$41:$Y$41,MATCH(J$32,BLD_CH!$E$12:$Y$12,0)) -> 220425.04 | K36: =INDEX(BLD_CH!$E$41:$Y$41,MATCH(K$32,BLD_CH!$E$12:$Y$12,0)) -> 475975.22 | L36: =INDEX(BLD_CH!$E$41:$Y$41,MATCH(L$32,BLD_CH!$E$12:$Y$12,0)) -> 474922.22 | M36: =INDEX(BLD_CH!$E$41:$Y$41,MATCH(M$32,BLD_CH!$E$12:$Y$12,0)) -> 473425.25 | N36: =INDEX(BLD_CH!$E$41:$Y$41,MATCH(N$32,BLD_CH!$E$12:$Y$12,0)) -> 471458.53 | O36: =INDEX(BLD_CH!$E$41:$Y$41,MATCH(O$32,BLD_CH!$E$12:$Y$12,0)) -> 468995.07 | P36: =INDEX(BLD_CH!$E$41:$Y$41,MATCH(P$32,BLD_CH!$E$12:$Y$12,0)) -> 466006.62 | ... AC36: =INDEX(BLD_CH!$E$41:$Y$41,MATCH(AC$32,BLD_CH!$E$12:$Y$12,0)) -> 522083.69
B37: BLD_CC | C37: Constance Court | D37: 2518 E. Hastings Street | E37: Vancouver | F37: 2025 | G37: Active | I37: =INDEX(BLD_CC!$E$41:$Y$41,MATCH(I$32,BLD_CC!$E$12:$Y$12,0)) -> 343316.33 | J37: =INDEX(BLD_CC!$E$41:$Y$41,MATCH(J$32,BLD_CC!$E$12:$Y$12,0)) -> 342478.44 | K37: =INDEX(BLD_CC!$E$41:$Y$41,MATCH(K$32,BLD_CC!$E$12:$Y$12,0)) -> 467983.07 | L37: =INDEX(BLD_CC!$E$41:$Y$41,MATCH(L$32,BLD_CC!$E$12:$Y$12,0)) -> 290793.38 | M37: =INDEX(BLD_CC!$E$41:$Y$41,MATCH(M$32,BLD_CC!$E$12:$Y$12,0)) -> 291958.99 | N37: =INDEX(BLD_CC!$E$41:$Y$41,MATCH(N$32,BLD_CC!$E$12:$Y$12,0)) -> 292961.9 | O37: =INDEX(BLD_CC!$E$41:$Y$41,MATCH(O$32,BLD_CC!$E$12:$Y$12,0)) -> 293791.43 | P37: =INDEX(BLD_CC!$E$41:$Y$41,MATCH(P$32,BLD_CC!$E$12:$Y$12,0)) -> 294436.35 | ... AC37: =INDEX(BLD_CC!$E$41:$Y$41,MATCH(AC$32,BLD_CC!$E$12:$Y$12,0)) -> 346735.34
B38: BLD_EA | C38: Evergreen Apartments | D38: 815 5th Avenue | E38: New Westminster | F38: 2025 | G38: Active | I38: =INDEX(BLD_EA!$E$41:$Y$41,MATCH(I$32,BLD_EA!$E$12:$Y$12,0)) -> 579873.69 | J38: =INDEX(BLD_EA!$E$41:$Y$41,MATCH(J$32,BLD_EA!$E$12:$Y$12,0)) -> 583200.51 | K38: =INDEX(BLD_EA!$E$41:$Y$41,MATCH(K$32,BLD_EA!$E$12:$Y$12,0)) -> 586263.03 | L38: =INDEX(BLD_EA!$E$41:$Y$41,MATCH(L$32,BLD_EA!$E$12:$Y$12,0)) -> 589042.75 | M38: =INDEX(BLD_EA!$E$41:$Y$41,MATCH(M$32,BLD_EA!$E$12:$Y$12,0)) -> 591520.23 | N38: =INDEX(BLD_EA!$E$41:$Y$41,MATCH(N$32,BLD_EA!$E$12:$Y$12,0)) -> 593675.14 | O38: =INDEX(BLD_EA!$E$41:$Y$41,MATCH(O$32,BLD_EA!$E$12:$Y$12,0)) -> 595486.12 | P38: =INDEX(BLD_EA!$E$41:$Y$41,MATCH(P$32,BLD_EA!$E$12:$Y$12,0)) -> 596930.82 | ... AC38: =INDEX(BLD_EA!$E$41:$Y$41,MATCH(AC$32,BLD_EA!$E$12:$Y$12,0)) -> 703873.72
B39: BLD_EE | C39: Evelyn Estates | D39: 9155 136A Street | E39: Surrey | F39: 2025 | G39: Active | I39: =INDEX(BLD_EE!$E$41:$Y$41,MATCH(I$32,BLD_EE!$E$12:$Y$12,0)) -> 207537.01 | J39: =INDEX(BLD_EE!$E$41:$Y$41,MATCH(J$32,BLD_EE!$E$12:$Y$12,0)) -> 207348.17 | K39: =INDEX(BLD_EE!$E$41:$Y$41,MATCH(K$32,BLD_EE!$E$12:$Y$12,0)) -> 206981.97 | L39: =INDEX(BLD_EE!$E$41:$Y$41,MATCH(L$32,BLD_EE!$E$12:$Y$12,0)) -> 289501.41 | M39: =INDEX(BLD_EE!$E$41:$Y$41,MATCH(M$32,BLD_EE!$E$12:$Y$12,0)) -> 290410 | N39: =INDEX(BLD_EE!$E$41:$Y$41,MATCH(N$32,BLD_EE!$E$12:$Y$12,0)) -> 291141.51 | O39: =INDEX(BLD_EE!$E$41:$Y$41,MATCH(O$32,BLD_EE!$E$12:$Y$12,0)) -> 291684.57 | P39: =INDEX(BLD_EE!$E$41:$Y$41,MATCH(P$32,BLD_EE!$E$12:$Y$12,0)) -> 292027.31 | ... AC39: =INDEX(BLD_EE!$E$41:$Y$41,MATCH(AC$32,BLD_EE!$E$12:$Y$12,0)) -> 341921.29
B40: BLD_JP | C40: Jessica Place | D40: 9883 140th Street | E40: Surrey | F40: 2025 | G40: Active | I40: =INDEX(BLD_JP!$E$41:$Y$41,MATCH(I$32,BLD_JP!$E$12:$Y$12,0)) -> 141364.12 | J40: =INDEX(BLD_JP!$E$41:$Y$41,MATCH(J$32,BLD_JP!$E$12:$Y$12,0)) -> 236702.4 | K40: =INDEX(BLD_JP!$E$41:$Y$41,MATCH(K$32,BLD_JP!$E$12:$Y$12,0)) -> 236138.76 | L40: =INDEX(BLD_JP!$E$41:$Y$41,MATCH(L$32,BLD_JP!$E$12:$Y$12,0)) -> 235351.92 | M40: =INDEX(BLD_JP!$E$41:$Y$41,MATCH(M$32,BLD_JP!$E$12:$Y$12,0)) -> 234328.97 | N40: =INDEX(BLD_JP!$E$41:$Y$41,MATCH(N$32,BLD_JP!$E$12:$Y$12,0)) -> 233056.36 | O40: =INDEX(BLD_JP!$E$41:$Y$41,MATCH(O$32,BLD_JP!$E$12:$Y$12,0)) -> 231519.93 | P40: =INDEX(BLD_JP!$E$41:$Y$41,MATCH(P$32,BLD_JP!$E$12:$Y$12,0)) -> 229704.87 | ... AC40: =INDEX(BLD_JP!$E$41:$Y$41,MATCH(AC$32,BLD_JP!$E$12:$Y$12,0)) -> 255069.16
B41: BLD_MH | C41: Margaret Heights | D41: 1800 Rufus Drive | E41: CNV | F41: 2025 | G41: Active | I41: =INDEX(BLD_MH!$E$41:$Y$41,MATCH(I$32,BLD_MH!$E$12:$Y$12,0)) -> 146321.51 | J41: =INDEX(BLD_MH!$E$41:$Y$41,MATCH(J$32,BLD_MH!$E$12:$Y$12,0)) -> 210980.64 | K41: =INDEX(BLD_MH!$E$41:$Y$41,MATCH(K$32,BLD_MH!$E$12:$Y$12,0)) -> 211367.32 | L41: =INDEX(BLD_MH!$E$41:$Y$41,MATCH(L$32,BLD_MH!$E$12:$Y$12,0)) -> 211608.4 | M41: =INDEX(BLD_MH!$E$41:$Y$41,MATCH(M$32,BLD_MH!$E$12:$Y$12,0)) -> 211694.86 | N41: =INDEX(BLD_MH!$E$41:$Y$41,MATCH(N$32,BLD_MH!$E$12:$Y$12,0)) -> 211617.22 | O41: =INDEX(BLD_MH!$E$41:$Y$41,MATCH(O$32,BLD_MH!$E$12:$Y$12,0)) -> 211365.57 | P41: =INDEX(BLD_MH!$E$41:$Y$41,MATCH(P$32,BLD_MH!$E$12:$Y$12,0)) -> 210929.52 | ... AC41: =INDEX(BLD_MH!$E$41:$Y$41,MATCH(AC$32,BLD_MH!$E$12:$Y$12,0)) -> 242415.52
B42: BLD_MM | C42: Murray Manor | D42: 6435 Royal Oak Avenue | E42: Burnaby | F42: 2025 | G42: Active | I42: =INDEX(BLD_MM!$E$41:$Y$41,MATCH(I$32,BLD_MM!$E$12:$Y$12,0)) -> 502606.51 | J42: =INDEX(BLD_MM!$E$41:$Y$41,MATCH(J$32,BLD_MM!$E$12:$Y$12,0)) -> 507090.76 | K42: =INDEX(BLD_MM!$E$41:$Y$41,MATCH(K$32,BLD_MM!$E$12:$Y$12,0)) -> 511441.98 | L42: =INDEX(BLD_MM!$E$41:$Y$41,MATCH(L$32,BLD_MM!$E$12:$Y$12,0)) -> 515648.61 | M42: =INDEX(BLD_MM!$E$41:$Y$41,MATCH(M$32,BLD_MM!$E$12:$Y$12,0)) -> 519698.47 | N42: =INDEX(BLD_MM!$E$41:$Y$41,MATCH(N$32,BLD_MM!$E$12:$Y$12,0)) -> 523578.81 | O42: =INDEX(BLD_MM!$E$41:$Y$41,MATCH(O$32,BLD_MM!$E$12:$Y$12,0)) -> 527276.21 | P42: =INDEX(BLD_MM!$E$41:$Y$41,MATCH(P$32,BLD_MM!$E$12:$Y$12,0)) -> 530776.59 | ... AC42: =INDEX(BLD_MM!$E$41:$Y$41,MATCH(AC$32,BLD_MM!$E$12:$Y$12,0)) -> 640622.54
B43: BLD_NT | C43: Natalia Terrace | D43: 3550 S.E. Marine Drive | E43: Vancouver | F43: 2025 | G43: Active | I43: =INDEX(BLD_NT!$E$41:$Y$41,MATCH(I$32,BLD_NT!$E$12:$Y$12,0)) -> 310204.72 | J43: =INDEX(BLD_NT!$E$41:$Y$41,MATCH(J$32,BLD_NT!$E$12:$Y$12,0)) -> 310630.17 | K43: =INDEX(BLD_NT!$E$41:$Y$41,MATCH(K$32,BLD_NT!$E$12:$Y$12,0)) -> 440733.09 | L43: =INDEX(BLD_NT!$E$41:$Y$41,MATCH(L$32,BLD_NT!$E$12:$Y$12,0)) -> 443297.58 | M43: =INDEX(BLD_NT!$E$41:$Y$41,MATCH(M$32,BLD_NT!$E$12:$Y$12,0)) -> 445663.34 | N43: =INDEX(BLD_NT!$E$41:$Y$41,MATCH(N$32,BLD_NT!$E$12:$Y$12,0)) -> 447816.42 | O43: =INDEX(BLD_NT!$E$41:$Y$41,MATCH(O$32,BLD_NT!$E$12:$Y$12,0)) -> 449742.15 | P43: =INDEX(BLD_NT!$E$41:$Y$41,MATCH(P$32,BLD_NT!$E$12:$Y$12,0)) -> 451425.17 | ... AC43: =INDEX(BLD_NT!$E$41:$Y$41,MATCH(AC$32,BLD_NT!$E$12:$Y$12,0)) -> 536232.03
B44: BLD_NG | C44: Newton Green | D44: 12725 63rd Avenue | E44: Surrey | F44: 2025 | G44: Active | I44: =INDEX(BLD_NG!$E$41:$Y$41,MATCH(I$32,BLD_NG!$E$12:$Y$12,0)) -> 371605.62 | J44: =INDEX(BLD_NG!$E$41:$Y$41,MATCH(J$32,BLD_NG!$E$12:$Y$12,0)) -> 469146.47 | K44: =INDEX(BLD_NG!$E$41:$Y$41,MATCH(K$32,BLD_NG!$E$12:$Y$12,0)) -> 472064.11 | L44: =INDEX(BLD_NG!$E$41:$Y$41,MATCH(L$32,BLD_NG!$E$12:$Y$12,0)) -> 474781.5 | M44: =INDEX(BLD_NG!$E$41:$Y$41,MATCH(M$32,BLD_NG!$E$12:$Y$12,0)) -> 477284.28 | N44: =INDEX(BLD_NG!$E$41:$Y$41,MATCH(N$32,BLD_NG!$E$12:$Y$12,0)) -> 479557.4 | O44: =INDEX(BLD_NG!$E$41:$Y$41,MATCH(O$32,BLD_NG!$E$12:$Y$12,0)) -> 481585.08 | P44: =INDEX(BLD_NG!$E$41:$Y$41,MATCH(P$32,BLD_NG!$E$12:$Y$12,0)) -> 483350.77 | ... AC44: =INDEX(BLD_NG!$E$41:$Y$41,MATCH(AC$32,BLD_NG!$E$12:$Y$12,0)) -> 573913.26
B45: BLD_RG | C45: Rosemary Green | D45: 2880 152nd Street | E45: Surrey | F45: 2025 | G45: Active | I45: =INDEX(BLD_RG!$E$41:$Y$41,MATCH(I$32,BLD_RG!$E$12:$Y$12,0)) -> 233508.56 | J45: =INDEX(BLD_RG!$E$41:$Y$41,MATCH(J$32,BLD_RG!$E$12:$Y$12,0)) -> 233866.98 | K45: =INDEX(BLD_RG!$E$41:$Y$41,MATCH(K$32,BLD_RG!$E$12:$Y$12,0)) -> 234060.08 | L45: =INDEX(BLD_RG!$E$41:$Y$41,MATCH(L$32,BLD_RG!$E$12:$Y$12,0)) -> 234077.69 | M45: =INDEX(BLD_RG!$E$41:$Y$41,MATCH(M$32,BLD_RG!$E$12:$Y$12,0)) -> 233909.1 | N45: =INDEX(BLD_RG!$E$41:$Y$41,MATCH(N$32,BLD_RG!$E$12:$Y$12,0)) -> 233543.13 | O45: =INDEX(BLD_RG!$E$41:$Y$41,MATCH(O$32,BLD_RG!$E$12:$Y$12,0)) -> 232968.08 | P45: =INDEX(BLD_RG!$E$41:$Y$41,MATCH(P$32,BLD_RG!$E$12:$Y$12,0)) -> 232171.69 | ... AC45: =INDEX(BLD_RG!$E$41:$Y$41,MATCH(AC$32,BLD_RG!$E$12:$Y$12,0)) -> 264721.46
B46: BLD_AS | C46: 1656 Adanac Street | D46: 1656 Adanac Street | E46: Vancouver | F46: 2028 | G46: New Dev | I46: =INDEX(BLD_AS!$E$41:$Y$41,MATCH(I$32,BLD_AS!$E$12:$Y$12,0)) -> 0 | J46: =INDEX(BLD_AS!$E$41:$Y$41,MATCH(J$32,BLD_AS!$E$12:$Y$12,0)) -> 0 | K46: =INDEX(BLD_AS!$E$41:$Y$41,MATCH(K$32,BLD_AS!$E$12:$Y$12,0)) -> 0 | L46: =INDEX(BLD_AS!$E$41:$Y$41,MATCH(L$32,BLD_AS!$E$12:$Y$12,0)) -> 1213031.4 | M46: =INDEX(BLD_AS!$E$41:$Y$41,MATCH(M$32,BLD_AS!$E$12:$Y$12,0)) -> 1220832.7 | N46: =INDEX(BLD_AS!$E$41:$Y$41,MATCH(N$32,BLD_AS!$E$12:$Y$12,0)) -> 1228131.7 | O46: =INDEX(BLD_AS!$E$41:$Y$41,MATCH(O$32,BLD_AS!$E$12:$Y$12,0)) -> 1234891.9 | P46: =INDEX(BLD_AS!$E$41:$Y$41,MATCH(P$32,BLD_AS!$E$12:$Y$12,0)) -> 1241075.3 | ... AC46: =INDEX(BLD_AS!$E$41:$Y$41,MATCH(AC$32,BLD_AS!$E$12:$Y$12,0)) -> 1484593
B47: BLD_PS | C47: 450 Pacific Street | D47: 450 Pacific Street | E47: Vancouver | F47: 2028 | G47: New Dev | I47: =INDEX(BLD_PS!$E$41:$Y$41,MATCH(I$32,BLD_PS!$E$12:$Y$12,0)) -> 0 | J47: =INDEX(BLD_PS!$E$41:$Y$41,MATCH(J$32,BLD_PS!$E$12:$Y$12,0)) -> 0 | K47: =INDEX(BLD_PS!$E$41:$Y$41,MATCH(K$32,BLD_PS!$E$12:$Y$12,0)) -> 0 | L47: =INDEX(BLD_PS!$E$41:$Y$41,MATCH(L$32,BLD_PS!$E$12:$Y$12,0)) -> 1004966.2 | M47: =INDEX(BLD_PS!$E$41:$Y$41,MATCH(M$32,BLD_PS!$E$12:$Y$12,0)) -> 1009635.7 | N47: =INDEX(BLD_PS!$E$41:$Y$41,MATCH(N$32,BLD_PS!$E$12:$Y$12,0)) -> 1013781.4 | O47: =INDEX(BLD_PS!$E$41:$Y$41,MATCH(O$32,BLD_PS!$E$12:$Y$12,0)) -> 1017368.2 | P47: =INDEX(BLD_PS!$E$41:$Y$41,MATCH(P$32,BLD_PS!$E$12:$Y$12,0)) -> 1020359.1 | ... AC47: =INDEX(BLD_PS!$E$41:$Y$41,MATCH(AC$32,BLD_PS!$E$12:$Y$12,0)) -> 1206633.4
B48: BLD_PM | C48: The Creek, Port Moody | D48: 300 Angela Drive | E48: Port Moody | F48: 2027 | G48: New Dev | I48: =INDEX(BLD_PM!$E$41:$Y$41,MATCH(I$32,BLD_PM!$E$12:$Y$12,0)) -> 0 | J48: =INDEX(BLD_PM!$E$41:$Y$41,MATCH(J$32,BLD_PM!$E$12:$Y$12,0)) -> 0 | K48: =INDEX(BLD_PM!$E$41:$Y$41,MATCH(K$32,BLD_PM!$E$12:$Y$12,0)) -> 4693091.2 | L48: =INDEX(BLD_PM!$E$41:$Y$41,MATCH(L$32,BLD_PM!$E$12:$Y$12,0)) -> 4783137.2 | M48: =INDEX(BLD_PM!$E$41:$Y$41,MATCH(M$32,BLD_PM!$E$12:$Y$12,0)) -> 4874831.4 | N48: =INDEX(BLD_PM!$E$41:$Y$41,MATCH(N$32,BLD_PM!$E$12:$Y$12,0)) -> 4968200.8 | O48: =INDEX(BLD_PM!$E$41:$Y$41,MATCH(O$32,BLD_PM!$E$12:$Y$12,0)) -> 5063272.4 | P48: =INDEX(BLD_PM!$E$41:$Y$41,MATCH(P$32,BLD_PM!$E$12:$Y$12,0)) -> 5160073.8 | ... AC48: =INDEX(BLD_PM!$E$41:$Y$41,MATCH(AC$32,BLD_PM!$E$12:$Y$12,0)) -> 6645962.6
B49: BLD_CD | C49: 800 Commercial Drive | D49: 800 Commercial Drive | E49: Vancouver | F49: 2029 | G49: New Dev | I49: =INDEX(BLD_CD!$E$41:$Y$41,MATCH(I$32,BLD_CD!$E$12:$Y$12,0)) -> 0 | J49: =INDEX(BLD_CD!$E$41:$Y$41,MATCH(J$32,BLD_CD!$E$12:$Y$12,0)) -> 0 | K49: =INDEX(BLD_CD!$E$41:$Y$41,MATCH(K$32,BLD_CD!$E$12:$Y$12,0)) -> 0 | L49: =INDEX(BLD_CD!$E$41:$Y$41,MATCH(L$32,BLD_CD!$E$12:$Y$12,0)) -> 0 | M49: =INDEX(BLD_CD!$E$41:$Y$41,MATCH(M$32,BLD_CD!$E$12:$Y$12,0)) -> 1474873.8 | N49: =INDEX(BLD_CD!$E$41:$Y$41,MATCH(N$32,BLD_CD!$E$12:$Y$12,0)) -> 1489667.3 | O49: =INDEX(BLD_CD!$E$41:$Y$41,MATCH(O$32,BLD_CD!$E$12:$Y$12,0)) -> 1504168.6 | P49: =INDEX(BLD_CD!$E$41:$Y$41,MATCH(P$32,BLD_CD!$E$12:$Y$12,0)) -> 1518348.2 | ... AC49: =INDEX(BLD_CD!$E$41:$Y$41,MATCH(AC$32,BLD_CD!$E$12:$Y$12,0)) -> 1860319

Sheet 01_Base Yr. Inputs
B2: BASE YEAR INPUTS (2026) — RAW DATA (USER-TOGGLE)
B3: Line Item / Property | C3: Alma Blackwell | D3: Antkiw Court | E3: Beatrice Terrace | F3: Capilano House | G3: Constance Court | H3: Evergreen Apartments | I3: Evelyn Estates | J3: Jessica Place | K3: Margaret Heights | L3: Murray Manor | M3: Natalia Terrace | N3: Newton Green | O3: Rosemary Green | P3: 1656 Adanac Street | Q3: 450 Pacific Street | R3: The Creek, Port Moody | S3: 800 Commercial Drive
B4: REVENUE
B5: Rent Income | C5: 438228 | D5: 200000 | E5: 210000 | F5: 450000 | G5: 250000 | H5: 894501 | I5: 350000 | J5: 300000 | K5: 240000 | L5: 683452 | M5: 480000 | N5: 600000 | O5: 370000 | P5: 1636062 | Q5: 1399704 | R5: 3800872.3 | S5: 1812384
B6: Laundry Revenue | C6: 2500 | D6: 2500 | E6: 6500 | F6: 3000 | G6: 5000 | H6: 5000 | I6: 3300 | J6: 5000 | K6: 2500 | L6: 9270 | M6: 3000 | N6: 0 | O6: 4000 | P6: 18960 | Q6: 18960 | R6: 0 | S6: 15360
B7: Cable Income | C7: 0 | D7: 0 | E7: 0 | F7: 0 | G7: 0 | H7: 0 | I7: 0 | J7: 0 | K7: 0 | L7: 100 | M7: 0 | N7: 0 | O7: 0 | P7: 0 | Q7: 0 | R7: 0 | S7: 0
B8: Locker Income | C8: 0 | D8: 0 | E8: 0 | F8: 0 | G8: 0 | H8: 110 | I8: 0 | J8: 0 | K8: 0 | L8: 520 | M8: 0 | N8: 0 | O8: 0 | P8: 0 | Q8: 0 | R8: 50979 | S8: 23112
B9: Parking Revenue | C9: 0 | D9: 0 | E9: 0 | F9: 0 | G9: 0 | H9: 2805 | I9: 0 | J9: 1500 | K9: 0 | L9: 9440 | M9: 960 | N9: 0 | O9: 0 | P9: 19380 | Q9: 11220 | R9: 103527 | S9: 6000
B10: Other Revenue | C10: 0 | D10: 0 | E10: 0 | F10: 19724 | G10: 0 | H10: 0 | I10: 0 | J10: 0 | K10: 29400 | L10: 0 | M10: 0 | N10: 0 | O10: 0 | P10: 21570 | Q10: 19200 | R10: 0 | S10: 0
B11: OPERATING EXPENSES
B12: Cleaning & Janitorial | C12: 21500 | D12: 21500 | E12: 13530 | F12: 30000 | G12: 20100 | H12: 39361 | I12: 25340 | J12: 34000 | K12: 21000 | L12: 28118 | M12: 26400 | N12: 32250 | O12: 22282 | P12: 85200 | Q12: 84600 | R12: 0 | S12: 57351
B13: Cable, Internet & Telephone | C13: 1250 | D13: 1250 | E13: 1250 | F13: 32250 | G13: 1250 | H13: 1250 | I13: 1250 | J13: 725 | K13: 1800 | L13: 3632 | M13: 1250 | N13: 1800 | O13: 1250 | P13: 12000 | Q13: 12000 | R13: 0 | S13: 6000
B14: Maintenance Staff | C14: 24445 | D14: 24445 | E14: 22800 | F14: 58150 | G14: 38650 | H14: 43500 | I14: 38000 | J14: 40100 | K14: 35680 | L14: 20000 | M14: 39200 | N14: 45214 | O14: 20185 | P14: 85000 | Q14: 85000 | R14: 0 | S14: 72125
B15: Grounds & Exterior Maint. | C15: 4810 | D15: 4810 | E15: 6360 | F15: 24500 | G15: 200 | H15: 15360 | I15: 14600 | J15: 15400 | K15: 28650 | L15: 13204 | M15: 27000 | N15: 30000 | O15: 16400 | P15: 80000 | Q15: 39996 | R15: 0 | S15: 28428
B16: Repairs & Maintenance | C16: 25000 | D16: 25000 | E16: 19000 | F16: 40000 | G16: 24000 | H16: 74914 | I16: 33000 | J16: 33000 | K16: 21550 | L16: 36541 | M16: 45000 | N16: 47000 | O16: 26000 | P16: 40000 | Q16: 129996 | R16: 0 | S16: 118451
B17: Mechanical Systems & Contracts | C17: 10000 | D17: 10000 | E17: 10000 | F17: 25000 | G17: 12000 | H17: 9635 | I17: 10000 | J17: 10000 | K17: 12000 | L17: 11907 | M17: 25000 | N17: 15000 | O17: 10000 | P17: 100000 | Q17: 120000 | R17: 0 | S17: 47381
B18: Tenant Turnover & Misc. | C18: 0 | D18: 0 | E18: 0 | F18: 0 | G18: 0 | H18: 1325 | I18: 0 | J18: 0 | K18: 0 | L18: 3103 | M18: 0 | N18: 0 | O18: 0 | P18: 0 | Q18: 0 | R18: 0 | S18: 0
B19: Hydro — Gas | C19: 8610 | D19: 8610 | E19: 5336 | F19: 30324 | G19: 7500 | H19: 52462 | I19: 800 | J19: 0 | K19: 2835 | L19: 30479 | M19: 0 | N19: 1155 | O19: 845 | P19: 0 | Q19: 0 | R19: 0 | S19: 0
B20: Hydro — Electric | C20: 6200 | D20: 6200 | E20: 5336 | F20: 31446 | G20: 11000 | H20: 7777 | I20: 4000 | J20: 6300 | K20: 2835 | L20: 4851 | M20: 14037 | N20: 4200 | O20: 5616 | P20: 60000 | Q20: 0 | R20: 0 | S20: 60000
B21: Utilities — Water & Sewer | C21: 15160 | D21: 15160 | E21: 14850 | F21: 96600 | G21: 17000 | H21: 88700 | I21: 32987 | J21: 43797 | K21: 17342 | L21: 34566 | M21: 29400 | N21: 45150 | O21: 41635 | P21: 50000 | Q21: 50004 | R21: 0 | S21: 28428
B22: Property Insurance | C22: 32208 | D22: 32208 | E22: 20605 | F22: 96954 | G22: 40970 | H22: 42432 | I22: 55729 | J22: 55651 | K22: 28484 | L22: 43660 | M22: 64215 | N22: 70162 | O22: 55651 | P22: 125040 | Q22: 101760 | R22: 0 | S22: 125000
B23: Property Taxes | C23: 1386 | D23: 1386 | E23: 1273 | F23: 23520 | G23: 34033 | H23: 36817 | I23: 1273 | J23: 15724 | K23: 12100 | L23: 48333 | M23: 17430 | N23: 18900 | O23: 15724 | P23: 94374 | Q23: 62496 | R23: 176400 | S23: 85285
B25: Notes:
B26: Source: shared by NGO B operator.
B27: Property cash flow models reference operating expenses directly from this sheet.
B28: All inputs are annualized figures.

Sheet 02_Rent Engine
B2: RENT ENGINE (2026)
B3: RENT ASSUMPTIONS — UNIT MIX & BLENDED WEIGHTED AVERAGE RENT | G3: 100% Affordable | I3: Blended | L3: Market Rents
B4: Property Name | C4: City | D4: Start Yr. (Current Yr. if Active) | E4: Total Units | F4: Base Yr. Rent Income (Source) | G4: Implied Rent/Unit/Yr. | H4: Implied Rent/Unit/Mo. | I4: Market Rent/Unit/Yr. | J4: Market Rent/Unit/Mo. | L4: City | M4: Market Rent/Mo.
B5: {=_xlfn.UNIQUE('01_Property Summary'!$C$5:$C$21)} -> Alma Blackwell | C5: =INDEX('01_Property Summary'!$E$5:$E$21,MATCH('02_Rent Engine'!$B5,'01_Property Summary'!$C$5:$C$21,0)) -> Vancouver | D5: =INDEX('01_Property Summary'!$F$5:$F$21,MATCH('02_Rent Engine'!$B5,'01_Property Summary'!$C$5:$C$21,0)) -> 2025 | E5: =INDEX('01_Property Summary'!$S$5:$S$21,MATCH('02_Rent Engine'!$B5,'01_Property Summary'!$C$5:$C$21,0)) -> 46 | F5: =INDEX('01_Base Yr. Inputs'!$5:$5,MATCH('02_Rent Engine'!$B5,'01_Base Yr. Inputs'!$3:$3,0)) -> 438228 | G5: =F5/E5 -> 9526.6957 | H5: =G5/12 -> 793.8913 | I5: =J5*12*E5 -> 2017146 | J5: =INDEX($M$5:$M$11,MATCH($C5,_xlfn.ANCHORARRAY($L$5),0)) -> 3654.25 | L5: {=_xlfn.UNIQUE($C$5:$C$21)} -> Vancouver | M5: 3654.25
B6: Antkiw Court | C6: =INDEX('01_Property Summary'!$E$5:$E$21,MATCH('02_Rent Engine'!$B6,'01_Property Summary'!$C$5:$C$21,0)) -> Vancouver | D6: =INDEX('01_Property Summary'!$F$5:$F$21,MATCH('02_Rent Engine'!$B6,'01_Property Summary'!$C$5:$C$21,0)) -> 2025 | E6: =INDEX('01_Property Summary'!$S$5:$S$21,MATCH('02_Rent Engine'!$B6,'01_Property Summary'!$C$5:$C$21,0)) -> 21 | F6: =INDEX('01_Base Yr. Inputs'!$5:$5,MATCH('02_Rent Engine'!$B6,'01_Base Yr. Inputs'!$3:$3,0)) -> 200000 | G6: =F6/E6 -> 9523.8095 | H6: =G6/12 -> 793.65079 | I6: =J6*12*E6 -> 920871 | J6: =INDEX($M$5:$M$11,MATCH($C6,_xlfn.ANCHORARRAY($L$5),0)) -> 3654.25 | L6: DNV | M6: 3923
B7: Beatrice Terrace | C7: =INDEX('01_Property Summary'!$E$5:$E$21,MATCH('02_Rent Engine'!$B7,'01_Property Summary'!$C$5:$C$21,0)) -> Vancouver | D7: =INDEX('01_Property Summary'!$F$5:$F$21,MATCH('02_Rent Engine'!$B7,'01_Property Summary'!$C$5:$C$21,0)) -> 2025 | E7: =INDEX('01_Property Summary'!$S$5:$S$21,MATCH('02_Rent Engine'!$B7,'01_Property Summary'!$C$5:$C$21,0)) -> 18 | F7: =INDEX('01_Base Yr. Inputs'!$5:$5,MATCH('02_Rent Engine'!$B7,'01_Base Yr. Inputs'!$3:$3,0)) -> 210000 | G7: =F7/E7 -> 11666.667 | H7: =G7/12 -> 972.22222 | I7: =J7*12*E7 -> 789318 | J7: =INDEX($M$5:$M$11,MATCH($C7,_xlfn.ANCHORARRAY($L$5),0)) -> 3654.25 | L7: New Westminster | M7: 2742
B8: Capilano House | C8: =INDEX('01_Property Summary'!$E$5:$E$21,MATCH('02_Rent Engine'!$B8,'01_Property Summary'!$C$5:$C$21,0)) -> DNV | D8: =INDEX('01_Property Summary'!$F$5:$F$21,MATCH('02_Rent Engine'!$B8,'01_Property Summary'!$C$5:$C$21,0)) -> 2025 | E8: =INDEX('01_Property Summary'!$S$5:$S$21,MATCH('02_Rent Engine'!$B8,'01_Property Summary'!$C$5:$C$21,0)) -> 64 | F8: =INDEX('01_Base Yr. Inputs'!$5:$5,MATCH('02_Rent Engine'!$B8,'01_Base Yr. Inputs'!$3:$3,0)) -> 450000 | G8: =F8/E8 -> 7031.25 | H8: =G8/12 -> 585.9375 | I8: =J8*12*E8 -> 3012864 | J8: =INDEX($M$5:$M$11,MATCH($C8,_xlfn.ANCHORARRAY($L$5),0)) -> 3923 | L8: Surrey | M8: 2659.25
B9: Constance Court | C9: =INDEX('01_Property Summary'!$E$5:$E$21,MATCH('02_Rent Engine'!$B9,'01_Property Summary'!$C$5:$C$21,0)) -> Vancouver | D9: =INDEX('01_Property Summary'!$F$5:$F$21,MATCH('02_Rent Engine'!$B9,'01_Property Summary'!$C$5:$C$21,0)) -> 2025 | E9: =INDEX('01_Property Summary'!$S$5:$S$21,MATCH('02_Rent Engine'!$B9,'01_Property Summary'!$C$5:$C$21,0)) -> 34 | F9: =INDEX('01_Base Yr. Inputs'!$5:$5,MATCH('02_Rent Engine'!$B9,'01_Base Yr. Inputs'!$3:$3,0)) -> 250000 | G9: =F9/E9 -> 7352.9412 | H9: =G9/12 -> 612.7451 | I9: =J9*12*E9 -> 1490934 | J9: =INDEX($M$5:$M$11,MATCH($C9,_xlfn.ANCHORARRAY($L$5),0)) -> 3654.25 | L9: CNV | M9: 3923
B10: Evergreen Apartments | C10: =INDEX('01_Property Summary'!$E$5:$E$21,MATCH('02_Rent Engine'!$B10,'01_Property Summary'!$C$5:$C$21,0)) -> New Westminster | D10: =INDEX('01_Property Summary'!$F$5:$F$21,MATCH('02_Rent Engine'!$B10,'01_Property Summary'!$C$5:$C$21,0)) -> 2025 | E10: =INDEX('01_Property Summary'!$S$5:$S$21,MATCH('02_Rent Engine'!$B10,'01_Property Summary'!$C$5:$C$21,0)) -> 61 | F10: =INDEX('01_Base Yr. Inputs'!$5:$5,MATCH('02_Rent Engine'!$B10,'01_Base Yr. Inputs'!$3:$3,0)) -> 894501 | G10: =F10/E10 -> 14663.951 | H10: =G10/12 -> 1221.9959 | I10: =J10*12*E10 -> 2007144 | J10: =INDEX($M$5:$M$11,MATCH($C10,_xlfn.ANCHORARRAY($L$5),0)) -> 2742 | L10: Burnaby | M10: 2881.25
B11: Evelyn Estates | C11: =INDEX('01_Property Summary'!$E$5:$E$21,MATCH('02_Rent Engine'!$B11,'01_Property Summary'!$C$5:$C$21,0)) -> Surrey | D11: =INDEX('01_Property Summary'!$F$5:$F$21,MATCH('02_Rent Engine'!$B11,'01_Property Summary'!$C$5:$C$21,0)) -> 2025 | E11: =INDEX('01_Property Summary'!$S$5:$S$21,MATCH('02_Rent Engine'!$B11,'01_Property Summary'!$C$5:$C$21,0)) -> 36 | F11: =INDEX('01_Base Yr. Inputs'!$5:$5,MATCH('02_Rent Engine'!$B11,'01_Base Yr. Inputs'!$3:$3,0)) -> 350000 | G11: =F11/E11 -> 9722.2222 | H11: =G11/12 -> 810.18519 | I11: =J11*12*E11 -> 1148796 | J11: =INDEX($M$5:$M$11,MATCH($C11,_xlfn.ANCHORARRAY($L$5),0)) -> 2659.25 | L11: Port Moody | M11: 3086.25
B12: Jessica Place | C12: =INDEX('01_Property Summary'!$E$5:$E$21,MATCH('02_Rent Engine'!$B12,'01_Property Summary'!$C$5:$C$21,0)) -> Surrey | D12: =INDEX('01_Property Summary'!$F$5:$F$21,MATCH('02_Rent Engine'!$B12,'01_Property Summary'!$C$5:$C$21,0)) -> 2025 | E12: =INDEX('01_Property Summary'!$S$5:$S$21,MATCH('02_Rent Engine'!$B12,'01_Property Summary'!$C$5:$C$21,0)) -> 40 | F12: =INDEX('01_Base Yr. Inputs'!$5:$5,MATCH('02_Rent Engine'!$B12,'01_Base Yr. Inputs'!$3:$3,0)) -> 300000 | G12: =F12/E12 -> 7500 | H12: =G12/12 -> 625 | I12: =J12*12*E12 -> 1276440 | J12: =INDEX($M$5:$M$11,MATCH($C12,_xlfn.ANCHORARRAY($L$5),0)) -> 2659.25
B13: Margaret Heights | C13: =INDEX('01_Property Summary'!$E$5:$E$21,MATCH('02_Rent Engine'!$B13,'01_Property Summary'!$C$5:$C$21,0)) -> CNV | D13: =INDEX('01_Property Summary'!$F$5:$F$21,MATCH('02_Rent Engine'!$B13,'01_Property Summary'!$C$5:$C$21,0)) -> 2025 | E13: =INDEX('01_Property Summary'!$S$5:$S$21,MATCH('02_Rent Engine'!$B13,'01_Property Summary'!$C$5:$C$21,0)) -> 19 | F13: =INDEX('01_Base Yr. Inputs'!$5:$5,MATCH('02_Rent Engine'!$B13,'01_Base Yr. Inputs'!$3:$3,0)) -> 240000 | G13: =F13/E13 -> 12631.579 | H13: =G13/12 -> 1052.6316 | I13: =J13*12*E13 -> 894444 | J13: =INDEX($M$5:$M$11,MATCH($C13,_xlfn.ANCHORARRAY($L$5),0)) -> 3923
B14: Murray Manor | C14: =INDEX('01_Property Summary'!$E$5:$E$21,MATCH('02_Rent Engine'!$B14,'01_Property Summary'!$C$5:$C$21,0)) -> Burnaby | D14: =INDEX('01_Property Summary'!$F$5:$F$21,MATCH('02_Rent Engine'!$B14,'01_Property Summary'!$C$5:$C$21,0)) -> 2025 | E14: =INDEX('01_Property Summary'!$S$5:$S$21,MATCH('02_Rent Engine'!$B14,'01_Property Summary'!$C$5:$C$21,0)) -> 47 | F14: =INDEX('01_Base Yr. Inputs'!$5:$5,MATCH('02_Rent Engine'!$B14,'01_Base Yr. Inputs'!$3:$3,0)) -> 683452 | G14: =F14/E14 -> 14541.532 | H14: =G14/12 -> 1211.7943 | I14: =J14*12*E14 -> 1625025 | J14: =INDEX($M$5:$M$11,MATCH($C14,_xlfn.ANCHORARRAY($L$5),0)) -> 2881.25
B15: Natalia Terrace | C15: =INDEX('01_Property Summary'!$E$5:$E$21,MATCH('02_Rent Engine'!$B15,'01_Property Summary'!$C$5:$C$21,0)) -> Vancouver | D15: =INDEX('01_Property Summary'!$F$5:$F$21,MATCH('02_Rent Engine'!$B15,'01_Property Summary'!$C$5:$C$21,0)) -> 2025 | E15: =INDEX('01_Property Summary'!$S$5:$S$21,MATCH('02_Rent Engine'!$B15,'01_Property Summary'!$C$5:$C$21,0)) -> 40 | F15: =INDEX('01_Base Yr. Inputs'!$5:$5,MATCH('02_Rent Engine'!$B15,'01_Base Yr. Inputs'!$3:$3,0)) -> 480000 | G15: =F15/E15 -> 12000 | H15: =G15/12 -> 1000 | I15: =J15*12*E15 -> 1754040 | J15: =INDEX($M$5:$M$11,MATCH($C15,_xlfn.ANCHORARRAY($L$5),0)) -> 3654.25
B16: Newton Green | C16: =INDEX('01_Property Summary'!$E$5:$E$21,MATCH('02_Rent Engine'!$B16,'01_Property Summary'!$C$5:$C$21,0)) -> Surrey | D16: =INDEX('01_Property Summary'!$F$5:$F$21,MATCH('02_Rent Engine'!$B16,'01_Property Summary'!$C$5:$C$21,0)) -> 2025 | E16: =INDEX('01_Property Summary'!$S$5:$S$21,MATCH('02_Rent Engine'!$B16,'01_Property Summary'!$C$5:$C$21,0)) -> 49 | F16: =INDEX('01_Base Yr. Inputs'!$5:$5,MATCH('02_Rent Engine'!$B16,'01_Base Yr. Inputs'!$3:$3,0)) -> 600000 | G16: =F16/E16 -> 12244.898 | H16: =G16/12 -> 1020.4082 | I16: =J16*12*E16 -> 1563639 | J16: =INDEX($M$5:$M$11,MATCH($C16,_xlfn.ANCHORARRAY($L$5),0)) -> 2659.25
B17: Rosemary Green | C17: =INDEX('01_Property Summary'!$E$5:$E$21,MATCH('02_Rent Engine'!$B17,'01_Property Summary'!$C$5:$C$21,0)) -> Surrey | D17: =INDEX('01_Property Summary'!$F$5:$F$21,MATCH('02_Rent Engine'!$B17,'01_Property Summary'!$C$5:$C$21,0)) -> 2025 | E17: =INDEX('01_Property Summary'!$S$5:$S$21,MATCH('02_Rent Engine'!$B17,'01_Property Summary'!$C$5:$C$21,0)) -> 38 | F17: =INDEX('01_Base Yr. Inputs'!$5:$5,MATCH('02_Rent Engine'!$B17,'01_Base Yr. Inputs'!$3:$3,0)) -> 370000 | G17: =F17/E17 -> 9736.8421 | H17: =G17/12 -> 811.40351 | I17: =J17*12*E17 -> 1212618 | J17: =INDEX($M$5:$M$11,MATCH($C17,_xlfn.ANCHORARRAY($L$5),0)) -> 2659.25
B18: 1656 Adanac Street | C18: =INDEX('01_Property Summary'!$E$5:$E$21,MATCH('02_Rent Engine'!$B18,'01_Property Summary'!$C$5:$C$21,0)) -> Vancouver | D18: =INDEX('01_Property Summary'!$F$5:$F$21,MATCH('02_Rent Engine'!$B18,'01_Property Summary'!$C$5:$C$21,0)) -> 2028 | E18: =INDEX('01_Property Summary'!$S$5:$S$21,MATCH('02_Rent Engine'!$B18,'01_Property Summary'!$C$5:$C$21,0)) -> 97 | F18: =INDEX('01_Base Yr. Inputs'!$5:$5,MATCH('02_Rent Engine'!$B18,'01_Base Yr. Inputs'!$3:$3,0)) -> 1636062 | G18: =F18/E18 -> 16866.619 | H18: =G18/12 -> 1405.5515 | I18: =J18*12*E18 -> 4253547 | J18: =INDEX($M$5:$M$11,MATCH($C18,_xlfn.ANCHORARRAY($L$5),0)) -> 3654.25
B19: 450 Pacific Street | C19: =INDEX('01_Property Summary'!$E$5:$E$21,MATCH('02_Rent Engine'!$B19,'01_Property Summary'!$C$5:$C$21,0)) -> Vancouver | D19: =INDEX('01_Property Summary'!$F$5:$F$21,MATCH('02_Rent Engine'!$B19,'01_Property Summary'!$C$5:$C$21,0)) -> 2028 | E19: =INDEX('01_Property Summary'!$S$5:$S$21,MATCH('02_Rent Engine'!$B19,'01_Property Summary'!$C$5:$C$21,0)) -> 91 | F19: =INDEX('01_Base Yr. Inputs'!$5:$5,MATCH('02_Rent Engine'!$B19,'01_Base Yr. Inputs'!$3:$3,0)) -> 1399704 | G19: =F19/E19 -> 15381.363 | H19: =G19/12 -> 1281.7802 | I19: =J19*12*E19 -> 3990441 | J19: =INDEX($M$5:$M$11,MATCH($C19,_xlfn.ANCHORARRAY($L$5),0)) -> 3654.25
B20: The Creek, Port Moody | C20: =INDEX('01_Property Summary'!$E$5:$E$21,MATCH('02_Rent Engine'!$B20,'01_Property Summary'!$C$5:$C$21,0)) -> Port Moody | D20: =INDEX('01_Property Summary'!$F$5:$F$21,MATCH('02_Rent Engine'!$B20,'01_Property Summary'!$C$5:$C$21,0)) -> 2027 | E20: =INDEX('01_Property Summary'!$S$5:$S$21,MATCH('02_Rent Engine'!$B20,'01_Property Summary'!$C$5:$C$21,0)) -> 328 | F20: =INDEX('01_Base Yr. Inputs'!$5:$5,MATCH('02_Rent Engine'!$B20,'01_Base Yr. Inputs'!$3:$3,0)) -> 3800872.3 | G20: =F20/E20 -> 11588.025 | H20: =G20/12 -> 965.66877 | I20: =J20*12*E20 -> 12147480 | J20: =INDEX($M$5:$M$11,MATCH($C20,_xlfn.ANCHORARRAY($L$5),0)) -> 3086.25
B21: 800 Commercial Drive | C21: =INDEX('01_Property Summary'!$E$5:$E$21,MATCH('02_Rent Engine'!$B21,'01_Property Summary'!$C$5:$C$21,0)) -> Vancouver | D21: =INDEX('01_Property Summary'!$F$5:$F$21,MATCH('02_Rent Engine'!$B21,'01_Property Summary'!$C$5:$C$21,0)) -> 2029 | E21: =INDEX('01_Property Summary'!$S$5:$S$21,MATCH('02_Rent Engine'!$B21,'01_Property Summary'!$C$5:$C$21,0)) -> 93 | F21: =INDEX('01_Base Yr. Inputs'!$5:$5,MATCH('02_Rent Engine'!$B21,'01_Base Yr. Inputs'!$3:$3,0)) -> 1812384 | G21: =F21/E21 -> 19488 | H21: =G21/12 -> 1624 | I21: =J21*12*E21 -> 4078143 | J21: =INDEX($M$5:$M$11,MATCH($C21,_xlfn.ANCHORARRAY($L$5),0)) -> 3654.25
B23: Notes:
B24: Source: 01 tabs.
B25: Market rents assumed based on market research.

Sheet 02_Debt Engine
B2: DEBT ENGINE (2026)
B4: New Development Loan-Sizing
B5: LTC | C5: ='01_Assumptions'!$C$25 -> 0.9
B6: Cost/Unit | C6: ='01_Assumptions'!$C$26 -> 450000
B7: Rate | C7: ='01_Assumptions'!$C$27 -> 0.045
B8: Amortizing Years | C8: ='01_Assumptions'!$C$28 -> 40
B9: Refi Loan-Sizing
B10: LTV | C10: ='01_Assumptions'!$C$18 -> 0.75
B11: DSCR | C11: ='01_Assumptions'!$C$19 -> 1.2
B12: Cap Rate | C12: ='01_Assumptions'!$C$22 -> 0.06
B13: Rate | C13: ='01_Assumptions'!$C$20 -> 0.04
B14: Amortizing Years | C14: ='01_Assumptions'!$C$21 -> 35
B15: Refer to 01_Assumptions tab
B17: RENT ASSUMPTIONS — UNIT MIX & BLENDED WEIGHTED AVERAGE RENT | G17: Current Loans | O17: New Development | Q17: Debt Service | S17: Refinancing Scenario
B18: Property Name | C18: City | D18: Status | E18: Units | F18: Refinance Potential | G18: Mortgage | H18: Interest Rate | I18: Term Year | J18: Amortizing Years | K18: Annual Mortgage Payment | L18: Annual Mortgage Subsidy | M18: Mortgage Subsidy as a % of Debt Serv. | N18: Mortgage Balance Outstanding 2025 | O18: New Dev LTC Loan | P18: New Dev PMT | Q18: Interest PMT | R18: Principle PMT | S18: NOI During Refi Year | T18: LTV Proceeds | U18: DSCR Proceeds | V18: Refi Loan (Minimum of LTV vs. DSCR) | W18: Refi Loan PMT | X18: Refi Loan Interest PMT | Y18: Refi Loan Principle PMT
B19: {=_xlfn.UNIQUE('01_Property Summary'!$C$5:$C$21)} -> Alma Blackwell | C19: =INDEX('01_Property Summary'!$E$5:$E$21,MATCH('02_Rent Engine'!$B5,'01_Property Summary'!$C$5:$C$21,0)) -> Vancouver | D19: =INDEX('01_Property Summary'!$G$5:$G$21,MATCH('02_Debt Engine'!B19,'01_Property Summary'!$C$5:$C$21,0)) -> Active | E19: =INDEX('01_Property Summary'!$S$5:$S$21,MATCH('02_Debt Engine'!B19,'01_Property Summary'!$C$5:$C$21,0)) -> 46 | F19: No | G19: =INDEX('01_Property Summary'!L$5:L$21,MATCH('02_Debt Engine'!$B19,'01_Property Summary'!$C$5:$C$21,0)) -> N/A | H19: =INDEX('01_Property Summary'!M$5:M$21,MATCH('02_Debt Engine'!$B19,'01_Property Summary'!$C$5:$C$21,0)) -> 0 | I19: =IF(D19="Active",YEAR(INDEX('01_Property Summary'!N$5:N$21,MATCH('02_Debt Engine'!$B19,'01_Property Summary'!$C$5:$C$21,0))),INDEX('02_Rent Engine'!$D$5:$D$21,MATCH($B19,'02_Rent Engine'!$B$5:$B$21,0))) -> 1900 | J19: =INDEX('01_Property Summary'!O$5:O$21,MATCH('02_Debt Engine'!$B19,'01_Property Summary'!$C$5:$C$21,0)) -> 0 | K19: =INDEX('01_Property Summary'!P$5:P$21,MATCH('02_Debt Engine'!$B19,'01_Property Summary'!$C$5:$C$21,0)) -> 0 | L19: =INDEX('01_Property Summary'!Q$5:Q$21,MATCH('02_Debt Engine'!$B19,'01_Property Summary'!$C$5:$C$21,0)) -> 0 | M19: =IFERROR(L19/K19,0) -> 0 | N19: =INDEX('01_Property Summary'!R$5:R$21,MATCH('02_Debt Engine'!$B19,'01_Property Summary'!$C$5:$C$21,0)) -> 0 | O19: =IF($D19="New Dev",E19*$C$6*$C$5,0) -> 0 | P19: =IFERROR(-PMT($C$7/12,$C$8*12,O19)*12,0) -> 0 | Q19: =IF($D19="Active",N19*H19,(O19*$C$7)) -> 0 | R19: =IF($D19="Active",K19-Q19,P19-Q19) -> 0 | S19: =IFERROR(INDEX(BLD_AB!$41:$41,MATCH('02_Debt Engine'!$I19,BLD_AB!$12:$12,0)),0) -> 0 | T19: =IF($F19="Yes",MAX(0,$S19/$C$12*$C$10),0) -> 0 | U19: =IF($F19="Yes",MAX(0,IF($S19<=0,0,$S19/$C$11/(PMT($C$13/12,$C$14*12,-1)*12))),0) -> 0 | V19: =MIN(T19,U19) -> 0 | W19: =IFERROR(-PMT($C$13/12,$C$14*12,$V19)*12,0) -> 0 | X19: =IF($V19<>0,$V19*$C$13,0) -> 0 | Y19: =W19-X19 -> 0
B20: Antkiw Court | C20: =INDEX('01_Property Summary'!$E$5:$E$21,MATCH('02_Rent Engine'!$B6,'01_Property Summary'!$C$5:$C$21,0)) -> Vancouver | D20: =INDEX('01_Property Summary'!$G$5:$G$21,MATCH('02_Debt Engine'!B20,'01_Property Summary'!$C$5:$C$21,0)) -> Active | E20: =INDEX('01_Property Summary'!$S$5:$S$21,MATCH('02_Debt Engine'!B20,'01_Property Summary'!$C$5:$C$21,0)) -> 21 | F20: No | G20: =INDEX('01_Property Summary'!L$5:L$21,MATCH('02_Debt Engine'!$B20,'01_Property Summary'!$C$5:$C$21,0)) -> BCHMC/NPAT | H20: =INDEX('01_Property Summary'!M$5:M$21,MATCH('02_Debt Engine'!$B20,'01_Property Summary'!$C$5:$C$21,0)) -> 0.04024 | I20: =IF(D20="Active",YEAR(INDEX('01_Property Summary'!N$5:N$21,MATCH('02_Debt Engine'!$B20,'01_Property Summary'!$C$5:$C$21,0))),INDEX('02_Rent Engine'!$D$5:$D$21,MATCH($B20,'02_Rent Engine'!$B$5:$B$21,0))) -> 2035 | J20: =INDEX('01_Property Summary'!O$5:O$21,MATCH('02_Debt Engine'!$B20,'01_Property Summary'!$C$5:$C$21,0)) -> 22 | K20: =INDEX('01_Property Summary'!P$5:P$21,MATCH('02_Debt Engine'!$B20,'01_Property Summary'!$C$5:$C$21,0)) -> 54330.12 | L20: =INDEX('01_Property Summary'!Q$5:Q$21,MATCH('02_Debt Engine'!$B20,'01_Property Summary'!$C$5:$C$21,0)) -> 54330.12 | M20: =IFERROR(L20/K20,0) -> 1 | N20: =INDEX('01_Property Summary'!R$5:R$21,MATCH('02_Debt Engine'!$B20,'01_Property Summary'!$C$5:$C$21,0)) -> 794745.17 | O20: =IF($D20="New Dev",E20*$C$6*$C$5,0) -> 0 | P20: =IFERROR(-PMT($C$7/12,$C$8*12,O20)*12,0) -> 0 | Q20: =IF($D20="Active",N20*H20,(O20*$C$7)) -> 31980.546 | R20: =IF($D20="Active",K20-Q20,P20-Q20) -> 22349.574 | S20: =IFERROR(INDEX(BLD_AC!$41:$41,MATCH('02_Debt Engine'!$I20,BLD_AC!$12:$12,0)),0) -> 248807.85 | T20: =IF($F20="Yes",MAX(0,$S20/$C$12*$C$10),0) -> 0 | U20: =IF($F20="Yes",MAX(0,IF($S20<=0,0,$S20/$C$11/(PMT($C$13/12,$C$14*12,-1)*12))),0) -> 0 | V20: =MIN(T20,U20) -> 0 | W20: =IFERROR(-PMT($C$13/12,$C$14*12,$V20)*12,0) -> 0 | X20: =IF($V20<>0,$V20*$C$13,0) -> 0 | Y20: =W20-X20 -> 0
B21: Beatrice Terrace | C21: =INDEX('01_Property Summary'!$E$5:$E$21,MATCH('02_Rent Engine'!$B7,'01_Property Summary'!$C$5:$C$21,0)) -> Vancouver | D21: =INDEX('01_Property Summary'!$G$5:$G$21,MATCH('02_Debt Engine'!B21,'01_Property Summary'!$C$5:$C$21,0)) -> Active | E21: =INDEX('01_Property Summary'!$S$5:$S$21,MATCH('02_Debt Engine'!B21,'01_Property Summary'!$C$5:$C$21,0)) -> 18 | F21: No | G21: =INDEX('01_Property Summary'!L$5:L$21,MATCH('02_Debt Engine'!$B21,'01_Property Summary'!$C$5:$C$21,0)) -> BCHMC/NPAT | H21: =INDEX('01_Property Summary'!M$5:M$21,MATCH('02_Debt Engine'!$B21,'01_Property Summary'!$C$5:$C$21,0)) -> 0.04024 | I21: =IF(D21="Active",YEAR(INDEX('01_Property Summary'!N$5:N$21,MATCH('02_Debt Engine'!$B21,'01_Property Summary'!$C$5:$C$21,0))),INDEX('02_Rent Engine'!$D$5:$D$21,MATCH($B21,'02_Rent Engine'!$B$5:$B$21,0))) -> 2035 | J21: =INDEX('01_Property Summary'!O$5:O$21,MATCH('02_Debt Engine'!$B21,'01_Property Summary'!$C$5:$C$21,0)) -> 22 | K21: =INDEX('01_Property Summary'!P$5:P$21,MATCH('02_Debt Engine'!$B21,'01_Property Summary'!$C$5:$C$21,0)) -> 110563.68 | L21: =INDEX('01_Property Summary'!Q$5:Q$21,MATCH('02_Debt Engine'!$B21,'01_Property Summary'!$C$5:$C$21,0)) -> 110563.68 | M21: =IFERROR(L21/K21,0) -> 1 | N21: =INDEX('01_Property Summary'!R$5:R$21,MATCH('02_Debt Engine'!$B21,'01_Property Summary'!$C$5:$C$21,0)) -> 1617334.9 | O21: =IF($D21="New Dev",E21*$C$6*$C$5,0) -> 0 | P21: =IFERROR(-PMT($C$7/12,$C$8*12,O21)*12,0) -> 0 | Q21: =IF($D21="Active",N21*H21,(O21*$C$7)) -> 65081.556 | R21: =IF($D21="Active",K21-Q21,P21-Q21) -> 45482.124 | S21: =IFERROR(INDEX(BLD_BT!$41:$41,MATCH('02_Debt Engine'!$I21,BLD_BT!$12:$12,0)),0) -> 332046.69 | T21: =IF($F21="Yes",MAX(0,$S21/$C$12*$C$10),0) -> 0 | U21: =IF($F21="Yes",MAX(0,IF($S21<=0,0,$S21/$C$11/(PMT($C$13/12,$C$14*12,-1)*12))),0) -> 0 | V21: =MIN(T21,U21) -> 0 | W21: =IFERROR(-PMT($C$13/12,$C$14*12,$V21)*12,0) -> 0 | X21: =IF($V21<>0,$V21*$C$13,0) -> 0 | Y21: =W21-X21 -> 0
B22: Capilano House | C22: =INDEX('01_Property Summary'!$E$5:$E$21,MATCH('02_Rent Engine'!$B8,'01_Property Summary'!$C$5:$C$21,0)) -> DNV | D22: =INDEX('01_Property Summary'!$G$5:$G$21,MATCH('02_Debt Engine'!B22,'01_Property Summary'!$C$5:$C$21,0)) -> Active | E22: =INDEX('01_Property Summary'!$S$5:$S$21,MATCH('02_Debt Engine'!B22,'01_Property Summary'!$C$5:$C$21,0)) -> 64 | F22: No | G22: =INDEX('01_Property Summary'!L$5:L$21,MATCH('02_Debt Engine'!$B22,'01_Property Summary'!$C$5:$C$21,0)) -> N/A | H22: =INDEX('01_Property Summary'!M$5:M$21,MATCH('02_Debt Engine'!$B22,'01_Property Summary'!$C$5:$C$21,0)) -> 0 | I22: =IF(D22="Active",YEAR(INDEX('01_Property Summary'!N$5:N$21,MATCH('02_Debt Engine'!$B22,'01_Property Summary'!$C$5:$C$21,0))),INDEX('02_Rent Engine'!$D$5:$D$21,MATCH($B22,'02_Rent Engine'!$B$5:$B$21,0))) -> 1900 | J22: =INDEX('01_Property Summary'!O$5:O$21,MATCH('02_Debt Engine'!$B22,'01_Property Summary'!$C$5:$C$21,0)) -> 0 | K22: =INDEX('01_Property Summary'!P$5:P$21,MATCH('02_Debt Engine'!$B22,'01_Property Summary'!$C$5:$C$21,0)) -> 0 | L22: =INDEX('01_Property Summary'!Q$5:Q$21,MATCH('02_Debt Engine'!$B22,'01_Property Summary'!$C$5:$C$21,0)) -> 0 | M22: =IFERROR(L22/K22,0) -> 0 | N22: =INDEX('01_Property Summary'!R$5:R$21,MATCH('02_Debt Engine'!$B22,'01_Property Summary'!$C$5:$C$21,0)) -> 0 | O22: =IF($D22="New Dev",E22*$C$6*$C$5,0) -> 0 | P22: =IFERROR(-PMT($C$7/12,$C$8*12,O22)*12,0) -> 0 | Q22: =IF($D22="Active",N22*H22,(O22*$C$7)) -> 0 | R22: =IF($D22="Active",K22-Q22,P22-Q22) -> 0 | S22: =IFERROR(INDEX(BLD_CH!$41:$41,MATCH('02_Debt Engine'!$I22,BLD_CH!$12:$12,0)),0) -> 0 | T22: =IF($F22="Yes",MAX(0,$S22/$C$12*$C$10),0) -> 0 | U22: =IF($F22="Yes",MAX(0,IF($S22<=0,0,$S22/$C$11/(PMT($C$13/12,$C$14*12,-1)*12))),0) -> 0 | V22: =MIN(T22,U22) -> 0 | W22: =IFERROR(-PMT($C$13/12,$C$14*12,$V22)*12,0) -> 0 | X22: =IF($V22<>0,$V22*$C$13,0) -> 0 | Y22: =W22-X22 -> 0
B23: Constance Court | C23: =INDEX('01_Property Summary'!$E$5:$E$21,MATCH('02_Rent Engine'!$B9,'01_Property Summary'!$C$5:$C$21,0)) -> Vancouver | D23: =INDEX('01_Property Summary'!$G$5:$G$21,MATCH('02_Debt Engine'!B23,'01_Property Summary'!$C$5:$C$21,0)) -> Active | E23: =INDEX('01_Property Summary'!$S$5:$S$21,MATCH('02_Debt Engine'!B23,'01_Property Summary'!$C$5:$C$21,0)) -> 34 | F23: No | G23: =INDEX('01_Property Summary'!L$5:L$21,MATCH('02_Debt Engine'!$B23,'01_Property Summary'!$C$5:$C$21,0)) -> BCHMC | H23: =INDEX('01_Property Summary'!M$5:M$21,MATCH('02_Debt Engine'!$B23,'01_Property Summary'!$C$5:$C$21,0)) -> 0.0423 | I23: =IF(D23="Active",YEAR(INDEX('01_Property Summary'!N$5:N$21,MATCH('02_Debt Engine'!$B23,'01_Property Summary'!$C$5:$C$21,0))),INDEX('02_Rent Engine'!$D$5:$D$21,MATCH($B23,'02_Rent Engine'!$B$5:$B$21,0))) -> 2027 | J23: =INDEX('01_Property Summary'!O$5:O$21,MATCH('02_Debt Engine'!$B23,'01_Property Summary'!$C$5:$C$21,0)) -> 3 | K23: =INDEX('01_Property Summary'!P$5:P$21,MATCH('02_Debt Engine'!$B23,'01_Property Summary'!$C$5:$C$21,0)) -> 178507.8 | L23: =INDEX('01_Property Summary'!Q$5:Q$21,MATCH('02_Debt Engine'!$B23,'01_Property Summary'!$C$5:$C$21,0)) -> 178507.8 | M23: =IFERROR(L23/K23,0) -> 1 | N23: =INDEX('01_Property Summary'!R$5:R$21,MATCH('02_Debt Engine'!$B23,'01_Property Summary'!$C$5:$C$21,0)) -> 274036.81 | O23: =IF($D23="New Dev",E23*$C$6*$C$5,0) -> 0 | P23: =IFERROR(-PMT($C$7/12,$C$8*12,O23)*12,0) -> 0 | Q23: =IF($D23="Active",N23*H23,(O23*$C$7)) -> 11591.757 | R23: =IF($D23="Active",K23-Q23,P23-Q23) -> 166916.04 | S23: =IFERROR(INDEX(BLD_CC!$41:$41,MATCH('02_Debt Engine'!$I23,BLD_CC!$12:$12,0)),0) -> 467983.07 | T23: =IF($F23="Yes",MAX(0,$S23/$C$12*$C$10),0) -> 0 | U23: =IF($F23="Yes",MAX(0,IF($S23<=0,0,$S23/$C$11/(PMT($C$13/12,$C$14*12,-1)*12))),0) -> 0 | V23: =MIN(T23,U23) -> 0 | W23: =IFERROR(-PMT($C$13/12,$C$14*12,$V23)*12,0) -> 0 | X23: =IF($V23<>0,$V23*$C$13,0) -> 0 | Y23: =W23-X23 -> 0
B24: Evergreen Apartments | C24: =INDEX('01_Property Summary'!$E$5:$E$21,MATCH('02_Rent Engine'!$B10,'01_Property Summary'!$C$5:$C$21,0)) -> New Westminster | D24: =INDEX('01_Property Summary'!$G$5:$G$21,MATCH('02_Debt Engine'!B24,'01_Property Summary'!$C$5:$C$21,0)) -> Active | E24: =INDEX('01_Property Summary'!$S$5:$S$21,MATCH('02_Debt Engine'!B24,'01_Property Summary'!$C$5:$C$21,0)) -> 61 | F24: Yes | G24: =INDEX('01_Property Summary'!L$5:L$21,MATCH('02_Debt Engine'!$B24,'01_Property Summary'!$C$5:$C$21,0)) -> Vancity | H24: =INDEX('01_Property Summary'!M$5:M$21,MATCH('02_Debt Engine'!$B24,'01_Property Summary'!$C$5:$C$21,0)) -> 0.0421 | I24: =IF(D24="Active",YEAR(INDEX('01_Property Summary'!N$5:N$21,MATCH('02_Debt Engine'!$B24,'01_Property Summary'!$C$5:$C$21,0))),INDEX('02_Rent Engine'!$D$5:$D$21,MATCH($B24,'02_Rent Engine'!$B$5:$B$21,0))) -> 2034 | J24: =INDEX('01_Property Summary'!O$5:O$21,MATCH('02_Debt Engine'!$B24,'01_Property Summary'!$C$5:$C$21,0)) -> 35 | K24: =INDEX('01_Property Summary'!P$5:P$21,MATCH('02_Debt Engine'!$B24,'01_Property Summary'!$C$5:$C$21,0)) -> 297840 | L24: =INDEX('01_Property Summary'!Q$5:Q$21,MATCH('02_Debt Engine'!$B24,'01_Property Summary'!$C$5:$C$21,0)) -> 0 | M24: =IFERROR(L24/K24,0) -> 0 | N24: =INDEX('01_Property Summary'!R$5:R$21,MATCH('02_Debt Engine'!$B24,'01_Property Summary'!$C$5:$C$21,0)) -> 5475821.3 | O24: =IF($D24="New Dev",E24*$C$6*$C$5,0) -> 0 | P24: =IFERROR(-PMT($C$7/12,$C$8*12,O24)*12,0) -> 0 | Q24: =IF($D24="Active",N24*H24,(O24*$C$7)) -> 230532.08 | R24: =IF($D24="Active",K24-Q24,P24-Q24) -> 67307.923 | S24: =IFERROR(INDEX(BLD_EA!$41:$41,MATCH('02_Debt Engine'!$I24,BLD_EA!$12:$12,0)),0) -> 598626.55 | T24: =IF($F24="Yes",MAX(0,$S24/$C$12*$C$10),0) -> 7482831.9 | U24: =IF($F24="Yes",MAX(0,IF($S24<=0,0,$S24/$C$11/(PMT($C$13/12,$C$14*12,-1)*12))),0) -> 9388812.1 | V24: =MIN(T24,U24) -> 7482831.9 | W24: =IFERROR(-PMT($C$13/12,$C$14*12,$V24)*12,0) -> 397585.08 | X24: =IF($V24<>0,$V24*$C$13,0) -> 299313.28 | Y24: =W24-X24 -> 98271.799
B25: Evelyn Estates | C25: =INDEX('01_Property Summary'!$E$5:$E$21,MATCH('02_Rent Engine'!$B11,'01_Property Summary'!$C$5:$C$21,0)) -> Surrey | D25: =INDEX('01_Property Summary'!$G$5:$G$21,MATCH('02_Debt Engine'!B25,'01_Property Summary'!$C$5:$C$21,0)) -> Active | E25: =INDEX('01_Property Summary'!$S$5:$S$21,MATCH('02_Debt Engine'!B25,'01_Property Summary'!$C$5:$C$21,0)) -> 36 | F25: No | G25: =INDEX('01_Property Summary'!L$5:L$21,MATCH('02_Debt Engine'!$B25,'01_Property Summary'!$C$5:$C$21,0)) -> BCHMC | H25: =INDEX('01_Property Summary'!M$5:M$21,MATCH('02_Debt Engine'!$B25,'01_Property Summary'!$C$5:$C$21,0)) -> 0.0374 | I25: =IF(D25="Active",YEAR(INDEX('01_Property Summary'!N$5:N$21,MATCH('02_Debt Engine'!$B25,'01_Property Summary'!$C$5:$C$21,0))),INDEX('02_Rent Engine'!$D$5:$D$21,MATCH($B25,'02_Rent Engine'!$B$5:$B$21,0))) -> 2028 | J25: =INDEX('01_Property Summary'!O$5:O$21,MATCH('02_Debt Engine'!$B25,'01_Property Summary'!$C$5:$C$21,0)) -> 4 | K25: =INDEX('01_Property Summary'!P$5:P$21,MATCH('02_Debt Engine'!$B25,'01_Property Summary'!$C$5:$C$21,0)) -> 244376.04 | L25: =INDEX('01_Property Summary'!Q$5:Q$21,MATCH('02_Debt Engine'!$B25,'01_Property Summary'!$C$5:$C$21,0)) -> 0 | M25: =IFERROR(L25/K25,0) -> 0 | N25: =INDEX('01_Property Summary'!R$5:R$21,MATCH('02_Debt Engine'!$B25,'01_Property Summary'!$C$5:$C$21,0)) -> 639949.69 | O25: =IF($D25="New Dev",E25*$C$6*$C$5,0) -> 0 | P25: =IFERROR(-PMT($C$7/12,$C$8*12,O25)*12,0) -> 0 | Q25: =IF($D25="Active",N25*H25,(O25*$C$7)) -> 23934.118 | R25: =IF($D25="Active",K25-Q25,P25-Q25) -> 220441.92 | S25: =IFERROR(INDEX(BLD_EE!$41:$41,MATCH('02_Debt Engine'!$I25,BLD_EE!$12:$12,0)),0) -> 289501.41 | T25: =IF($F25="Yes",MAX(0,$S25/$C$12*$C$10),0) -> 0 | U25: =IF($F25="Yes",MAX(0,IF($S25<=0,0,$S25/$C$11/(PMT($C$13/12,$C$14*12,-1)*12))),0) -> 0 | V25: =MIN(T25,U25) -> 0 | W25: =IFERROR(-PMT($C$13/12,$C$14*12,$V25)*12,0) -> 0 | X25: =IF($V25<>0,$V25*$C$13,0) -> 0 | Y25: =W25-X25 -> 0
B26: Jessica Place | C26: =INDEX('01_Property Summary'!$E$5:$E$21,MATCH('02_Rent Engine'!$B12,'01_Property Summary'!$C$5:$C$21,0)) -> Surrey | D26: =INDEX('01_Property Summary'!$G$5:$G$21,MATCH('02_Debt Engine'!B26,'01_Property Summary'!$C$5:$C$21,0)) -> Active | E26: =INDEX('01_Property Summary'!$S$5:$S$21,MATCH('02_Debt Engine'!B26,'01_Property Summary'!$C$5:$C$21,0)) -> 40 | F26: No | G26: =INDEX('01_Property Summary'!L$5:L$21,MATCH('02_Debt Engine'!$B26,'01_Property Summary'!$C$5:$C$21,0)) -> BCHMC | H26: =INDEX('01_Property Summary'!M$5:M$21,MATCH('02_Debt Engine'!$B26,'01_Property Summary'!$C$5:$C$21,0)) -> 0.0101 | I26: =IF(D26="Active",YEAR(INDEX('01_Property Summary'!N$5:N$21,MATCH('02_Debt Engine'!$B26,'01_Property Summary'!$C$5:$C$21,0))),INDEX('02_Rent Engine'!$D$5:$D$21,MATCH($B26,'02_Rent Engine'!$B$5:$B$21,0))) -> 2026 | J26: =INDEX('01_Property Summary'!O$5:O$21,MATCH('02_Debt Engine'!$B26,'01_Property Summary'!$C$5:$C$21,0)) -> 4 | K26: =INDEX('01_Property Summary'!P$5:P$21,MATCH('02_Debt Engine'!$B26,'01_Property Summary'!$C$5:$C$21,0)) -> 176698.83 | L26: =INDEX('01_Property Summary'!Q$5:Q$21,MATCH('02_Debt Engine'!$B26,'01_Property Summary'!$C$5:$C$21,0)) -> 0 | M26: =IFERROR(L26/K26,0) -> 0 | N26: =INDEX('01_Property Summary'!R$5:R$21,MATCH('02_Debt Engine'!$B26,'01_Property Summary'!$C$5:$C$21,0)) -> 176698.83 | O26: =IF($D26="New Dev",E26*$C$6*$C$5,0) -> 0 | P26: =IFERROR(-PMT($C$7/12,$C$8*12,O26)*12,0) -> 0 | Q26: =IF($D26="Active",N26*H26,(O26*$C$7)) -> 1784.6582 | R26: =IF($D26="Active",K26-Q26,P26-Q26) -> 174914.17 | S26: =IFERROR(INDEX(BLD_JP!$41:$41,MATCH('02_Debt Engine'!$I26,BLD_JP!$12:$12,0)),0) -> 236702.4 | T26: =IF($F26="Yes",MAX(0,$S26/$C$12*$C$10),0) -> 0 | U26: =IF($F26="Yes",MAX(0,IF($S26<=0,0,$S26/$C$11/(PMT($C$13/12,$C$14*12,-1)*12))),0) -> 0 | V26: =MIN(T26,U26) -> 0 | W26: =IFERROR(-PMT($C$13/12,$C$14*12,$V26)*12,0) -> 0 | X26: =IF($V26<>0,$V26*$C$13,0) -> 0 | Y26: =W26-X26 -> 0
B27: Margaret Heights | C27: =INDEX('01_Property Summary'!$E$5:$E$21,MATCH('02_Rent Engine'!$B13,'01_Property Summary'!$C$5:$C$21,0)) -> CNV | D27: =INDEX('01_Property Summary'!$G$5:$G$21,MATCH('02_Debt Engine'!B27,'01_Property Summary'!$C$5:$C$21,0)) -> Active | E27: =INDEX('01_Property Summary'!$S$5:$S$21,MATCH('02_Debt Engine'!B27,'01_Property Summary'!$C$5:$C$21,0)) -> 19 | F27: No | G27: =INDEX('01_Property Summary'!L$5:L$21,MATCH('02_Debt Engine'!$B27,'01_Property Summary'!$C$5:$C$21,0)) -> BCHMC | H27: =INDEX('01_Property Summary'!M$5:M$21,MATCH('02_Debt Engine'!$B27,'01_Property Summary'!$C$5:$C$21,0)) -> 0.0101 | I27: =IF(D27="Active",YEAR(INDEX('01_Property Summary'!N$5:N$21,MATCH('02_Debt Engine'!$B27,'01_Property Summary'!$C$5:$C$21,0))),INDEX('02_Rent Engine'!$D$5:$D$21,MATCH($B27,'02_Rent Engine'!$B$5:$B$21,0))) -> 2026 | J27: =INDEX('01_Property Summary'!O$5:O$21,MATCH('02_Debt Engine'!$B27,'01_Property Summary'!$C$5:$C$21,0)) -> 5 | K27: =INDEX('01_Property Summary'!P$5:P$21,MATCH('02_Debt Engine'!$B27,'01_Property Summary'!$C$5:$C$21,0)) -> 125540.52 | L27: =INDEX('01_Property Summary'!Q$5:Q$21,MATCH('02_Debt Engine'!$B27,'01_Property Summary'!$C$5:$C$21,0)) -> 0 | M27: =IFERROR(L27/K27,0) -> 0 | N27: =INDEX('01_Property Summary'!R$5:R$21,MATCH('02_Debt Engine'!$B27,'01_Property Summary'!$C$5:$C$21,0)) -> 145670.52 | O27: =IF($D27="New Dev",E27*$C$6*$C$5,0) -> 0 | P27: =IFERROR(-PMT($C$7/12,$C$8*12,O27)*12,0) -> 0 | Q27: =IF($D27="Active",N27*H27,(O27*$C$7)) -> 1471.2723 | R27: =IF($D27="Active",K27-Q27,P27-Q27) -> 124069.25 | S27: =IFERROR(INDEX(BLD_MH!$41:$41,MATCH('02_Debt Engine'!$I27,BLD_MH!$12:$12,0)),0) -> 210980.64 | T27: =IF($F27="Yes",MAX(0,$S27/$C$12*$C$10),0) -> 0 | U27: =IF($F27="Yes",MAX(0,IF($S27<=0,0,$S27/$C$11/(PMT($C$13/12,$C$14*12,-1)*12))),0) -> 0 | V27: =MIN(T27,U27) -> 0 | W27: =IFERROR(-PMT($C$13/12,$C$14*12,$V27)*12,0) -> 0 | X27: =IF($V27<>0,$V27*$C$13,0) -> 0 | Y27: =W27-X27 -> 0
B28: Murray Manor | C28: =INDEX('01_Property Summary'!$E$5:$E$21,MATCH('02_Rent Engine'!$B14,'01_Property Summary'!$C$5:$C$21,0)) -> Burnaby | D28: =INDEX('01_Property Summary'!$G$5:$G$21,MATCH('02_Debt Engine'!B28,'01_Property Summary'!$C$5:$C$21,0)) -> Active | E28: =INDEX('01_Property Summary'!$S$5:$S$21,MATCH('02_Debt Engine'!B28,'01_Property Summary'!$C$5:$C$21,0)) -> 47 | F28: Yes | G28: =INDEX('01_Property Summary'!L$5:L$21,MATCH('02_Debt Engine'!$B28,'01_Property Summary'!$C$5:$C$21,0)) -> Vancity | H28: =INDEX('01_Property Summary'!M$5:M$21,MATCH('02_Debt Engine'!$B28,'01_Property Summary'!$C$5:$C$21,0)) -> 0.0421 | I28: =IF(D28="Active",YEAR(INDEX('01_Property Summary'!N$5:N$21,MATCH('02_Debt Engine'!$B28,'01_Property Summary'!$C$5:$C$21,0))),INDEX('02_Rent Engine'!$D$5:$D$21,MATCH($B28,'02_Rent Engine'!$B$5:$B$21,0))) -> 2034 | J28: =INDEX('01_Property Summary'!O$5:O$21,MATCH('02_Debt Engine'!$B28,'01_Property Summary'!$C$5:$C$21,0)) -> 35 | K28: =INDEX('01_Property Summary'!P$5:P$21,MATCH('02_Debt Engine'!$B28,'01_Property Summary'!$C$5:$C$21,0)) -> 271563.84 | L28: =INDEX('01_Property Summary'!Q$5:Q$21,MATCH('02_Debt Engine'!$B28,'01_Property Summary'!$C$5:$C$21,0)) -> 0 | M28: =IFERROR(L28/K28,0) -> 0 | N28: =INDEX('01_Property Summary'!R$5:R$21,MATCH('02_Debt Engine'!$B28,'01_Property Summary'!$C$5:$C$21,0)) -> 4992966 | O28: =IF($D28="New Dev",E28*$C$6*$C$5,0) -> 0 | P28: =IFERROR(-PMT($C$7/12,$C$8*12,O28)*12,0) -> 0 | Q28: =IF($D28="Active",N28*H28,(O28*$C$7)) -> 210203.87 | R28: =IF($D28="Active",K28-Q28,P28-Q28) -> 61359.971 | S28: =IFERROR(INDEX(BLD_MM!$41:$41,MATCH('02_Debt Engine'!$I28,BLD_MM!$12:$12,0)),0) -> 537126.44 | T28: =IF($F28="Yes",MAX(0,$S28/$C$12*$C$10),0) -> 6714080.5 | U28: =IF($F28="Yes",MAX(0,IF($S28<=0,0,$S28/$C$11/(PMT($C$13/12,$C$14*12,-1)*12))),0) -> 8424249.1 | V28: =MIN(T28,U28) -> 6714080.5 | W28: =IFERROR(-PMT($C$13/12,$C$14*12,$V28)*12,0) -> 356739.03 | X28: =IF($V28<>0,$V28*$C$13,0) -> 268563.22 | Y28: =W28-X28 -> 88175.811
B29: Natalia Terrace | C29: =INDEX('01_Property Summary'!$E$5:$E$21,MATCH('02_Rent Engine'!$B15,'01_Property Summary'!$C$5:$C$21,0)) -> Vancouver | D29: =INDEX('01_Property Summary'!$G$5:$G$21,MATCH('02_Debt Engine'!B29,'01_Property Summary'!$C$5:$C$21,0)) -> Active | E29: =INDEX('01_Property Summary'!$S$5:$S$21,MATCH('02_Debt Engine'!B29,'01_Property Summary'!$C$5:$C$21,0)) -> 40 | F29: No | G29: =INDEX('01_Property Summary'!L$5:L$21,MATCH('02_Debt Engine'!$B29,'01_Property Summary'!$C$5:$C$21,0)) -> BCHMC | H29: =INDEX('01_Property Summary'!M$5:M$21,MATCH('02_Debt Engine'!$B29,'01_Property Summary'!$C$5:$C$21,0)) -> 0.0424 | I29: =IF(D29="Active",YEAR(INDEX('01_Property Summary'!N$5:N$21,MATCH('02_Debt Engine'!$B29,'01_Property Summary'!$C$5:$C$21,0))),INDEX('02_Rent Engine'!$D$5:$D$21,MATCH($B29,'02_Rent Engine'!$B$5:$B$21,0))) -> 2027 | J29: =INDEX('01_Property Summary'!O$5:O$21,MATCH('02_Debt Engine'!$B29,'01_Property Summary'!$C$5:$C$21,0)) -> 3 | K29: =INDEX('01_Property Summary'!P$5:P$21,MATCH('02_Debt Engine'!$B29,'01_Property Summary'!$C$5:$C$21,0)) -> 274351.8 | L29: =INDEX('01_Property Summary'!Q$5:Q$21,MATCH('02_Debt Engine'!$B29,'01_Property Summary'!$C$5:$C$21,0)) -> 0 | M29: =IFERROR(L29/K29,0) -> 0 | N29: =INDEX('01_Property Summary'!R$5:R$21,MATCH('02_Debt Engine'!$B29,'01_Property Summary'!$C$5:$C$21,0)) -> 485006.87 | O29: =IF($D29="New Dev",E29*$C$6*$C$5,0) -> 0 | P29: =IFERROR(-PMT($C$7/12,$C$8*12,O29)*12,0) -> 0 | Q29: =IF($D29="Active",N29*H29,(O29*$C$7)) -> 20564.291 | R29: =IF($D29="Active",K29-Q29,P29-Q29) -> 253787.51 | S29: =IFERROR(INDEX(BLD_NT!$41:$41,MATCH('02_Debt Engine'!$I29,BLD_NT!$12:$12,0)),0) -> 440733.09 | T29: =IF($F29="Yes",MAX(0,$S29/$C$12*$C$10),0) -> 0 | U29: =IF($F29="Yes",MAX(0,IF($S29<=0,0,$S29/$C$11/(PMT($C$13/12,$C$14*12,-1)*12))),0) -> 0 | V29: =MIN(T29,U29) -> 0 | W29: =IFERROR(-PMT($C$13/12,$C$14*12,$V29)*12,0) -> 0 | X29: =IF($V29<>0,$V29*$C$13,0) -> 0 | Y29: =W29-X29 -> 0
B30: Newton Green | C30: =INDEX('01_Property Summary'!$E$5:$E$21,MATCH('02_Rent Engine'!$B16,'01_Property Summary'!$C$5:$C$21,0)) -> Surrey | D30: =INDEX('01_Property Summary'!$G$5:$G$21,MATCH('02_Debt Engine'!B30,'01_Property Summary'!$C$5:$C$21,0)) -> Active | E30: =INDEX('01_Property Summary'!$S$5:$S$21,MATCH('02_Debt Engine'!B30,'01_Property Summary'!$C$5:$C$21,0)) -> 49 | F30: Yes | G30: =INDEX('01_Property Summary'!L$5:L$21,MATCH('02_Debt Engine'!$B30,'01_Property Summary'!$C$5:$C$21,0)) -> CMLS | H30: =INDEX('01_Property Summary'!M$5:M$21,MATCH('02_Debt Engine'!$B30,'01_Property Summary'!$C$5:$C$21,0)) -> 0.04465 | I30: =IF(D30="Active",YEAR(INDEX('01_Property Summary'!N$5:N$21,MATCH('02_Debt Engine'!$B30,'01_Property Summary'!$C$5:$C$21,0))),INDEX('02_Rent Engine'!$D$5:$D$21,MATCH($B30,'02_Rent Engine'!$B$5:$B$21,0))) -> 2034 | J30: =INDEX('01_Property Summary'!O$5:O$21,MATCH('02_Debt Engine'!$B30,'01_Property Summary'!$C$5:$C$21,0)) -> 9 | K30: =INDEX('01_Property Summary'!P$5:P$21,MATCH('02_Debt Engine'!$B30,'01_Property Summary'!$C$5:$C$21,0)) -> 443187 | L30: =INDEX('01_Property Summary'!Q$5:Q$21,MATCH('02_Debt Engine'!$B30,'01_Property Summary'!$C$5:$C$21,0)) -> 0 | M30: =IFERROR(L30/K30,0) -> 0 | N30: =INDEX('01_Property Summary'!R$5:R$21,MATCH('02_Debt Engine'!$B30,'01_Property Summary'!$C$5:$C$21,0)) -> 3432387.1 | O30: =IF($D30="New Dev",E30*$C$6*$C$5,0) -> 0 | P30: =IFERROR(-PMT($C$7/12,$C$8*12,O30)*12,0) -> 0 | Q30: =IF($D30="Active",N30*H30,(O30*$C$7)) -> 153256.08 | R30: =IF($D30="Active",K30-Q30,P30-Q30) -> 289930.92 | S30: =IFERROR(INDEX(BLD_NG!$41:$41,MATCH('02_Debt Engine'!$I30,BLD_NG!$12:$12,0)),0) -> 486026.01 | T30: =IF($F30="Yes",MAX(0,$S30/$C$12*$C$10),0) -> 6075325.1 | U30: =IF($F30="Yes",MAX(0,IF($S30<=0,0,$S30/$C$11/(PMT($C$13/12,$C$14*12,-1)*12))),0) -> 7622793.9 | V30: =MIN(T30,U30) -> 6075325.1 | W30: =IFERROR(-PMT($C$13/12,$C$14*12,$V30)*12,0) -> 322800.06 | X30: =IF($V30<>0,$V30*$C$13,0) -> 243013 | Y30: =W30-X30 -> 79787.056
B31: Rosemary Green | C31: =INDEX('01_Property Summary'!$E$5:$E$21,MATCH('02_Rent Engine'!$B17,'01_Property Summary'!$C$5:$C$21,0)) -> Surrey | D31: =INDEX('01_Property Summary'!$G$5:$G$21,MATCH('02_Debt Engine'!B31,'01_Property Summary'!$C$5:$C$21,0)) -> Active | E31: =INDEX('01_Property Summary'!$S$5:$S$21,MATCH('02_Debt Engine'!B31,'01_Property Summary'!$C$5:$C$21,0)) -> 38 | F31: No | G31: =INDEX('01_Property Summary'!L$5:L$21,MATCH('02_Debt Engine'!$B31,'01_Property Summary'!$C$5:$C$21,0)) -> Peoples Group | H31: =INDEX('01_Property Summary'!M$5:M$21,MATCH('02_Debt Engine'!$B31,'01_Property Summary'!$C$5:$C$21,0)) -> 0.024 | I31: =IF(D31="Active",YEAR(INDEX('01_Property Summary'!N$5:N$21,MATCH('02_Debt Engine'!$B31,'01_Property Summary'!$C$5:$C$21,0))),INDEX('02_Rent Engine'!$D$5:$D$21,MATCH($B31,'02_Rent Engine'!$B$5:$B$21,0))) -> 2026 | J31: =INDEX('01_Property Summary'!O$5:O$21,MATCH('02_Debt Engine'!$B31,'01_Property Summary'!$C$5:$C$21,0)) -> 10 | K31: =INDEX('01_Property Summary'!P$5:P$21,MATCH('02_Debt Engine'!$B31,'01_Property Summary'!$C$5:$C$21,0)) -> 291146.28 | L31: =INDEX('01_Property Summary'!Q$5:Q$21,MATCH('02_Debt Engine'!$B31,'01_Property Summary'!$C$5:$C$21,0)) -> 0 | M31: =IFERROR(L31/K31,0) -> 0 | N31: =INDEX('01_Property Summary'!R$5:R$21,MATCH('02_Debt Engine'!$B31,'01_Property Summary'!$C$5:$C$21,0)) -> 1976761.2 | O31: =IF($D31="New Dev",E31*$C$6*$C$5,0) -> 0 | P31: =IFERROR(-PMT($C$7/12,$C$8*12,O31)*12,0) -> 0 | Q31: =IF($D31="Active",N31*H31,(O31*$C$7)) -> 47442.269 | R31: =IF($D31="Active",K31-Q31,P31-Q31) -> 243704.01 | S31: =IFERROR(INDEX(BLD_RG!$41:$41,MATCH('02_Debt Engine'!$I31,BLD_RG!$12:$12,0)),0) -> 233866.98 | T31: =IF($F31="Yes",MAX(0,$S31/$C$12*$C$10),0) -> 0 | U31: =IF($F31="Yes",MAX(0,IF($S31<=0,0,$S31/$C$11/(PMT($C$13/12,$C$14*12,-1)*12))),0) -> 0 | V31: =MIN(T31,U31) -> 0 | W31: =IFERROR(-PMT($C$13/12,$C$14*12,$V31)*12,0) -> 0 | X31: =IF($V31<>0,$V31*$C$13,0) -> 0 | Y31: =W31-X31 -> 0
B32: 1656 Adanac Street | C32: =INDEX('01_Property Summary'!$E$5:$E$21,MATCH('02_Rent Engine'!$B18,'01_Property Summary'!$C$5:$C$21,0)) -> Vancouver | D32: =INDEX('01_Property Summary'!$G$5:$G$21,MATCH('02_Debt Engine'!B32,'01_Property Summary'!$C$5:$C$21,0)) -> New Dev | E32: =INDEX('01_Property Summary'!$S$5:$S$21,MATCH('02_Debt Engine'!B32,'01_Property Summary'!$C$5:$C$21,0)) -> 97 | F32: Yes | G32: =INDEX('01_Property Summary'!L$5:L$21,MATCH('02_Debt Engine'!$B32,'01_Property Summary'!$C$5:$C$21,0)) -> BCH CHF | H32: =INDEX('01_Property Summary'!M$5:M$21,MATCH('02_Debt Engine'!$B32,'01_Property Summary'!$C$5:$C$21,0)) -> 0 | I32: =IF(D32="Active",YEAR(INDEX('01_Property Summary'!N$5:N$21,MATCH('02_Debt Engine'!$B32,'01_Property Summary'!$C$5:$C$21,0))),INDEX('02_Rent Engine'!$D$5:$D$21,MATCH($B32,'02_Rent Engine'!$B$5:$B$21,0))) -> 2028 | J32: =INDEX('01_Property Summary'!O$5:O$21,MATCH('02_Debt Engine'!$B32,'01_Property Summary'!$C$5:$C$21,0)) -> 0 | K32: =INDEX('01_Property Summary'!P$5:P$21,MATCH('02_Debt Engine'!$B32,'01_Property Summary'!$C$5:$C$21,0)) -> 0 | L32: =INDEX('01_Property Summary'!Q$5:Q$21,MATCH('02_Debt Engine'!$B32,'01_Property Summary'!$C$5:$C$21,0)) -> 0 | M32: =IFERROR(L32/K32,0) -> 0 | N32: =INDEX('01_Property Summary'!R$5:R$21,MATCH('02_Debt Engine'!$B32,'01_Property Summary'!$C$5:$C$21,0)) -> 0 | O32: =IF($D32="New Dev",E32*$C$6*$C$5,0) -> 39285000 | P32: =IFERROR(-PMT($C$7/12,$C$8*12,O32)*12,0) -> 2119329.1 | Q32: =IF($D32="Active",N32*H32,(O32*$C$7)) -> 1767825 | R32: =IF($D32="Active",K32-Q32,P32-Q32) -> 351504.13 | S32: =IFERROR(INDEX(BLD_AS!$41:$41,MATCH('02_Debt Engine'!$I32,BLD_AS!$12:$12,0)),0) -> 1213031.4 | T32: =IF($F32="Yes",MAX(0,$S32/$C$12*$C$10),0) -> 15162893 | U32: =IF($F32="Yes",MAX(0,IF($S32<=0,0,$S32/$C$11/(PMT($C$13/12,$C$14*12,-1)*12))),0) -> 19025090 | V32: =MIN(T32,U32) -> 15162893 | W32: =IFERROR(-PMT($C$13/12,$C$14*12,$V32)*12,0) -> 805649.52 | X32: =IF($V32<>0,$V32*$C$13,0) -> 606515.72 | Y32: =W32-X32 -> 199133.8
B33: 450 Pacific Street | C33: =INDEX('01_Property Summary'!$E$5:$E$21,MATCH('02_Rent Engine'!$B19,'01_Property Summary'!$C$5:$C$21,0)) -> Vancouver | D33: =INDEX('01_Property Summary'!$G$5:$G$21,MATCH('02_Debt Engine'!B33,'01_Property Summary'!$C$5:$C$21,0)) -> New Dev | E33: =INDEX('01_Property Summary'!$S$5:$S$21,MATCH('02_Debt Engine'!B33,'01_Property Summary'!$C$5:$C$21,0)) -> 91 | F33: Yes | G33: =INDEX('01_Property Summary'!L$5:L$21,MATCH('02_Debt Engine'!$B33,'01_Property Summary'!$C$5:$C$21,0)) -> BCH CHF | H33: =INDEX('01_Property Summary'!M$5:M$21,MATCH('02_Debt Engine'!$B33,'01_Property Summary'!$C$5:$C$21,0)) -> 0 | I33: =IF(D33="Active",YEAR(INDEX('01_Property Summary'!N$5:N$21,MATCH('02_Debt Engine'!$B33,'01_Property Summary'!$C$5:$C$21,0))),INDEX('02_Rent Engine'!$D$5:$D$21,MATCH($B33,'02_Rent Engine'!$B$5:$B$21,0))) -> 2028 | J33: =INDEX('01_Property Summary'!O$5:O$21,MATCH('02_Debt Engine'!$B33,'01_Property Summary'!$C$5:$C$21,0)) -> 0 | K33: =INDEX('01_Property Summary'!P$5:P$21,MATCH('02_Debt Engine'!$B33,'01_Property Summary'!$C$5:$C$21,0)) -> 0 | L33: =INDEX('01_Property Summary'!Q$5:Q$21,MATCH('02_Debt Engine'!$B33,'01_Property Summary'!$C$5:$C$21,0)) -> 0 | M33: =IFERROR(L33/K33,0) -> 0 | N33: =INDEX('01_Property Summary'!R$5:R$21,MATCH('02_Debt Engine'!$B33,'01_Property Summary'!$C$5:$C$21,0)) -> 0 | O33: =IF($D33="New Dev",E33*$C$6*$C$5,0) -> 36855000 | P33: =IFERROR(-PMT($C$7/12,$C$8*12,O33)*12,0) -> 1988236.6 | Q33: =IF($D33="Active",N33*H33,(O33*$C$7)) -> 1658475 | R33: =IF($D33="Active",K33-Q33,P33-Q33) -> 329761.6 | S33: =IFERROR(INDEX(BLD_PS!$41:$41,MATCH('02_Debt Engine'!$I33,BLD_PS!$12:$12,0)),0) -> 1004966.2 | T33: =IF($F33="Yes",MAX(0,$S33/$C$12*$C$10),0) -> 12562077 | U33: =IF($F33="Yes",MAX(0,IF($S33<=0,0,$S33/$C$11/(PMT($C$13/12,$C$14*12,-1)*12))),0) -> 15761811 | V33: =MIN(T33,U33) -> 12562077 | W33: =IFERROR(-PMT($C$13/12,$C$14*12,$V33)*12,0) -> 667460.46 | X33: =IF($V33<>0,$V33*$C$13,0) -> 502483.09 | Y33: =W33-X33 -> 164977.37
B34: The Creek, Port Moody | C34: =INDEX('01_Property Summary'!$E$5:$E$21,MATCH('02_Rent Engine'!$B20,'01_Property Summary'!$C$5:$C$21,0)) -> Port Moody | D34: =INDEX('01_Property Summary'!$G$5:$G$21,MATCH('02_Debt Engine'!B34,'01_Property Summary'!$C$5:$C$21,0)) -> New Dev | E34: =INDEX('01_Property Summary'!$S$5:$S$21,MATCH('02_Debt Engine'!B34,'01_Property Summary'!$C$5:$C$21,0)) -> 328 | F34: Yes | G34: =INDEX('01_Property Summary'!L$5:L$21,MATCH('02_Debt Engine'!$B34,'01_Property Summary'!$C$5:$C$21,0)) -> CMHC | H34: =INDEX('01_Property Summary'!M$5:M$21,MATCH('02_Debt Engine'!$B34,'01_Property Summary'!$C$5:$C$21,0)) -> 0 | I34: =IF(D34="Active",YEAR(INDEX('01_Property Summary'!N$5:N$21,MATCH('02_Debt Engine'!$B34,'01_Property Summary'!$C$5:$C$21,0))),INDEX('02_Rent Engine'!$D$5:$D$21,MATCH($B34,'02_Rent Engine'!$B$5:$B$21,0))) -> 2027 | J34: =INDEX('01_Property Summary'!O$5:O$21,MATCH('02_Debt Engine'!$B34,'01_Property Summary'!$C$5:$C$21,0)) -> 0 | K34: =INDEX('01_Property Summary'!P$5:P$21,MATCH('02_Debt Engine'!$B34,'01_Property Summary'!$C$5:$C$21,0)) -> 0 | L34: =INDEX('01_Property Summary'!Q$5:Q$21,MATCH('02_Debt Engine'!$B34,'01_Property Summary'!$C$5:$C$21,0)) -> 0 | M34: =IFERROR(L34/K34,0) -> 0 | N34: =INDEX('01_Property Summary'!R$5:R$21,MATCH('02_Debt Engine'!$B34,'01_Property Summary'!$C$5:$C$21,0)) -> 0 | O34: =IF($D34="New Dev",E34*$C$6*$C$5,0) -> 132840000 | P34: =IFERROR(-PMT($C$7/12,$C$8*12,O34)*12,0) -> 7166391.3 | Q34: =IF($D34="Active",N34*H34,(O34*$C$7)) -> 5977800 | R34: =IF($D34="Active",K34-Q34,P34-Q34) -> 1188591.3 | S34: =IFERROR(INDEX(BLD_PM!$41:$41,MATCH('02_Debt Engine'!$I34,BLD_PM!$12:$12,0)),0) -> 4693091.2 | T34: =IF($F34="Yes",MAX(0,$S34/$C$12*$C$10),0) -> 58663640 | U34: =IF($F34="Yes",MAX(0,IF($S34<=0,0,$S34/$C$11/(PMT($C$13/12,$C$14*12,-1)*12))),0) -> 73606076 | V34: =MIN(T34,U34) -> 58663640 | W34: =IFERROR(-PMT($C$13/12,$C$14*12,$V34)*12,0) -> 3116973.4 | X34: =IF($V34<>0,$V34*$C$13,0) -> 2346545.6 | Y34: =W34-X34 -> 770427.77
B35: 800 Commercial Drive | C35: =INDEX('01_Property Summary'!$E$5:$E$21,MATCH('02_Rent Engine'!$B21,'01_Property Summary'!$C$5:$C$21,0)) -> Vancouver | D35: =INDEX('01_Property Summary'!$G$5:$G$21,MATCH('02_Debt Engine'!B35,'01_Property Summary'!$C$5:$C$21,0)) -> New Dev | E35: =INDEX('01_Property Summary'!$S$5:$S$21,MATCH('02_Debt Engine'!B35,'01_Property Summary'!$C$5:$C$21,0)) -> 93 | F35: Yes | G35: =INDEX('01_Property Summary'!L$5:L$21,MATCH('02_Debt Engine'!$B35,'01_Property Summary'!$C$5:$C$21,0)) -> BCH CHF | H35: =INDEX('01_Property Summary'!M$5:M$21,MATCH('02_Debt Engine'!$B35,'01_Property Summary'!$C$5:$C$21,0)) -> 0 | I35: =IF(D35="Active",YEAR(INDEX('01_Property Summary'!N$5:N$21,MATCH('02_Debt Engine'!$B35,'01_Property Summary'!$C$5:$C$21,0))),INDEX('02_Rent Engine'!$D$5:$D$21,MATCH($B35,'02_Rent Engine'!$B$5:$B$21,0))) -> 2029 | J35: =INDEX('01_Property Summary'!O$5:O$21,MATCH('02_Debt Engine'!$B35,'01_Property Summary'!$C$5:$C$21,0)) -> 0 | K35: =INDEX('01_Property Summary'!P$5:P$21,MATCH('02_Debt Engine'!$B35,'01_Property Summary'!$C$5:$C$21,0)) -> 0 | L35: =INDEX('01_Property Summary'!Q$5:Q$21,MATCH('02_Debt Engine'!$B35,'01_Property Summary'!$C$5:$C$21,0)) -> 0 | M35: =IFERROR(L35/K35,0) -> 0 | N35: =INDEX('01_Property Summary'!R$5:R$21,MATCH('02_Debt Engine'!$B35,'01_Property Summary'!$C$5:$C$21,0)) -> 0 | O35: =IF($D35="New Dev",E35*$C$6*$C$5,0) -> 37665000 | P35: =IFERROR(-PMT($C$7/12,$C$8*12,O35)*12,0) -> 2031934.1 | Q35: =IF($D35="Active",N35*H35,(O35*$C$7)) -> 1694925 | R35: =IF($D35="Active",K35-Q35,P35-Q35) -> 337009.11 | S35: =IFERROR(INDEX(BLD_CD!$41:$41,MATCH('02_Debt Engine'!$I35,BLD_CD!$12:$12,0)),0) -> 1474873.8 | T35: =IF($F35="Yes",MAX(0,$S35/$C$12*$C$10),0) -> 18435922 | U35: =IF($F35="Yes",MAX(0,IF($S35<=0,0,$S35/$C$11/(PMT($C$13/12,$C$14*12,-1)*12))),0) -> 23131805 | V35: =MIN(T35,U35) -> 18435922 | W35: =IFERROR(-PMT($C$13/12,$C$14*12,$V35)*12,0) -> 979555.28 | X35: =IF($V35<>0,$V35*$C$13,0) -> 737436.89 | Y35: =W35-X35 -> 242118.39
F44: Total Debt Service
B45: Property Name | F45: 2025 | G45: =F45+1 -> 2026 | H45: =G45+1 -> 2027 | I45: =H45+1 -> 2028 | J45: =I45+1 -> 2029 | K45: =J45+1 -> 2030 | L45: =K45+1 -> 2031 | M45: =L45+1 -> 2032 | N45: =M45+1 -> 2033 | ... Z45: =Y45+1 -> 2045
B46: {=_xlfn.UNIQUE('01_Property Summary'!$C$5:$C$21)} -> Alma Blackwell | F46: ='02A_Debt Schedule'!C14 -> 0 | G46: ='02A_Debt Schedule'!D14 -> 0 | H46: ='02A_Debt Schedule'!E14 -> 0 | I46: ='02A_Debt Schedule'!F14 -> 0 | J46: ='02A_Debt Schedule'!G14 -> 0 | K46: ='02A_Debt Schedule'!H14 -> 0 | L46: ='02A_Debt Schedule'!I14 -> 0 | M46: ='02A_Debt Schedule'!J14 -> 0 | ... Z46: ='02A_Debt Schedule'!W14 -> 0
B47: Antkiw Court | F47: ='02A_Debt Schedule'!C24 -> 54330.12 | G47: ='02A_Debt Schedule'!D24 -> 54330.12 | H47: ='02A_Debt Schedule'!E24 -> 54330.12 | I47: ='02A_Debt Schedule'!F24 -> 54330.12 | J47: ='02A_Debt Schedule'!G24 -> 54330.12 | K47: ='02A_Debt Schedule'!H24 -> 54330.12 | L47: ='02A_Debt Schedule'!I24 -> 54330.12 | M47: ='02A_Debt Schedule'!J24 -> 54330.12 | ... Z47: ='02A_Debt Schedule'!W24 -> 54330.12
B48: Beatrice Terrace | F48: ='02A_Debt Schedule'!C34 -> 110563.68 | G48: ='02A_Debt Schedule'!D34 -> 110563.68 | H48: ='02A_Debt Schedule'!E34 -> 110563.68 | I48: ='02A_Debt Schedule'!F34 -> 110563.68 | J48: ='02A_Debt Schedule'!G34 -> 110563.68 | K48: ='02A_Debt Schedule'!H34 -> 110563.68 | L48: ='02A_Debt Schedule'!I34 -> 110563.68 | M48: ='02A_Debt Schedule'!J34 -> 110563.68 | ... Z48: ='02A_Debt Schedule'!W34 -> 110563.68
B49: Capilano House | F49: ='02A_Debt Schedule'!C44 -> 0 | G49: ='02A_Debt Schedule'!D44 -> 0 | H49: ='02A_Debt Schedule'!E44 -> 0 | I49: ='02A_Debt Schedule'!F44 -> 0 | J49: ='02A_Debt Schedule'!G44 -> 0 | K49: ='02A_Debt Schedule'!H44 -> 0 | L49: ='02A_Debt Schedule'!I44 -> 0 | M49: ='02A_Debt Schedule'!J44 -> 0 | ... Z49: ='02A_Debt Schedule'!W44 -> 0
B50: Constance Court | F50: ='02A_Debt Schedule'!C54 -> 178507.8 | G50: ='02A_Debt Schedule'!D54 -> 111651.98 | H50: ='02A_Debt Schedule'!E54 -> 0 | I50: ='02A_Debt Schedule'!F54 -> 0 | J50: ='02A_Debt Schedule'!G54 -> 0 | K50: ='02A_Debt Schedule'!H54 -> 0 | L50: ='02A_Debt Schedule'!I54 -> 0 | M50: ='02A_Debt Schedule'!J54 -> 0 | ... Z50: ='02A_Debt Schedule'!W54 -> 0
B51: Evergreen Apartments | F51: ='02A_Debt Schedule'!C64 -> 297840 | G51: ='02A_Debt Schedule'!D64 -> 297840 | H51: ='02A_Debt Schedule'!E64 -> 297840 | I51: ='02A_Debt Schedule'!F64 -> 297840 | J51: ='02A_Debt Schedule'!G64 -> 297840 | K51: ='02A_Debt Schedule'!H64 -> 297840 | L51: ='02A_Debt Schedule'!I64 -> 297840 | M51: ='02A_Debt Schedule'!J64 -> 297840 | ... Z51: ='02A_Debt Schedule'!W64 -> 397585.08
B52: Evelyn Estates | F52: ='02A_Debt Schedule'!C74 -> 244376.04 | G52: ='02A_Debt Schedule'!D74 -> 244376.04 | H52: ='02A_Debt Schedule'!E74 -> 197958.04 | I52: ='02A_Debt Schedule'!F74 -> 0 | J52: ='02A_Debt Schedule'!G74 -> 0 | K52: ='02A_Debt Schedule'!H74 -> 0 | L52: ='02A_Debt Schedule'!I74 -> 0 | M52: ='02A_Debt Schedule'!J74 -> 0 | ... Z52: ='02A_Debt Schedule'!W74 -> 0
B53: Jessica Place | F53: ='02A_Debt Schedule'!C84 -> 176698.83 | G53: ='02A_Debt Schedule'!D84 -> 1802.6832 | H53: ='02A_Debt Schedule'!E84 -> 0 | I53: ='02A_Debt Schedule'!F84 -> 0 | J53: ='02A_Debt Schedule'!G84 -> 0 | K53: ='02A_Debt Schedule'!H84 -> 0 | L53: ='02A_Debt Schedule'!I84 -> 0 | M53: ='02A_Debt Schedule'!J84 -> 0 | ... Z53: ='02A_Debt Schedule'!W84 -> 0
B54: Margaret Heights | F54: ='02A_Debt Schedule'!C94 -> 125540.52 | G54: ='02A_Debt Schedule'!D94 -> 21819.445 | H54: ='02A_Debt Schedule'!E94 -> 0 | I54: ='02A_Debt Schedule'!F94 -> 0 | J54: ='02A_Debt Schedule'!G94 -> 0 | K54: ='02A_Debt Schedule'!H94 -> 0 | L54: ='02A_Debt Schedule'!I94 -> 0 | M54: ='02A_Debt Schedule'!J94 -> 0 | ... Z54: ='02A_Debt Schedule'!W94 -> 0
B55: Murray Manor | F55: ='02A_Debt Schedule'!C104 -> 271563.84 | G55: ='02A_Debt Schedule'!D104 -> 271563.84 | H55: ='02A_Debt Schedule'!E104 -> 271563.84 | I55: ='02A_Debt Schedule'!F104 -> 271563.84 | J55: ='02A_Debt Schedule'!G104 -> 271563.84 | K55: ='02A_Debt Schedule'!H104 -> 271563.84 | L55: ='02A_Debt Schedule'!I104 -> 271563.84 | M55: ='02A_Debt Schedule'!J104 -> 271563.84 | ... Z55: ='02A_Debt Schedule'!W104 -> 356739.03
B56: Natalia Terrace | F56: ='02A_Debt Schedule'!C114 -> 274351.8 | G56: ='02A_Debt Schedule'!D114 -> 241023.06 | H56: ='02A_Debt Schedule'!E114 -> 0 | I56: ='02A_Debt Schedule'!F114 -> 0 | J56: ='02A_Debt Schedule'!G114 -> 0 | K56: ='02A_Debt Schedule'!H114 -> 0 | L56: ='02A_Debt Schedule'!I114 -> 0 | M56: ='02A_Debt Schedule'!J114 -> 0 | ... Z56: ='02A_Debt Schedule'!W114 -> 0
B57: Newton Green | F57: ='02A_Debt Schedule'!C124 -> 443187 | G57: ='02A_Debt Schedule'!D124 -> 443187 | H57: ='02A_Debt Schedule'!E124 -> 443187 | I57: ='02A_Debt Schedule'!F124 -> 443187 | J57: ='02A_Debt Schedule'!G124 -> 443187 | K57: ='02A_Debt Schedule'!H124 -> 443187 | L57: ='02A_Debt Schedule'!I124 -> 443187 | M57: ='02A_Debt Schedule'!J124 -> 443187 | ... Z57: ='02A_Debt Schedule'!W124 -> 322800.06
B58: Rosemary Green | F58: ='02A_Debt Schedule'!C134 -> 291146.28 | G58: ='02A_Debt Schedule'!D134 -> 291146.28 | H58: ='02A_Debt Schedule'!E134 -> 291146.28 | I58: ='02A_Debt Schedule'!F134 -> 291146.28 | J58: ='02A_Debt Schedule'!G134 -> 291146.28 | K58: ='02A_Debt Schedule'!H134 -> 291146.28 | L58: ='02A_Debt Schedule'!I134 -> 291146.28 | M58: ='02A_Debt Schedule'!J134 -> 146404.96 | ... Z58: ='02A_Debt Schedule'!W134 -> 0
B59: 1656 Adanac Street | F59: ='02A_Debt Schedule'!C144 -> 2119329.1 | G59: ='02A_Debt Schedule'!D144 -> 2119329.1 | H59: ='02A_Debt Schedule'!E144 -> 2119329.1 | I59: ='02A_Debt Schedule'!F144 -> 2119329.1 | J59: ='02A_Debt Schedule'!G144 -> 805649.52 | K59: ='02A_Debt Schedule'!H144 -> 805649.52 | L59: ='02A_Debt Schedule'!I144 -> 805649.52 | M59: ='02A_Debt Schedule'!J144 -> 805649.52 | ... Z59: ='02A_Debt Schedule'!W144 -> 805649.52
B60: 450 Pacific Street | F60: ='02A_Debt Schedule'!C154 -> 1988236.6 | G60: ='02A_Debt Schedule'!D154 -> 1988236.6 | H60: ='02A_Debt Schedule'!E154 -> 1988236.6 | I60: ='02A_Debt Schedule'!F154 -> 1988236.6 | J60: ='02A_Debt Schedule'!G154 -> 667460.46 | K60: ='02A_Debt Schedule'!H154 -> 667460.46 | L60: ='02A_Debt Schedule'!I154 -> 667460.46 | M60: ='02A_Debt Schedule'!J154 -> 667460.46 | ... Z60: ='02A_Debt Schedule'!W154 -> 667460.46
B61: The Creek, Port Moody | F61: ='02A_Debt Schedule'!C164 -> 7166391.3 | G61: ='02A_Debt Schedule'!D164 -> 7166391.3 | H61: ='02A_Debt Schedule'!E164 -> 7166391.3 | I61: ='02A_Debt Schedule'!F164 -> 3116973.4 | J61: ='02A_Debt Schedule'!G164 -> 3116973.4 | K61: ='02A_Debt Schedule'!H164 -> 3116973.4 | L61: ='02A_Debt Schedule'!I164 -> 3116973.4 | M61: ='02A_Debt Schedule'!J164 -> 3116973.4 | ... Z61: ='02A_Debt Schedule'!W164 -> 3116973.4
B62: 800 Commercial Drive | F62: ='02A_Debt Schedule'!C174 -> 2031934.1 | G62: ='02A_Debt Schedule'!D174 -> 2031934.1 | H62: ='02A_Debt Schedule'!E174 -> 2031934.1 | I62: ='02A_Debt Schedule'!F174 -> 2031934.1 | J62: ='02A_Debt Schedule'!G174 -> 2031934.1 | K62: ='02A_Debt Schedule'!H174 -> 979555.28 | L62: ='02A_Debt Schedule'!I174 -> 979555.28 | M62: ='02A_Debt Schedule'!J174 -> 979555.28 | ... Z62: ='02A_Debt Schedule'!W174 -> 979555.28
F72: Remaining Debt Balance (EOY)
B73: Property Name | F73: 2025 | G73: =F73+1 -> 2026 | H73: =G73+1 -> 2027 | I73: =H73+1 -> 2028 | J73: =I73+1 -> 2029 | K73: =J73+1 -> 2030 | L73: =K73+1 -> 2031 | M73: =L73+1 -> 2032 | N73: =M73+1 -> 2033 | ... Z73: =Y73+1 -> 2045
B74: {=_xlfn.UNIQUE('01_Property Summary'!$C$5:$C$21)} -> Alma Blackwell | F74: ='02A_Debt Schedule'!C10 -> 0 | G74: ='02A_Debt Schedule'!D10 -> 0 | H74: ='02A_Debt Schedule'!E10 -> 0 | I74: ='02A_Debt Schedule'!F10 -> 0 | J74: ='02A_Debt Schedule'!G10 -> 0 | K74: ='02A_Debt Schedule'!H10 -> 0 | L74: ='02A_Debt Schedule'!I10 -> 0 | M74: ='02A_Debt Schedule'!J10 -> 0 | ... Z74: ='02A_Debt Schedule'!W10 -> 0
B75: Antkiw Court | F75: ='02A_Debt Schedule'!C20 -> 772395.6 | G75: ='02A_Debt Schedule'!D20 -> 749146.67 | H75: ='02A_Debt Schedule'!E20 -> 724962.22 | I75: ='02A_Debt Schedule'!F20 -> 699804.58 | J75: ='02A_Debt Schedule'!G20 -> 673634.59 | K75: ='02A_Debt Schedule'!H20 -> 646411.53 | L75: ='02A_Debt Schedule'!I20 -> 618093.01 | M75: ='02A_Debt Schedule'!J20 -> 588634.95 | ... Z75: ='02A_Debt Schedule'!W20 -> 78360.86
B76: Beatrice Terrace | F76: ='02A_Debt Schedule'!C30 -> 1571852.8 | G76: ='02A_Debt Schedule'!D30 -> 1524540.4 | H76: ='02A_Debt Schedule'!E30 -> 1475324.3 | I76: ='02A_Debt Schedule'!F30 -> 1424127.6 | J76: ='02A_Debt Schedule'!G30 -> 1370870.9 | K76: ='02A_Debt Schedule'!H30 -> 1315471 | L76: ='02A_Debt Schedule'!I30 -> 1257841.9 | M76: ='02A_Debt Schedule'!J30 -> 1197893.8 | ... Z76: ='02A_Debt Schedule'!W30 -> 159469.09
B77: Capilano House | F77: ='02A_Debt Schedule'!C40 -> 0 | G77: ='02A_Debt Schedule'!D40 -> 0 | H77: ='02A_Debt Schedule'!E40 -> 0 | I77: ='02A_Debt Schedule'!F40 -> 0 | J77: ='02A_Debt Schedule'!G40 -> 0 | K77: ='02A_Debt Schedule'!H40 -> 0 | L77: ='02A_Debt Schedule'!I40 -> 0 | M77: ='02A_Debt Schedule'!J40 -> 0 | ... Z77: ='02A_Debt Schedule'!W40 -> 0
B78: Constance Court | F78: ='02A_Debt Schedule'!C50 -> 107120.77 | G78: ='02A_Debt Schedule'!D50 -> 0 | H78: ='02A_Debt Schedule'!E50 -> 0 | I78: ='02A_Debt Schedule'!F50 -> 0 | J78: ='02A_Debt Schedule'!G50 -> 0 | K78: ='02A_Debt Schedule'!H50 -> 0 | L78: ='02A_Debt Schedule'!I50 -> 0 | M78: ='02A_Debt Schedule'!J50 -> 0 | ... Z78: ='02A_Debt Schedule'!W50 -> 0
B79: Evergreen Apartments | F79: ='02A_Debt Schedule'!C60 -> 5408513.4 | G79: ='02A_Debt Schedule'!D60 -> 5338371.8 | H79: ='02A_Debt Schedule'!E60 -> 5265277.2 | I79: ='02A_Debt Schedule'!F60 -> 5189105.4 | J79: ='02A_Debt Schedule'!G60 -> 5109726.8 | K79: ='02A_Debt Schedule'!H60 -> 5027006.2 | L79: ='02A_Debt Schedule'!I60 -> 4940803.2 | M79: ='02A_Debt Schedule'!J60 -> 4850971 | ... Z79: ='02A_Debt Schedule'!W60 -> 6157503.9
B80: Evelyn Estates | F80: ='02A_Debt Schedule'!C70 -> 419507.77 | G80: ='02A_Debt Schedule'!D70 -> 190821.32 | H80: ='02A_Debt Schedule'!E70 -> 0 | I80: ='02A_Debt Schedule'!F70 -> 0 | J80: ='02A_Debt Schedule'!G70 -> 0 | K80: ='02A_Debt Schedule'!H70 -> 0 | L80: ='02A_Debt Schedule'!I70 -> 0 | M80: ='02A_Debt Schedule'!J70 -> 0 | ... Z80: ='02A_Debt Schedule'!W70 -> 0
B81: Jessica Place | F81: ='02A_Debt Schedule'!C80 -> 1784.6582 | G81: ='02A_Debt Schedule'!D80 -> 0 | H81: ='02A_Debt Schedule'!E80 -> 0 | I81: ='02A_Debt Schedule'!F80 -> 0 | J81: ='02A_Debt Schedule'!G80 -> 0 | K81: ='02A_Debt Schedule'!H80 -> 0 | L81: ='02A_Debt Schedule'!I80 -> 0 | M81: ='02A_Debt Schedule'!J80 -> 0 | ... Z81: ='02A_Debt Schedule'!W80 -> 0
B82: Margaret Heights | F82: ='02A_Debt Schedule'!C90 -> 21601.272 | G82: ='02A_Debt Schedule'!D90 -> 0 | H82: ='02A_Debt Schedule'!E90 -> 0 | I82: ='02A_Debt Schedule'!F90 -> 0 | J82: ='02A_Debt Schedule'!G90 -> 0 | K82: ='02A_Debt Schedule'!H90 -> 0 | L82: ='02A_Debt Schedule'!I90 -> 0 | M82: ='02A_Debt Schedule'!J90 -> 0 | ... Z82: ='02A_Debt Schedule'!W90 -> 0
B83: Murray Manor | F83: ='02A_Debt Schedule'!C100 -> 4931606 | G83: ='02A_Debt Schedule'!D100 -> 4867662.8 | H83: ='02A_Debt Schedule'!E100 -> 4801027.6 | I83: ='02A_Debt Schedule'!F100 -> 4731587 | J83: ='02A_Debt Schedule'!G100 -> 4659223 | K83: ='02A_Debt Schedule'!H100 -> 4583812.4 | L83: ='02A_Debt Schedule'!I100 -> 4505227.1 | M83: ='02A_Debt Schedule'!J100 -> 4423333.3 | ... Z83: ='02A_Debt Schedule'!W100 -> 5524910.6
B84: Natalia Terrace | F84: ='02A_Debt Schedule'!C110 -> 231219.36 | G84: ='02A_Debt Schedule'!D110 -> 0 | H84: ='02A_Debt Schedule'!E110 -> 0 | I84: ='02A_Debt Schedule'!F110 -> 0 | J84: ='02A_Debt Schedule'!G110 -> 0 | K84: ='02A_Debt Schedule'!H110 -> 0 | L84: ='02A_Debt Schedule'!I110 -> 0 | M84: ='02A_Debt Schedule'!J110 -> 0 | ... Z84: ='02A_Debt Schedule'!W110 -> 0
B85: Newton Green | F85: ='02A_Debt Schedule'!C120 -> 3142456.2 | G85: ='02A_Debt Schedule'!D120 -> 2839579.9 | H85: ='02A_Debt Schedule'!E120 -> 2523180.1 | I85: ='02A_Debt Schedule'!F120 -> 2192653.1 | J85: ='02A_Debt Schedule'!G120 -> 1847368 | K85: ='02A_Debt Schedule'!H120 -> 1486666 | L85: ='02A_Debt Schedule'!I120 -> 1109858.7 | M85: ='02A_Debt Schedule'!J120 -> 716226.86 | ... Z85: ='02A_Debt Schedule'!W120 -> 4999288.8
B86: Rosemary Green | F86: ='02A_Debt Schedule'!C130 -> 1733057.2 | G86: ='02A_Debt Schedule'!D130 -> 1483504.3 | H86: ='02A_Debt Schedule'!E130 -> 1227962.1 | I86: ='02A_Debt Schedule'!F130 -> 966286.9 | J86: ='02A_Debt Schedule'!G130 -> 698331.51 | K86: ='02A_Debt Schedule'!H130 -> 423945.19 | L86: ='02A_Debt Schedule'!I130 -> 142973.59 | M86: ='02A_Debt Schedule'!J130 -> 0 | ... Z86: ='02A_Debt Schedule'!W130 -> 0
B87: 1656 Adanac Street | F87: ='02A_Debt Schedule'!C140 -> 38933496 | G87: ='02A_Debt Schedule'!D140 -> 38566174 | H87: ='02A_Debt Schedule'!E140 -> 38182323 | I87: ='02A_Debt Schedule'!F140 -> 37781198 | J87: ='02A_Debt Schedule'!G140 -> 14963759 | K87: ='02A_Debt Schedule'!H140 -> 14756660 | L87: ='02A_Debt Schedule'!I140 -> 14541277 | M87: ='02A_Debt Schedule'!J140 -> 14317278 | ... Z87: ='02A_Debt Schedule'!W140 -> 10443917
B88: 450 Pacific Street | F88: ='02A_Debt Schedule'!C150 -> 36525238 | G88: ='02A_Debt Schedule'!D150 -> 36180638 | H88: ='02A_Debt Schedule'!E150 -> 35820530 | I88: ='02A_Debt Schedule'!F150 -> 35444217 | J88: ='02A_Debt Schedule'!G150 -> 12397100 | K88: ='02A_Debt Schedule'!H150 -> 12225523 | L88: ='02A_Debt Schedule'!I150 -> 12047084 | M88: ='02A_Debt Schedule'!J150 -> 11861507 | ... Z88: ='02A_Debt Schedule'!W150 -> 8652524
B89: The Creek, Port Moody | F89: ='02A_Debt Schedule'!C160 -> 1.3165141e+08 | G89: ='02A_Debt Schedule'!D160 -> 1.3040933e+08 | H89: ='02A_Debt Schedule'!E160 -> 1.2911136e+08 | I89: ='02A_Debt Schedule'!F160 -> 57893213 | J89: ='02A_Debt Schedule'!G160 -> 57091968 | K89: ='02A_Debt Schedule'!H160 -> 56258673 | L89: ='02A_Debt Schedule'!I160 -> 55392047 | M89: ='02A_Debt Schedule'!J160 -> 54490755 | ... Z89: ='02A_Debt Schedule'!W160 -> 38905702
B90: 800 Commercial Drive | F90: ='02A_Debt Schedule'!C170 -> 37327991 | G90: ='02A_Debt Schedule'!D170 -> 36975816 | H90: ='02A_Debt Schedule'!E170 -> 36607794 | I90: ='02A_Debt Schedule'!F170 -> 36223211 | J90: ='02A_Debt Schedule'!G170 -> 35821321 | K90: ='02A_Debt Schedule'!H170 -> 18193804 | L90: ='02A_Debt Schedule'!I170 -> 17942001 | M90: ='02A_Debt Schedule'!J170 -> 17680125 | ... Z90: ='02A_Debt Schedule'!W170 -> 13151802
F100: Balloon Payments
B101: Property Name | F101: 2025 | G101: =F101+1 -> 2026 | H101: =G101+1 -> 2027 | I101: =H101+1 -> 2028 | J101: =I101+1 -> 2029 | K101: =J101+1 -> 2030 | L101: =K101+1 -> 2031 | M101: =L101+1 -> 2032 | N101: =M101+1 -> 2033 | ... Z101: =Y101+1 -> 2045
B102: {=_xlfn.UNIQUE('01_Property Summary'!$C$5:$C$21)} -> Alma Blackwell | F102: ='02A_Debt Schedule'!C11 -> 0 | G102: ='02A_Debt Schedule'!D11 -> 0 | H102: ='02A_Debt Schedule'!E11 -> 0 | I102: ='02A_Debt Schedule'!F11 -> 0 | J102: ='02A_Debt Schedule'!G11 -> 0 | K102: ='02A_Debt Schedule'!H11 -> 0 | L102: ='02A_Debt Schedule'!I11 -> 0 | M102: ='02A_Debt Schedule'!J11 -> 0 | ... Z102: ='02A_Debt Schedule'!W11 -> 0
B103: Antkiw Court | F103: ='02A_Debt Schedule'!C21 -> 0 | G103: ='02A_Debt Schedule'!D21 -> 0 | H103: ='02A_Debt Schedule'!E21 -> 0 | I103: ='02A_Debt Schedule'!F21 -> 0 | J103: ='02A_Debt Schedule'!G21 -> 0 | K103: ='02A_Debt Schedule'!H21 -> 0 | L103: ='02A_Debt Schedule'!I21 -> 0 | M103: ='02A_Debt Schedule'!J21 -> 0 | ... Z103: ='02A_Debt Schedule'!W21 -> 0
B104: Beatrice Terrace | F104: ='02A_Debt Schedule'!C31 -> 0 | G104: ='02A_Debt Schedule'!D31 -> 0 | H104: ='02A_Debt Schedule'!E31 -> 0 | I104: ='02A_Debt Schedule'!F31 -> 0 | J104: ='02A_Debt Schedule'!G31 -> 0 | K104: ='02A_Debt Schedule'!H31 -> 0 | L104: ='02A_Debt Schedule'!I31 -> 0 | M104: ='02A_Debt Schedule'!J31 -> 0 | ... Z104: ='02A_Debt Schedule'!W31 -> 0
B105: Capilano House | F105: ='02A_Debt Schedule'!C41 -> 0 | G105: ='02A_Debt Schedule'!D41 -> 0 | H105: ='02A_Debt Schedule'!E41 -> 0 | I105: ='02A_Debt Schedule'!F41 -> 0 | J105: ='02A_Debt Schedule'!G41 -> 0 | K105: ='02A_Debt Schedule'!H41 -> 0 | L105: ='02A_Debt Schedule'!I41 -> 0 | M105: ='02A_Debt Schedule'!J41 -> 0 | ... Z105: ='02A_Debt Schedule'!W41 -> 0
B106: Constance Court | F106: ='02A_Debt Schedule'!C51 -> 0 | G106: ='02A_Debt Schedule'!D51 -> 0 | H106: ='02A_Debt Schedule'!E51 -> 0 | I106: ='02A_Debt Schedule'!F51 -> 0 | J106: ='02A_Debt Schedule'!G51 -> 0 | K106: ='02A_Debt Schedule'!H51 -> 0 | L106: ='02A_Debt Schedule'!I51 -> 0 | M106: ='02A_Debt Schedule'!J51 -> 0 | ... Z106: ='02A_Debt Schedule'!W51 -> 0
B107: Evergreen Apartments | F107: ='02A_Debt Schedule'!C61 -> 0 | G107: ='02A_Debt Schedule'!D61 -> 0 | H107: ='02A_Debt Schedule'!E61 -> 0 | I107: ='02A_Debt Schedule'!F61 -> 0 | J107: ='02A_Debt Schedule'!G61 -> 0 | K107: ='02A_Debt Schedule'!H61 -> 0 | L107: ='02A_Debt Schedule'!I61 -> 0 | M107: ='02A_Debt Schedule'!J61 -> 0 | ... Z107: ='02A_Debt Schedule'!W61 -> 0
B108: Evelyn Estates | F108: ='02A_Debt Schedule'!C71 -> 0 | G108: ='02A_Debt Schedule'!D71 -> 0 | H108: ='02A_Debt Schedule'!E71 -> 0 | I108: ='02A_Debt Schedule'!F71 -> 0 | J108: ='02A_Debt Schedule'!G71 -> 0 | K108: ='02A_Debt Schedule'!H71 -> 0 | L108: ='02A_Debt Schedule'!I71 -> 0 | M108: ='02A_Debt Schedule'!J71 -> 0 | ... Z108: ='02A_Debt Schedule'!W71 -> 0
B109: Jessica Place | F109: ='02A_Debt Schedule'!C81 -> 0 | G109: ='02A_Debt Schedule'!D81 -> 0 | H109: ='02A_Debt Schedule'!E81 -> 0 | I109: ='02A_Debt Schedule'!F81 -> 0 | J109: ='02A_Debt Schedule'!G81 -> 0 | K109: ='02A_Debt Schedule'!H81 -> 0 | L109: ='02A_Debt Schedule'!I81 -> 0 | M109: ='02A_Debt Schedule'!J81 -> 0 | ... Z109: ='02A_Debt Schedule'!W81 -> 0
B110: Margaret Heights | F110: ='02A_Debt Schedule'!C91 -> 0 | G110: ='02A_Debt Schedule'!D91 -> 0 | H110: ='02A_Debt Schedule'!E91 -> 0 | I110: ='02A_Debt Schedule'!F91 -> 0 | J110: ='02A_Debt Schedule'!G91 -> 0 | K110: ='02A_Debt Schedule'!H91 -> 0 | L110: ='02A_Debt Schedule'!I91 -> 0 | M110: ='02A_Debt Schedule'!J91 -> 0 | ... Z110: ='02A_Debt Schedule'!W91 -> 0
B111: Murray Manor | F111: ='02A_Debt Schedule'!C101 -> 0 | G111: ='02A_Debt Schedule'!D101 -> 0 | H111: ='02A_Debt Schedule'!E101 -> 0 | I111: ='02A_Debt Schedule'!F101 -> 0 | J111: ='02A_Debt Schedule'!G101 -> 0 | K111: ='02A_Debt Schedule'!H101 -> 0 | L111: ='02A_Debt Schedule'!I101 -> 0 | M111: ='02A_Debt Schedule'!J101 -> 0 | ... Z111: ='02A_Debt Schedule'!W101 -> 0
B112: Natalia Terrace | F112: ='02A_Debt Schedule'!C111 -> 0 | G112: ='02A_Debt Schedule'!D111 -> 0 | H112: ='02A_Debt Schedule'!E111 -> 0 | I112: ='02A_Debt Schedule'!F111 -> 0 | J112: ='02A_Debt Schedule'!G111 -> 0 | K112: ='02A_Debt Schedule'!H111 -> 0 | L112: ='02A_Debt Schedule'!I111 -> 0 | M112: ='02A_Debt Schedule'!J111 -> 0 | ... Z112: ='02A_Debt Schedule'!W111 -> 0
B113: Newton Green | F113: ='02A_Debt Schedule'!C121 -> 0 | G113: ='02A_Debt Schedule'!D121 -> 0 | H113: ='02A_Debt Schedule'!E121 -> 0 | I113: ='02A_Debt Schedule'!F121 -> 0 | J113: ='02A_Debt Schedule'!G121 -> 0 | K113: ='02A_Debt Schedule'!H121 -> 0 | L113: ='02A_Debt Schedule'!I121 -> 0 | M113: ='02A_Debt Schedule'!J121 -> 0 | ... Z113: ='02A_Debt Schedule'!W121 -> 0
B114: Rosemary Green | F114: ='02A_Debt Schedule'!C131 -> 0 | G114: ='02A_Debt Schedule'!D131 -> 0 | H114: ='02A_Debt Schedule'!E131 -> 0 | I114: ='02A_Debt Schedule'!F131 -> 0 | J114: ='02A_Debt Schedule'!G131 -> 0 | K114: ='02A_Debt Schedule'!H131 -> 0 | L114: ='02A_Debt Schedule'!I131 -> 0 | M114: ='02A_Debt Schedule'!J131 -> 0 | ... Z114: ='02A_Debt Schedule'!W131 -> 0
B115: 1656 Adanac Street | F115: ='02A_Debt Schedule'!C141 -> 0 | G115: ='02A_Debt Schedule'!D141 -> 0 | H115: ='02A_Debt Schedule'!E141 -> 0 | I115: ='02A_Debt Schedule'!F141 -> -37781198 | J115: ='02A_Debt Schedule'!G141 -> 0 | K115: ='02A_Debt Schedule'!H141 -> 0 | L115: ='02A_Debt Schedule'!I141 -> 0 | M115: ='02A_Debt Schedule'!J141 -> 0 | ... Z115: ='02A_Debt Schedule'!W141 -> 0
B116: 450 Pacific Street | F116: ='02A_Debt Schedule'!C151 -> 0 | G116: ='02A_Debt Schedule'!D151 -> 0 | H116: ='02A_Debt Schedule'!E151 -> 0 | I116: ='02A_Debt Schedule'!F151 -> -35444217 | J116: ='02A_Debt Schedule'!G151 -> 0 | K116: ='02A_Debt Schedule'!H151 -> 0 | L116: ='02A_Debt Schedule'!I151 -> 0 | M116: ='02A_Debt Schedule'!J151 -> 0 | ... Z116: ='02A_Debt Schedule'!W151 -> 0
B117: The Creek, Port Moody | F117: ='02A_Debt Schedule'!C161 -> 0 | G117: ='02A_Debt Schedule'!D161 -> 0 | H117: ='02A_Debt Schedule'!E161 -> -1.2911136e+08 | I117: ='02A_Debt Schedule'!F161 -> 0 | J117: ='02A_Debt Schedule'!G161 -> 0 | K117: ='02A_Debt Schedule'!H161 -> 0 | L117: ='02A_Debt Schedule'!I161 -> 0 | M117: ='02A_Debt Schedule'!J161 -> 0 | ... Z117: ='02A_Debt Schedule'!W161 -> 0
B118: 800 Commercial Drive | F118: ='02A_Debt Schedule'!C171 -> 0 | G118: ='02A_Debt Schedule'!D171 -> 0 | H118: ='02A_Debt Schedule'!E171 -> 0 | I118: ='02A_Debt Schedule'!F171 -> 0 | J118: ='02A_Debt Schedule'!G171 -> -35821321 | K118: ='02A_Debt Schedule'!H171 -> 0 | L118: ='02A_Debt Schedule'!I171 -> 0 | M118: ='02A_Debt Schedule'!J171 -> 0 | ... Z118: ='02A_Debt Schedule'!W171 -> 0
F128: Refinancing Proceeds
B129: Property Name | F129: 2025 | G129: =F129+1 -> 2026 | H129: =G129+1 -> 2027 | I129: =H129+1 -> 2028 | J129: =I129+1 -> 2029 | K129: =J129+1 -> 2030 | L129: =K129+1 -> 2031 | M129: =L129+1 -> 2032 | N129: =M129+1 -> 2033 | ... Z129: =Y129+1 -> 2045
B130: {=_xlfn.UNIQUE('01_Property Summary'!$C$5:$C$21)} -> Alma Blackwell | F130: ='02A_Debt Schedule'!C12 -> 0 | G130: ='02A_Debt Schedule'!D12 -> 0 | H130: ='02A_Debt Schedule'!E12 -> 0 | I130: ='02A_Debt Schedule'!F12 -> 0 | J130: ='02A_Debt Schedule'!G12 -> 0 | K130: ='02A_Debt Schedule'!H12 -> 0 | L130: ='02A_Debt Schedule'!I12 -> 0 | M130: ='02A_Debt Schedule'!J12 -> 0 | ... Z130: ='02A_Debt Schedule'!W12 -> 0
B131: Antkiw Court | F131: ='02A_Debt Schedule'!C22 -> 0 | G131: ='02A_Debt Schedule'!D22 -> 0 | H131: ='02A_Debt Schedule'!E22 -> 0 | I131: ='02A_Debt Schedule'!F22 -> 0 | J131: ='02A_Debt Schedule'!G22 -> 0 | K131: ='02A_Debt Schedule'!H22 -> 0 | L131: ='02A_Debt Schedule'!I22 -> 0 | M131: ='02A_Debt Schedule'!J22 -> 0 | ... Z131: ='02A_Debt Schedule'!W22 -> 0
B132: Beatrice Terrace | F132: ='02A_Debt Schedule'!C32 -> 0 | G132: ='02A_Debt Schedule'!D32 -> 0 | H132: ='02A_Debt Schedule'!E32 -> 0 | I132: ='02A_Debt Schedule'!F32 -> 0 | J132: ='02A_Debt Schedule'!G32 -> 0 | K132: ='02A_Debt Schedule'!H32 -> 0 | L132: ='02A_Debt Schedule'!I32 -> 0 | M132: ='02A_Debt Schedule'!J32 -> 0 | ... Z132: ='02A_Debt Schedule'!W32 -> 0
B133: Capilano House | F133: ='02A_Debt Schedule'!C42 -> 0 | G133: ='02A_Debt Schedule'!D42 -> 0 | H133: ='02A_Debt Schedule'!E42 -> 0 | I133: ='02A_Debt Schedule'!F42 -> 0 | J133: ='02A_Debt Schedule'!G42 -> 0 | K133: ='02A_Debt Schedule'!H42 -> 0 | L133: ='02A_Debt Schedule'!I42 -> 0 | M133: ='02A_Debt Schedule'!J42 -> 0 | ... Z133: ='02A_Debt Schedule'!W42 -> 0
B134: Constance Court | F134: ='02A_Debt Schedule'!C52 -> 0 | G134: ='02A_Debt Schedule'!D52 -> 0 | H134: ='02A_Debt Schedule'!E52 -> 0 | I134: ='02A_Debt Schedule'!F52 -> 0 | J134: ='02A_Debt Schedule'!G52 -> 0 | K134: ='02A_Debt Schedule'!H52 -> 0 | L134: ='02A_Debt Schedule'!I52 -> 0 | M134: ='02A_Debt Schedule'!J52 -> 0 | ... Z134: ='02A_Debt Schedule'!W52 -> 0
B135: Evergreen Apartments | F135: ='02A_Debt Schedule'!C62 -> 0 | G135: ='02A_Debt Schedule'!D62 -> 0 | H135: ='02A_Debt Schedule'!E62 -> 0 | I135: ='02A_Debt Schedule'!F62 -> 0 | J135: ='02A_Debt Schedule'!G62 -> 0 | K135: ='02A_Debt Schedule'!H62 -> 0 | L135: ='02A_Debt Schedule'!I62 -> 0 | M135: ='02A_Debt Schedule'!J62 -> 0 | ... Z135: ='02A_Debt Schedule'!W62 -> 0
B136: Evelyn Estates | F136: ='02A_Debt Schedule'!C72 -> 0 | G136: ='02A_Debt Schedule'!D72 -> 0 | H136: ='02A_Debt Schedule'!E72 -> 0 | I136: ='02A_Debt Schedule'!F72 -> 0 | J136: ='02A_Debt Schedule'!G72 -> 0 | K136: ='02A_Debt Schedule'!H72 -> 0 | L136: ='02A_Debt Schedule'!I72 -> 0 | M136: ='02A_Debt Schedule'!J72 -> 0 | ... Z136: ='02A_Debt Schedule'!W72 -> 0
B137: Jessica Place | F137: ='02A_Debt Schedule'!C82 -> 0 | G137: ='02A_Debt Schedule'!D82 -> 0 | H137: ='02A_Debt Schedule'!E82 -> 0 | I137: ='02A_Debt Schedule'!F82 -> 0 | J137: ='02A_Debt Schedule'!G82 -> 0 | K137: ='02A_Debt Schedule'!H82 -> 0 | L137: ='02A_Debt Schedule'!I82 -> 0 | M137: ='02A_Debt Schedule'!J82 -> 0 | ... Z137: ='02A_Debt Schedule'!W82 -> 0
B138: Margaret Heights | F138: ='02A_Debt Schedule'!C92 -> 0 | G138: ='02A_Debt Schedule'!D92 -> 0 | H138: ='02A_Debt Schedule'!E92 -> 0 | I138: ='02A_Debt Schedule'!F92 -> 0 | J138: ='02A_Debt Schedule'!G92 -> 0 | K138: ='02A_Debt Schedule'!H92 -> 0 | L138: ='02A_Debt Schedule'!I92 -> 0 | M138: ='02A_Debt Schedule'!J92 -> 0 | ... Z138: ='02A_Debt Schedule'!W92 -> 0
...

Sheet 02A_Debt Schedule
B2: DEBT SCHEDULE (2026)
B4: Line Item | C4: 2025 | D4: =C4+1 -> 2026 | E4: =D4+1 -> 2027 | F4: =E4+1 -> 2028 | G4: =F4+1 -> 2029 | H4: =G4+1 -> 2030 | I4: =H4+1 -> 2031 | J4: =I4+1 -> 2032 | K4: =J4+1 -> 2033 | ... W4: =V4+1 -> 2045
B6: ='02_Debt Engine'!$B$19 -> Alma Blackwell | C6: =_xlfn.LET(_xlpm.refiyr,INDEX('02_Debt Engine'!$I$19:$I$35,MATCH('02A_Debt Schedule'!$B6,'02_Debt Engine'!$B$19:$B$35,0)),IF(_xlpm.refiyr='02A_Debt Schedule'!C$4,"Refi Yr.","")) | D6: =_xlfn.LET(_xlpm.refiyr,INDEX('02_Debt Engine'!$I$19:$I$35,MATCH('02A_Debt Schedule'!$B6,'02_Debt Engine'!$B$19:$B$35,0)),IF(_xlpm.refiyr='02A_Debt Schedule'!D$4,"Refi Yr.","")) | E6: =_xlfn.LET(_xlpm.refiyr,INDEX('02_Debt Engine'!$I$19:$I$35,MATCH('02A_Debt Schedule'!$B6,'02_Debt Engine'!$B$19:$B$35,0)),IF(_xlpm.refiyr='02A_Debt Schedule'!E$4,"Refi Yr.","")) | F6: =_xlfn.LET(_xlpm.refiyr,INDEX('02_Debt Engine'!$I$19:$I$35,MATCH('02A_Debt Schedule'!$B6,'02_Debt Engine'!$B$19:$B$35,0)),IF(_xlpm.refiyr='02A_Debt Schedule'!F$4,"Refi Yr.","")) | G6: =_xlfn.LET(_xlpm.refiyr,INDEX('02_Debt Engine'!$I$19:$I$35,MATCH('02A_Debt Schedule'!$B6,'02_Debt Engine'!$B$19:$B$35,0)),IF(_xlpm.refiyr='02A_Debt Schedule'!G$4,"Refi Yr.","")) | H6: =_xlfn.LET(_xlpm.refiyr,INDEX('02_Debt Engine'!$I$19:$I$35,MATCH('02A_Debt Schedule'!$B6,'02_Debt Engine'!$B$19:$B$35,0)),IF(_xlpm.refiyr='02A_Debt Schedule'!H$4,"Refi Yr.","")) | I6: =_xlfn.LET(_xlpm.refiyr,INDEX('02_Debt Engine'!$I$19:$I$35,MATCH('02A_Debt Schedule'!$B6,'02_Debt Engine'!$B$19:$B$35,0)),IF(_xlpm.refiyr='02A_Debt Schedule'!I$4,"Refi Yr.","")) | J6: =_xlfn.LET(_xlpm.refiyr,INDEX('02_Debt Engine'!$I$19:$I$35,MATCH('02A_Debt Schedule'!$B6,'02_Debt Engine'!$B$19:$B$35,0)),IF(_xlpm.refiyr='02A_Debt Schedule'!J$4,"Refi Yr.","")) | ... W6: =_xlfn.LET(_xlpm.refiyr,INDEX('02_Debt Engine'!$I$19:$I$35,MATCH('02A_Debt Schedule'!$B6,'02_Debt Engine'!$B$19:$B$35,0)),IF(_xlpm.refiyr='02A_Debt Schedule'!W$4,"Refi Yr.",""))
B7: Beginning Balance | C7: =IF('02_Debt Engine'!$D$19="Active",'02_Debt Engine'!$N$19,'02_Debt Engine'!$O$19) -> 0 | D7: =IF(AND('02_Debt Engine'!$F$19="Yes",'02_Debt Engine'!$V$19>0,C$4='02_Debt Engine'!$I$19),'02_Debt Engine'!$V$19,C10) -> 0 | E7: =IF(AND('02_Debt Engine'!$F$19="Yes",'02_Debt Engine'!$V$19>0,D$4='02_Debt Engine'!$I$19),'02_Debt Engine'!$V$19,D10) -> 0 | F7: =IF(AND('02_Debt Engine'!$F$19="Yes",'02_Debt Engine'!$V$19>0,E$4='02_Debt Engine'!$I$19),'02_Debt Engine'!$V$19,E10) -> 0 | G7: =IF(AND('02_Debt Engine'!$F$19="Yes",'02_Debt Engine'!$V$19>0,F$4='02_Debt Engine'!$I$19),'02_Debt Engine'!$V$19,F10) -> 0 | H7: =IF(AND('02_Debt Engine'!$F$19="Yes",'02_Debt Engine'!$V$19>0,G$4='02_Debt Engine'!$I$19),'02_Debt Engine'!$V$19,G10) -> 0 | I7: =IF(AND('02_Debt Engine'!$F$19="Yes",'02_Debt Engine'!$V$19>0,H$4='02_Debt Engine'!$I$19),'02_Debt Engine'!$V$19,H10) -> 0 | J7: =IF(AND('02_Debt Engine'!$F$19="Yes",'02_Debt Engine'!$V$19>0,I$4='02_Debt Engine'!$I$19),'02_Debt Engine'!$V$19,I10) -> 0 | K7: =IF(AND('02_Debt Engine'!$F$19="Yes",'02_Debt Engine'!$V$19>0,J$4='02_Debt Engine'!$I$19),'02_Debt Engine'!$V$19,J10) -> 0 | ... W7: =IF(AND('02_Debt Engine'!$F$19="Yes",'02_Debt Engine'!$V$19>0,V$4='02_Debt Engine'!$I$19),'02_Debt Engine'!$V$19,V10) -> 0
B8: Interest PMT | C8: =IF(C7<=0,0,C7*IF(AND('02_Debt Engine'!$F$19="Yes",'02_Debt Engine'!$V$19>0,C$4>'02_Debt Engine'!$I$19),'02_Debt Engine'!$C$13,IF('02_Debt Engine'!$D$19="Active",'02_Debt Engine'!$H$19,'02_Debt Engine'!$C$7))) -> 0 | D8: =IF(D7<=0,0,D7*IF(AND('02_Debt Engine'!$F$19="Yes",'02_Debt Engine'!$V$19>0,D$4>'02_Debt Engine'!$I$19),'02_Debt Engine'!$C$13,IF('02_Debt Engine'!$D$19="Active",'02_Debt Engine'!$H$19,'02_Debt Engine'!$C$7))) -> 0 | E8: =IF(E7<=0,0,E7*IF(AND('02_Debt Engine'!$F$19="Yes",'02_Debt Engine'!$V$19>0,E$4>'02_Debt Engine'!$I$19),'02_Debt Engine'!$C$13,IF('02_Debt Engine'!$D$19="Active",'02_Debt Engine'!$H$19,'02_Debt Engine'!$C$7))) -> 0 | F8: =IF(F7<=0,0,F7*IF(AND('02_Debt Engine'!$F$19="Yes",'02_Debt Engine'!$V$19>0,F$4>'02_Debt Engine'!$I$19),'02_Debt Engine'!$C$13,IF('02_Debt Engine'!$D$19="Active",'02_Debt Engine'!$H$19,'02_Debt Engine'!$C$7))) -> 0 | G8: =IF(G7<=0,0,G7*IF(AND('02_Debt Engine'!$F$19="Yes",'02_Debt Engine'!$V$19>0,G$4>'02_Debt Engine'!$I$19),'02_Debt Engine'!$C$13,IF('02_Debt Engine'!$D$19="Active",'02_Debt Engine'!$H$19,'02_Debt Engine'!$C$7))) -> 0 | H8: =IF(H7<=0,0,H7*IF(AND('02_Debt Engine'!$F$19="Yes",'02_Debt Engine'!$V$19>0,H$4>'02_Debt Engine'!$I$19),'02_Debt Engine'!$C$13,IF('02_Debt Engine'!$D$19="Active",'02_Debt Engine'!$H$19,'02_Debt Engine'!$C$7))) -> 0 | I8: =IF(I7<=0,0,I7*IF(AND('02_Debt Engine'!$F$19="Yes",'02_Debt Engine'!$V$19>0,I$4>'02_Debt Engine'!$I$19),'02_Debt Engine'!$C$13,IF('02_Debt Engine'!$D$19="Active",'02_Debt Engine'!$H$19,'02_Debt Engine'!$C$7))) -> 0 | J8: =IF(J7<=0,0,J7*IF(AND('02_Debt Engine'!$F$19="Yes",'02_Debt Engine'!$V$19>0,J$4>'02_Debt Engine'!$I$19),'02_Debt Engine'!$C$13,IF('02_Debt Engine'!$D$19="Active",'02_Debt Engine'!$H$19,'02_Debt Engine'!$C$7))) -> 0 | ... W8: =IF(W7<=0,0,W7*IF(AND('02_Debt Engine'!$F$19="Yes",'02_Debt Engine'!$V$19>0,W$4>'02_Debt Engine'!$I$19),'02_Debt Engine'!$C$13,IF('02_Debt Engine'!$D$19="Active",'02_Debt Engine'!$H$19,'02_Debt Engine'!$C$7))) -> 0
B9: Principal PMT | C9: =IF(C7<=0,0,MIN(C7,IF(AND('02_Debt Engine'!$F$19="Yes",'02_Debt Engine'!$V$19>0,C$4>'02_Debt Engine'!$I$19),'02_Debt Engine'!$W$19,IF('02_Debt Engine'!$D$19="Active",'02_Debt Engine'!$K$19,'02_Debt Engine'!$P$19))-C8)) -> 0 | D9: =IF(D7<=0,0,MIN(D7,IF(AND('02_Debt Engine'!$F$19="Yes",'02_Debt Engine'!$V$19>0,D$4>'02_Debt Engine'!$I$19),'02_Debt Engine'!$W$19,IF('02_Debt Engine'!$D$19="Active",'02_Debt Engine'!$K$19,'02_Debt Engine'!$P$19))-D8)) -> 0 | E9: =IF(E7<=0,0,MIN(E7,IF(AND('02_Debt Engine'!$F$19="Yes",'02_Debt Engine'!$V$19>0,E$4>'02_Debt Engine'!$I$19),'02_Debt Engine'!$W$19,IF('02_Debt Engine'!$D$19="Active",'02_Debt Engine'!$K$19,'02_Debt Engine'!$P$19))-E8)) -> 0 | F9: =IF(F7<=0,0,MIN(F7,IF(AND('02_Debt Engine'!$F$19="Yes",'02_Debt Engine'!$V$19>0,F$4>'02_Debt Engine'!$I$19),'02_Debt Engine'!$W$19,IF('02_Debt Engine'!$D$19="Active",'02_Debt Engine'!$K$19,'02_Debt Engine'!$P$19))-F8)) -> 0 | G9: =IF(G7<=0,0,MIN(G7,IF(AND('02_Debt Engine'!$F$19="Yes",'02_Debt Engine'!$V$19>0,G$4>'02_Debt Engine'!$I$19),'02_Debt Engine'!$W$19,IF('02_Debt Engine'!$D$19="Active",'02_Debt Engine'!$K$19,'02_Debt Engine'!$P$19))-G8)) -> 0 | H9: =IF(H7<=0,0,MIN(H7,IF(AND('02_Debt Engine'!$F$19="Yes",'02_Debt Engine'!$V$19>0,H$4>'02_Debt Engine'!$I$19),'02_Debt Engine'!$W$19,IF('02_Debt Engine'!$D$19="Active",'02_Debt Engine'!$K$19,'02_Debt Engine'!$P$19))-H8)) -> 0 | I9: =IF(I7<=0,0,MIN(I7,IF(AND('02_Debt Engine'!$F$19="Yes",'02_Debt Engine'!$V$19>0,I$4>'02_Debt Engine'!$I$19),'02_Debt Engine'!$W$19,IF('02_Debt Engine'!$D$19="Active",'02_Debt Engine'!$K$19,'02_Debt Engine'!$P$19))-I8)) -> 0 | J9: =IF(J7<=0,0,MIN(J7,IF(AND('02_Debt Engine'!$F$19="Yes",'02_Debt Engine'!$V$19>0,J$4>'02_Debt Engine'!$I$19),'02_Debt Engine'!$W$19,IF('02_Debt Engine'!$D$19="Active",'02_Debt Engine'!$K$19,'02_Debt Engine'!$P$19))-J8)) -> 0 | ... W9: =IF(W7<=0,0,MIN(W7,IF(AND('02_Debt Engine'!$F$19="Yes",'02_Debt Engine'!$V$19>0,W$4>'02_Debt Engine'!$I$19),'02_Debt Engine'!$W$19,IF('02_Debt Engine'!$D$19="Active",'02_Debt Engine'!$K$19,'02_Debt Engine'!$P$19))-W8)) -> 0
B10: End Balance | C10: =C7-C9 -> 0 | D10: =D7-D9 -> 0 | E10: =E7-E9 -> 0 | F10: =F7-F9 -> 0 | G10: =G7-G9 -> 0 | H10: =H7-H9 -> 0 | I10: =I7-I9 -> 0 | J10: =J7-J9 -> 0 | ... W10: =W7-W9 -> 0
B11: Balloon Payment | C11: =IF(AND('02_Debt Engine'!$F$19="Yes",'02_Debt Engine'!$V$19>0,C$4='02_Debt Engine'!$I$19),-C10,0) -> 0 | D11: =IF(AND('02_Debt Engine'!$F$19="Yes",'02_Debt Engine'!$V$19>0,D$4='02_Debt Engine'!$I$19),-D10,0) -> 0 | E11: =IF(AND('02_Debt Engine'!$F$19="Yes",'02_Debt Engine'!$V$19>0,E$4='02_Debt Engine'!$I$19),-E10,0) -> 0 | F11: =IF(AND('02_Debt Engine'!$F$19="Yes",'02_Debt Engine'!$V$19>0,F$4='02_Debt Engine'!$I$19),-F10,0) -> 0 | G11: =IF(AND('02_Debt Engine'!$F$19="Yes",'02_Debt Engine'!$V$19>0,G$4='02_Debt Engine'!$I$19),-G10,0) -> 0 | H11: =IF(AND('02_Debt Engine'!$F$19="Yes",'02_Debt Engine'!$V$19>0,H$4='02_Debt Engine'!$I$19),-H10,0) -> 0 | I11: =IF(AND('02_Debt Engine'!$F$19="Yes",'02_Debt Engine'!$V$19>0,I$4='02_Debt Engine'!$I$19),-I10,0) -> 0 | J11: =IF(AND('02_Debt Engine'!$F$19="Yes",'02_Debt Engine'!$V$19>0,J$4='02_Debt Engine'!$I$19),-J10,0) -> 0 | ... W11: =IF(AND('02_Debt Engine'!$F$19="Yes",'02_Debt Engine'!$V$19>0,W$4='02_Debt Engine'!$I$19),-W10,0) -> 0
B12: Refinance Proceeds | C12: =IF(AND('02_Debt Engine'!$F$19="Yes",'02_Debt Engine'!$V$19>0,C$4='02_Debt Engine'!$I$19),'02_Debt Engine'!$V$19,0) -> 0 | D12: =IF(AND('02_Debt Engine'!$F$19="Yes",'02_Debt Engine'!$V$19>0,D$4='02_Debt Engine'!$I$19),'02_Debt Engine'!$V$19,0) -> 0 | E12: =IF(AND('02_Debt Engine'!$F$19="Yes",'02_Debt Engine'!$V$19>0,E$4='02_Debt Engine'!$I$19),'02_Debt Engine'!$V$19,0) -> 0 | F12: =IF(AND('02_Debt Engine'!$F$19="Yes",'02_Debt Engine'!$V$19>0,F$4='02_Debt Engine'!$I$19),'02_Debt Engine'!$V$19,0) -> 0 | G12: =IF(AND('02_Debt Engine'!$F$19="Yes",'02_Debt Engine'!$V$19>0,G$4='02_Debt Engine'!$I$19),'02_Debt Engine'!$V$19,0) -> 0 | H12: =IF(AND('02_Debt Engine'!$F$19="Yes",'02_Debt Engine'!$V$19>0,H$4='02_Debt Engine'!$I$19),'02_Debt Engine'!$V$19,0) -> 0 | I12: =IF(AND('02_Debt Engine'!$F$19="Yes",'02_Debt Engine'!$V$19>0,I$4='02_Debt Engine'!$I$19),'02_Debt Engine'!$V$19,0) -> 0 | J12: =IF(AND('02_Debt Engine'!$F$19="Yes",'02_Debt Engine'!$V$19>0,J$4='02_Debt Engine'!$I$19),'02_Debt Engine'!$V$19,0) -> 0 | ... W12: =IF(AND('02_Debt Engine'!$F$19="Yes",'02_Debt Engine'!$V$19>0,W$4='02_Debt Engine'!$I$19),'02_Debt Engine'!$V$19,0) -> 0
B13: Net Refinancing | C13: =C11+C12 -> 0 | D13: =D11+D12 -> 0 | E13: =E11+E12 -> 0 | F13: =F11+F12 -> 0 | G13: =G11+G12 -> 0 | H13: =H11+H12 -> 0 | I13: =I11+I12 -> 0 | J13: =J11+J12 -> 0 | ... W13: =W11+W12 -> 0
B14: Total Debt Service | C14: =C8+C9 -> 0 | D14: =D8+D9 -> 0 | E14: =E8+E9 -> 0 | F14: =F8+F9 -> 0 | G14: =G8+G9 -> 0 | H14: =H8+H9 -> 0 | I14: =I8+I9 -> 0 | J14: =J8+J9 -> 0 | ... W14: =W8+W9 -> 0
B16: ='02_Debt Engine'!$B$20 -> Antkiw Court | C16: =_xlfn.LET(_xlpm.refiyr,INDEX('02_Debt Engine'!$I$19:$I$35,MATCH('02A_Debt Schedule'!$B16,'02_Debt Engine'!$B$19:$B$35,0)),IF(_xlpm.refiyr='02A_Debt Schedule'!C$4,"Refi Yr.","")) | D16: =_xlfn.LET(_xlpm.refiyr,INDEX('02_Debt Engine'!$I$19:$I$35,MATCH('02A_Debt Schedule'!$B16,'02_Debt Engine'!$B$19:$B$35,0)),IF(_xlpm.refiyr='02A_Debt Schedule'!D$4,"Refi Yr.","")) | E16: =_xlfn.LET(_xlpm.refiyr,INDEX('02_Debt Engine'!$I$19:$I$35,MATCH('02A_Debt Schedule'!$B16,'02_Debt Engine'!$B$19:$B$35,0)),IF(_xlpm.refiyr='02A_Debt Schedule'!E$4,"Refi Yr.","")) | F16: =_xlfn.LET(_xlpm.refiyr,INDEX('02_Debt Engine'!$I$19:$I$35,MATCH('02A_Debt Schedule'!$B16,'02_Debt Engine'!$B$19:$B$35,0)),IF(_xlpm.refiyr='02A_Debt Schedule'!F$4,"Refi Yr.","")) | G16: =_xlfn.LET(_xlpm.refiyr,INDEX('02_Debt Engine'!$I$19:$I$35,MATCH('02A_Debt Schedule'!$B16,'02_Debt Engine'!$B$19:$B$35,0)),IF(_xlpm.refiyr='02A_Debt Schedule'!G$4,"Refi Yr.","")) | H16: =_xlfn.LET(_xlpm.refiyr,INDEX('02_Debt Engine'!$I$19:$I$35,MATCH('02A_Debt Schedule'!$B16,'02_Debt Engine'!$B$19:$B$35,0)),IF(_xlpm.refiyr='02A_Debt Schedule'!H$4,"Refi Yr.","")) | I16: =_xlfn.LET(_xlpm.refiyr,INDEX('02_Debt Engine'!$I$19:$I$35,MATCH('02A_Debt Schedule'!$B16,'02_Debt Engine'!$B$19:$B$35,0)),IF(_xlpm.refiyr='02A_Debt Schedule'!I$4,"Refi Yr.","")) | J16: =_xlfn.LET(_xlpm.refiyr,INDEX('02_Debt Engine'!$I$19:$I$35,MATCH('02A_Debt Schedule'!$B16,'02_Debt Engine'!$B$19:$B$35,0)),IF(_xlpm.refiyr='02A_Debt Schedule'!J$4,"Refi Yr.","")) | ... W16: =_xlfn.LET(_xlpm.refiyr,INDEX('02_Debt Engine'!$I$19:$I$35,MATCH('02A_Debt Schedule'!$B16,'02_Debt Engine'!$B$19:$B$35,0)),IF(_xlpm.refiyr='02A_Debt Schedule'!W$4,"Refi Yr.",""))
B17: Beginning Balance | C17: =IF('02_Debt Engine'!$D$20="Active",'02_Debt Engine'!$N$20,'02_Debt Engine'!$O$20) -> 794745.17 | D17: =IF(AND('02_Debt Engine'!$F$20="Yes",'02_Debt Engine'!$V$20>0,C$4='02_Debt Engine'!$I$20),'02_Debt Engine'!$V$20,C20) -> 772395.6 | E17: =IF(AND('02_Debt Engine'!$F$20="Yes",'02_Debt Engine'!$V$20>0,D$4='02_Debt Engine'!$I$20),'02_Debt Engine'!$V$20,D20) -> 749146.67 | F17: =IF(AND('02_Debt Engine'!$F$20="Yes",'02_Debt Engine'!$V$20>0,E$4='02_Debt Engine'!$I$20),'02_Debt Engine'!$V$20,E20) -> 724962.22 | G17: =IF(AND('02_Debt Engine'!$F$20="Yes",'02_Debt Engine'!$V$20>0,F$4='02_Debt Engine'!$I$20),'02_Debt Engine'!$V$20,F20) -> 699804.58 | H17: =IF(AND('02_Debt Engine'!$F$20="Yes",'02_Debt Engine'!$V$20>0,G$4='02_Debt Engine'!$I$20),'02_Debt Engine'!$V$20,G20) -> 673634.59 | I17: =IF(AND('02_Debt Engine'!$F$20="Yes",'02_Debt Engine'!$V$20>0,H$4='02_Debt Engine'!$I$20),'02_Debt Engine'!$V$20,H20) -> 646411.53 | J17: =IF(AND('02_Debt Engine'!$F$20="Yes",'02_Debt Engine'!$V$20>0,I$4='02_Debt Engine'!$I$20),'02_Debt Engine'!$V$20,I20) -> 618093.01 | K17: =IF(AND('02_Debt Engine'!$F$20="Yes",'02_Debt Engine'!$V$20>0,J$4='02_Debt Engine'!$I$20),'02_Debt Engine'!$V$20,J20) -> 588634.95 | ... W17: =IF(AND('02_Debt Engine'!$F$20="Yes",'02_Debt Engine'!$V$20>0,V$4='02_Debt Engine'!$I$20),'02_Debt Engine'!$V$20,V20) -> 127558.04
B18: Interest PMT | C18: =IF(C17<=0,0,C17*IF(AND('02_Debt Engine'!$F$20="Yes",'02_Debt Engine'!$V$20>0,C$4>'02_Debt Engine'!$I$20),'02_Debt Engine'!$C$13,IF('02_Debt Engine'!$D$20="Active",'02_Debt Engine'!$H$20,'02_Debt Engine'!$C$7))) -> 31980.546 | D18: =IF(D17<=0,0,D17*IF(AND('02_Debt Engine'!$F$20="Yes",'02_Debt Engine'!$V$20>0,D$4>'02_Debt Engine'!$I$20),'02_Debt Engine'!$C$13,IF('02_Debt Engine'!$D$20="Active",'02_Debt Engine'!$H$20,'02_Debt Engine'!$C$7))) -> 31081.199 | E18: =IF(E17<=0,0,E17*IF(AND('02_Debt Engine'!$F$20="Yes",'02_Debt Engine'!$V$20>0,E$4>'02_Debt Engine'!$I$20),'02_Debt Engine'!$C$13,IF('02_Debt Engine'!$D$20="Active",'02_Debt Engine'!$H$20,'02_Debt Engine'!$C$7))) -> 30145.662 | F18: =IF(F17<=0,0,F17*IF(AND('02_Debt Engine'!$F$20="Yes",'02_Debt Engine'!$V$20>0,F$4>'02_Debt Engine'!$I$20),'02_Debt Engine'!$C$13,IF('02_Debt Engine'!$D$20="Active",'02_Debt Engine'!$H$20,'02_Debt Engine'!$C$7))) -> 29172.48 | G18: =IF(G17<=0,0,G17*IF(AND('02_Debt Engine'!$F$20="Yes",'02_Debt Engine'!$V$20>0,G$4>'02_Debt Engine'!$I$20),'02_Debt Engine'!$C$13,IF('02_Debt Engine'!$D$20="Active",'02_Debt Engine'!$H$20,'02_Debt Engine'!$C$7))) -> 28160.136 | H18: =IF(H17<=0,0,H17*IF(AND('02_Debt Engine'!$F$20="Yes",'02_Debt Engine'!$V$20>0,H$4>'02_Debt Engine'!$I$20),'02_Debt Engine'!$C$13,IF('02_Debt Engine'!$D$20="Active",'02_Debt Engine'!$H$20,'02_Debt Engine'!$C$7))) -> 27107.056 | I18: =IF(I17<=0,0,I17*IF(AND('02_Debt Engine'!$F$20="Yes",'02_Debt Engine'!$V$20>0,I$4>'02_Debt Engine'!$I$20),'02_Debt Engine'!$C$13,IF('02_Debt Engine'!$D$20="Active",'02_Debt Engine'!$H$20,'02_Debt Engine'!$C$7))) -> 26011.6 | J18: =IF(J17<=0,0,J17*IF(AND('02_Debt Engine'!$F$20="Yes",'02_Debt Engine'!$V$20>0,J$4>'02_Debt Engine'!$I$20),'02_Debt Engine'!$C$13,IF('02_Debt Engine'!$D$20="Active",'02_Debt Engine'!$H$20,'02_Debt Engine'!$C$7))) -> 24872.063 | ... W18: =IF(W17<=0,0,W17*IF(AND('02_Debt Engine'!$F$20="Yes",'02_Debt Engine'!$V$20>0,W$4>'02_Debt Engine'!$I$20),'02_Debt Engine'!$C$13,IF('02_Debt Engine'!$D$20="Active",'02_Debt Engine'!$H$20,'02_Debt Engine'!$C$7))) -> 5132.9357
B19: Principal PMT | C19: =IF(C17<=0,0,MIN(C17,IF(AND('02_Debt Engine'!$F$20="Yes",'02_Debt Engine'!$V$20>0,C$4>'02_Debt Engine'!$I$20),'02_Debt Engine'!$W$20,IF('02_Debt Engine'!$D$20="Active",'02_Debt Engine'!$K$20,'02_Debt Engine'!$P$20))-C18)) -> 22349.574 | D19: =IF(D17<=0,0,MIN(D17,IF(AND('02_Debt Engine'!$F$20="Yes",'02_Debt Engine'!$V$20>0,D$4>'02_Debt Engine'!$I$20),'02_Debt Engine'!$W$20,IF('02_Debt Engine'!$D$20="Active",'02_Debt Engine'!$K$20,'02_Debt Engine'!$P$20))-D18)) -> 23248.921 | E19: =IF(E17<=0,0,MIN(E17,IF(AND('02_Debt Engine'!$F$20="Yes",'02_Debt Engine'!$V$20>0,E$4>'02_Debt Engine'!$I$20),'02_Debt Engine'!$W$20,IF('02_Debt Engine'!$D$20="Active",'02_Debt Engine'!$K$20,'02_Debt Engine'!$P$20))-E18)) -> 24184.458 | F19: =IF(F17<=0,0,MIN(F17,IF(AND('02_Debt Engine'!$F$20="Yes",'02_Debt Engine'!$V$20>0,F$4>'02_Debt Engine'!$I$20),'02_Debt Engine'!$W$20,IF('02_Debt Engine'!$D$20="Active",'02_Debt Engine'!$K$20,'02_Debt Engine'!$P$20))-F18)) -> 25157.64 | G19: =IF(G17<=0,0,MIN(G17,IF(AND('02_Debt Engine'!$F$20="Yes",'02_Debt Engine'!$V$20>0,G$4>'02_Debt Engine'!$I$20),'02_Debt Engine'!$W$20,IF('02_Debt Engine'!$D$20="Active",'02_Debt Engine'!$K$20,'02_Debt Engine'!$P$20))-G18)) -> 26169.984 | H19: =IF(H17<=0,0,MIN(H17,IF(AND('02_Debt Engine'!$F$20="Yes",'02_Debt Engine'!$V$20>0,H$4>'02_Debt Engine'!$I$20),'02_Debt Engine'!$W$20,IF('02_Debt Engine'!$D$20="Active",'02_Debt Engine'!$K$20,'02_Debt Engine'!$P$20))-H18)) -> 27223.064 | I19: =IF(I17<=0,0,MIN(I17,IF(AND('02_Debt Engine'!$F$20="Yes",'02_Debt Engine'!$V$20>0,I$4>'02_Debt Engine'!$I$20),'02_Debt Engine'!$W$20,IF('02_Debt Engine'!$D$20="Active",'02_Debt Engine'!$K$20,'02_Debt Engine'!$P$20))-I18)) -> 28318.52 | J19: =IF(J17<=0,0,MIN(J17,IF(AND('02_Debt Engine'!$F$20="Yes",'02_Debt Engine'!$V$20>0,J$4>'02_Debt Engine'!$I$20),'02_Debt Engine'!$W$20,IF('02_Debt Engine'!$D$20="Active",'02_Debt Engine'!$K$20,'02_Debt Engine'!$P$20))-J18)) -> 29458.057 | ... W19: =IF(W17<=0,0,MIN(W17,IF(AND('02_Debt Engine'!$F$20="Yes",'02_Debt Engine'!$V$20>0,W$4>'02_Debt Engine'!$I$20),'02_Debt Engine'!$W$20,IF('02_Debt Engine'!$D$20="Active",'02_Debt Engine'!$K$20,'02_Debt Engine'!$P$20))-W18)) -> 49197.184
B20: End Balance | C20: =C17-C19 -> 772395.6 | D20: =D17-D19 -> 749146.67 | E20: =E17-E19 -> 724962.22 | F20: =F17-F19 -> 699804.58 | G20: =G17-G19 -> 673634.59 | H20: =H17-H19 -> 646411.53 | I20: =I17-I19 -> 618093.01 | J20: =J17-J19 -> 588634.95 | ... W20: =W17-W19 -> 78360.86
B21: Balloon Payment | C21: =IF(AND('02_Debt Engine'!$F$20="Yes",'02_Debt Engine'!$V$20>0,C$4='02_Debt Engine'!$I$20),-C20,0) -> 0 | D21: =IF(AND('02_Debt Engine'!$F$20="Yes",'02_Debt Engine'!$V$20>0,D$4='02_Debt Engine'!$I$20),-D20,0) -> 0 | E21: =IF(AND('02_Debt Engine'!$F$20="Yes",'02_Debt Engine'!$V$20>0,E$4='02_Debt Engine'!$I$20),-E20,0) -> 0 | F21: =IF(AND('02_Debt Engine'!$F$20="Yes",'02_Debt Engine'!$V$20>0,F$4='02_Debt Engine'!$I$20),-F20,0) -> 0 | G21: =IF(AND('02_Debt Engine'!$F$20="Yes",'02_Debt Engine'!$V$20>0,G$4='02_Debt Engine'!$I$20),-G20,0) -> 0 | H21: =IF(AND('02_Debt Engine'!$F$20="Yes",'02_Debt Engine'!$V$20>0,H$4='02_Debt Engine'!$I$20),-H20,0) -> 0 | I21: =IF(AND('02_Debt Engine'!$F$20="Yes",'02_Debt Engine'!$V$20>0,I$4='02_Debt Engine'!$I$20),-I20,0) -> 0 | J21: =IF(AND('02_Debt Engine'!$F$20="Yes",'02_Debt Engine'!$V$20>0,J$4='02_Debt Engine'!$I$20),-J20,0) -> 0 | ... W21: =IF(AND('02_Debt Engine'!$F$20="Yes",'02_Debt Engine'!$V$20>0,W$4='02_Debt Engine'!$I$20),-W20,0) -> 0
B22: Refinance Proceeds | C22: =IF(AND('02_Debt Engine'!$F$20="Yes",'02_Debt Engine'!$V$20>0,C$4='02_Debt Engine'!$I$20),'02_Debt Engine'!$V$20,0) -> 0 | D22: =IF(AND('02_Debt Engine'!$F$20="Yes",'02_Debt Engine'!$V$20>0,D$4='02_Debt Engine'!$I$20),'02_Debt Engine'!$V$20,0) -> 0 | E22: =IF(AND('02_Debt Engine'!$F$20="Yes",'02_Debt Engine'!$V$20>0,E$4='02_Debt Engine'!$I$20),'02_Debt Engine'!$V$20,0) -> 0 | F22: =IF(AND('02_Debt Engine'!$F$20="Yes",'02_Debt Engine'!$V$20>0,F$4='02_Debt Engine'!$I$20),'02_Debt Engine'!$V$20,0) -> 0 | G22: =IF(AND('02_Debt Engine'!$F$20="Yes",'02_Debt Engine'!$V$20>0,G$4='02_Debt Engine'!$I$20),'02_Debt Engine'!$V$20,0) -> 0 | H22: =IF(AND('02_Debt Engine'!$F$20="Yes",'02_Debt Engine'!$V$20>0,H$4='02_Debt Engine'!$I$20),'02_Debt Engine'!$V$20,0) -> 0 | I22: =IF(AND('02_Debt Engine'!$F$20="Yes",'02_Debt Engine'!$V$20>0,I$4='02_Debt Engine'!$I$20),'02_Debt Engine'!$V$20,0) -> 0 | J22: =IF(AND('02_Debt Engine'!$F$20="Yes",'02_Debt Engine'!$V$20>0,J$4='02_Debt Engine'!$I$20),'02_Debt Engine'!$V$20,0) -> 0 | ... W22: =IF(AND('02_Debt Engine'!$F$20="Yes",'02_Debt Engine'!$V$20>0,W$4='02_Debt Engine'!$I$20),'02_Debt Engine'!$V$20,0) -> 0
B23: Net Refinancing | C23: =C21+C22 -> 0 | D23: =D21+D22 -> 0 | E23: =E21+E22 -> 0 | F23: =F21+F22 -> 0 | G23: =G21+G22 -> 0 | H23: =H21+H22 -> 0 | I23: =I21+I22 -> 0 | J23: =J21+J22 -> 0 | ... W23: =W21+W22 -> 0
B24: Total Debt Service | C24: =C18+C19 -> 54330.12 | D24: =D18+D19 -> 54330.12 | E24: =E18+E19 -> 54330.12 | F24: =F18+F19 -> 54330.12 | G24: =G18+G19 -> 54330.12 | H24: =H18+H19 -> 54330.12 | I24: =I18+I19 -> 54330.12 | J24: =J18+J19 -> 54330.12 | ... W24: =W18+W19 -> 54330.12
B26: ='02_Debt Engine'!$B$21 -> Beatrice Terrace | C26: =_xlfn.LET(_xlpm.refiyr,INDEX('02_Debt Engine'!$I$19:$I$35,MATCH('02A_Debt Schedule'!$B26,'02_Debt Engine'!$B$19:$B$35,0)),IF(_xlpm.refiyr='02A_Debt Schedule'!C$4,"Refi Yr.","")) | D26: =_xlfn.LET(_xlpm.refiyr,INDEX('02_Debt Engine'!$I$19:$I$35,MATCH('02A_Debt Schedule'!$B26,'02_Debt Engine'!$B$19:$B$35,0)),IF(_xlpm.refiyr='02A_Debt Schedule'!D$4,"Refi Yr.","")) | E26: =_xlfn.LET(_xlpm.refiyr,INDEX('02_Debt Engine'!$I$19:$I$35,MATCH('02A_Debt Schedule'!$B26,'02_Debt Engine'!$B$19:$B$35,0)),IF(_xlpm.refiyr='02A_Debt Schedule'!E$4,"Refi Yr.","")) | F26: =_xlfn.LET(_xlpm.refiyr,INDEX('02_Debt Engine'!$I$19:$I$35,MATCH('02A_Debt Schedule'!$B26,'02_Debt Engine'!$B$19:$B$35,0)),IF(_xlpm.refiyr='02A_Debt Schedule'!F$4,"Refi Yr.","")) | G26: =_xlfn.LET(_xlpm.refiyr,INDEX('02_Debt Engine'!$I$19:$I$35,MATCH('02A_Debt Schedule'!$B26,'02_Debt Engine'!$B$19:$B$35,0)),IF(_xlpm.refiyr='02A_Debt Schedule'!G$4,"Refi Yr.","")) | H26: =_xlfn.LET(_xlpm.refiyr,INDEX('02_Debt Engine'!$I$19:$I$35,MATCH('02A_Debt Schedule'!$B26,'02_Debt Engine'!$B$19:$B$35,0)),IF(_xlpm.refiyr='02A_Debt Schedule'!H$4,"Refi Yr.","")) | I26: =_xlfn.LET(_xlpm.refiyr,INDEX('02_Debt Engine'!$I$19:$I$35,MATCH('02A_Debt Schedule'!$B26,'02_Debt Engine'!$B$19:$B$35,0)),IF(_xlpm.refiyr='02A_Debt Schedule'!I$4,"Refi Yr.","")) | J26: =_xlfn.LET(_xlpm.refiyr,INDEX('02_Debt Engine'!$I$19:$I$35,MATCH('02A_Debt Schedule'!$B26,'02_Debt Engine'!$B$19:$B$35,0)),IF(_xlpm.refiyr='02A_Debt Schedule'!J$4,"Refi Yr.","")) | ... W26: =_xlfn.LET(_xlpm.refiyr,INDEX('02_Debt Engine'!$I$19:$I$35,MATCH('02A_Debt Schedule'!$B26,'02_Debt Engine'!$B$19:$B$35,0)),IF(_xlpm.refiyr='02A_Debt Schedule'!W$4,"Refi Yr.",""))
B27: Beginning Balance | C27: =IF('02_Debt Engine'!$D$21="Active",'02_Debt Engine'!$N$21,'02_Debt Engine'!$O$21) -> 1617334.9 | D27: =IF(AND('02_Debt Engine'!$F$21="Yes",'02_Debt Engine'!$V$21>0,C$4='02_Debt Engine'!$I$21),'02_Debt Engine'!$V$21,C30) -> 1571852.8 | E27: =IF(AND('02_Debt Engine'!$F$21="Yes",'02_Debt Engine'!$V$21>0,D$4='02_Debt Engine'!$I$21),'02_Debt Engine'!$V$21,D30) -> 1524540.4 | F27: =IF(AND('02_Debt Engine'!$F$21="Yes",'02_Debt Engine'!$V$21>0,E$4='02_Debt Engine'!$I$21),'02_Debt Engine'!$V$21,E30) -> 1475324.3 | G27: =IF(AND('02_Debt Engine'!$F$21="Yes",'02_Debt Engine'!$V$21>0,F$4='02_Debt Engine'!$I$21),'02_Debt Engine'!$V$21,F30) -> 1424127.6 | H27: =IF(AND('02_Debt Engine'!$F$21="Yes",'02_Debt Engine'!$V$21>0,G$4='02_Debt Engine'!$I$21),'02_Debt Engine'!$V$21,G30) -> 1370870.9 | I27: =IF(AND('02_Debt Engine'!$F$21="Yes",'02_Debt Engine'!$V$21>0,H$4='02_Debt Engine'!$I$21),'02_Debt Engine'!$V$21,H30) -> 1315471 | J27: =IF(AND('02_Debt Engine'!$F$21="Yes",'02_Debt Engine'!$V$21>0,I$4='02_Debt Engine'!$I$21),'02_Debt Engine'!$V$21,I30) -> 1257841.9 | K27: =IF(AND('02_Debt Engine'!$F$21="Yes",'02_Debt Engine'!$V$21>0,J$4='02_Debt Engine'!$I$21),'02_Debt Engine'!$V$21,J30) -> 1197893.8 | ... W27: =IF(AND('02_Debt Engine'!$F$21="Yes",'02_Debt Engine'!$V$21>0,V$4='02_Debt Engine'!$I$21),'02_Debt Engine'!$V$21,V30) -> 259586.99
B28: Interest PMT | C28: =IF(C27<=0,0,C27*IF(AND('02_Debt Engine'!$F$21="Yes",'02_Debt Engine'!$V$21>0,C$4>'02_Debt Engine'!$I$21),'02_Debt Engine'!$C$13,IF('02_Debt Engine'!$D$21="Active",'02_Debt Engine'!$H$21,'02_Debt Engine'!$C$7))) -> 65081.556 | D28: =IF(D27<=0,0,D27*IF(AND('02_Debt Engine'!$F$21="Yes",'02_Debt Engine'!$V$21>0,D$4>'02_Debt Engine'!$I$21),'02_Debt Engine'!$C$13,IF('02_Debt Engine'!$D$21="Active",'02_Debt Engine'!$H$21,'02_Debt Engine'!$C$7))) -> 63251.355 | E28: =IF(E27<=0,0,E27*IF(AND('02_Debt Engine'!$F$21="Yes",'02_Debt Engine'!$V$21>0,E$4>'02_Debt Engine'!$I$21),'02_Debt Engine'!$C$13,IF('02_Debt Engine'!$D$21="Active",'02_Debt Engine'!$H$21,'02_Debt Engine'!$C$7))) -> 61347.507 | F28: =IF(F27<=0,0,F27*IF(AND('02_Debt Engine'!$F$21="Yes",'02_Debt Engine'!$V$21>0,F$4>'02_Debt Engine'!$I$21),'02_Debt Engine'!$C$13,IF('02_Debt Engine'!$D$21="Active",'02_Debt Engine'!$H$21,'02_Debt Engine'!$C$7))) -> 59367.049 | G28: =IF(G27<=0,0,G27*IF(AND('02_Debt Engine'!$F$21="Yes",'02_Debt Engine'!$V$21>0,G$4>'02_Debt Engine'!$I$21),'02_Debt Engine'!$C$13,IF('02_Debt Engine'!$D$21="Active",'02_Debt Engine'!$H$21,'02_Debt Engine'!$C$7))) -> 57306.896 | H28: =IF(H27<=0,0,H27*IF(AND('02_Debt Engine'!$F$21="Yes",'02_Debt Engine'!$V$21>0,H$4>'02_Debt Engine'!$I$21),'02_Debt Engine'!$C$13,IF('02_Debt Engine'!$D$21="Active",'02_Debt Engine'!$H$21,'02_Debt Engine'!$C$7))) -> 55163.843 | I28: =IF(I27<=0,0,I27*IF(AND('02_Debt Engine'!$F$21="Yes",'02_Debt Engine'!$V$21>0,I$4>'02_Debt Engine'!$I$21),'02_Debt Engine'!$C$13,IF('02_Debt Engine'!$D$21="Active",'02_Debt Engine'!$H$21,'02_Debt Engine'!$C$7))) -> 52934.554 | J28: =IF(J27<=0,0,J27*IF(AND('02_Debt Engine'!$F$21="Yes",'02_Debt Engine'!$V$21>0,J$4>'02_Debt Engine'!$I$21),'02_Debt Engine'!$C$13,IF('02_Debt Engine'!$D$21="Active",'02_Debt Engine'!$H$21,'02_Debt Engine'!$C$7))) -> 50615.558 | ... W28: =IF(W27<=0,0,W27*IF(AND('02_Debt Engine'!$F$21="Yes",'02_Debt Engine'!$V$21>0,W$4>'02_Debt Engine'!$I$21),'02_Debt Engine'!$C$13,IF('02_Debt Engine'!$D$21="Active",'02_Debt Engine'!$H$21,'02_Debt Engine'!$C$7))) -> 10445.781
B29: Principal PMT | C29: =IF(C27<=0,0,MIN(C27,IF(AND('02_Debt Engine'!$F$21="Yes",'02_Debt Engine'!$V$21>0,C$4>'02_Debt Engine'!$I$21),'02_Debt Engine'!$W$21,IF('02_Debt Engine'!$D$21="Active",'02_Debt Engine'!$K$21,'02_Debt Engine'!$P$21))-C28)) -> 45482.124 | D29: =IF(D27<=0,0,MIN(D27,IF(AND('02_Debt Engine'!$F$21="Yes",'02_Debt Engine'!$V$21>0,D$4>'02_Debt Engine'!$I$21),'02_Debt Engine'!$W$21,IF('02_Debt Engine'!$D$21="Active",'02_Debt Engine'!$K$21,'02_Debt Engine'!$P$21))-D28)) -> 47312.325 | E29: =IF(E27<=0,0,MIN(E27,IF(AND('02_Debt Engine'!$F$21="Yes",'02_Debt Engine'!$V$21>0,E$4>'02_Debt Engine'!$I$21),'02_Debt Engine'!$W$21,IF('02_Debt Engine'!$D$21="Active",'02_Debt Engine'!$K$21,'02_Debt Engine'!$P$21))-E28)) -> 49216.173 | F29: =IF(F27<=0,0,MIN(F27,IF(AND('02_Debt Engine'!$F$21="Yes",'02_Debt Engine'!$V$21>0,F$4>'02_Debt Engine'!$I$21),'02_Debt Engine'!$W$21,IF('02_Debt Engine'!$D$21="Active",'02_Debt Engine'!$K$21,'02_Debt Engine'!$P$21))-F28)) -> 51196.631 | G29: =IF(G27<=0,0,MIN(G27,IF(AND('02_Debt Engine'!$F$21="Yes",'02_Debt Engine'!$V$21>0,G$4>'02_Debt Engine'!$I$21),'02_Debt Engine'!$W$21,IF('02_Debt Engine'!$D$21="Active",'02_Debt Engine'!$K$21,'02_Debt Engine'!$P$21))-G28)) -> 53256.784 | H29: =IF(H27<=0,0,MIN(H27,IF(AND('02_Debt Engine'!$F$21="Yes",'02_Debt Engine'!$V$21>0,H$4>'02_Debt Engine'!$I$21),'02_Debt Engine'!$W$21,IF('02_Debt Engine'!$D$21="Active",'02_Debt Engine'!$K$21,'02_Debt Engine'!$P$21))-H28)) -> 55399.837 | I29: =IF(I27<=0,0,MIN(I27,IF(AND('02_Debt Engine'!$F$21="Yes",'02_Debt Engine'!$V$21>0,I$4>'02_Debt Engine'!$I$21),'02_Debt Engine'!$W$21,IF('02_Debt Engine'!$D$21="Active",'02_Debt Engine'!$K$21,'02_Debt Engine'!$P$21))-I28)) -> 57629.126 | J29: =IF(J27<=0,0,MIN(J27,IF(AND('02_Debt Engine'!$F$21="Yes",'02_Debt Engine'!$V$21>0,J$4>'02_Debt Engine'!$I$21),'02_Debt Engine'!$W$21,IF('02_Debt Engine'!$D$21="Active",'02_Debt Engine'!$K$21,'02_Debt Engine'!$P$21))-J28)) -> 59948.122 | ... W29: =IF(W27<=0,0,MIN(W27,IF(AND('02_Debt Engine'!$F$21="Yes",'02_Debt Engine'!$V$21>0,W$4>'02_Debt Engine'!$I$21),'02_Debt Engine'!$W$21,IF('02_Debt Engine'!$D$21="Active",'02_Debt Engine'!$K$21,'02_Debt Engine'!$P$21))-W28)) -> 100117.9
B30: End Balance | C30: =C27-C29 -> 1571852.8 | D30: =D27-D29 -> 1524540.4 | E30: =E27-E29 -> 1475324.3 | F30: =F27-F29 -> 1424127.6 | G30: =G27-G29 -> 1370870.9 | H30: =H27-H29 -> 1315471 | I30: =I27-I29 -> 1257841.9 | J30: =J27-J29 -> 1197893.8 | ... W30: =W27-W29 -> 159469.09
B31: Balloon Payment | C31: =IF(AND('02_Debt Engine'!$F$21="Yes",'02_Debt Engine'!$V$21>0,C$4='02_Debt Engine'!$I$21),-C30,0) -> 0 | D31: =IF(AND('02_Debt Engine'!$F$21="Yes",'02_Debt Engine'!$V$21>0,D$4='02_Debt Engine'!$I$21),-D30,0) -> 0 | E31: =IF(AND('02_Debt Engine'!$F$21="Yes",'02_Debt Engine'!$V$21>0,E$4='02_Debt Engine'!$I$21),-E30,0) -> 0 | F31: =IF(AND('02_Debt Engine'!$F$21="Yes",'02_Debt Engine'!$V$21>0,F$4='02_Debt Engine'!$I$21),-F30,0) -> 0 | G31: =IF(AND('02_Debt Engine'!$F$21="Yes",'02_Debt Engine'!$V$21>0,G$4='02_Debt Engine'!$I$21),-G30,0) -> 0 | H31: =IF(AND('02_Debt Engine'!$F$21="Yes",'02_Debt Engine'!$V$21>0,H$4='02_Debt Engine'!$I$21),-H30,0) -> 0 | I31: =IF(AND('02_Debt Engine'!$F$21="Yes",'02_Debt Engine'!$V$21>0,I$4='02_Debt Engine'!$I$21),-I30,0) -> 0 | J31: =IF(AND('02_Debt Engine'!$F$21="Yes",'02_Debt Engine'!$V$21>0,J$4='02_Debt Engine'!$I$21),-J30,0) -> 0 | ... W31: =IF(AND('02_Debt Engine'!$F$21="Yes",'02_Debt Engine'!$V$21>0,W$4='02_Debt Engine'!$I$21),-W30,0) -> 0
B32: Refinance Proceeds | C32: =IF(AND('02_Debt Engine'!$F$21="Yes",'02_Debt Engine'!$V$21>0,C$4='02_Debt Engine'!$I$21),'02_Debt Engine'!$V$21,0) -> 0 | D32: =IF(AND('02_Debt Engine'!$F$21="Yes",'02_Debt Engine'!$V$21>0,D$4='02_Debt Engine'!$I$21),'02_Debt Engine'!$V$21,0) -> 0 | E32: =IF(AND('02_Debt Engine'!$F$21="Yes",'02_Debt Engine'!$V$21>0,E$4='02_Debt Engine'!$I$21),'02_Debt Engine'!$V$21,0) -> 0 | F32: =IF(AND('02_Debt Engine'!$F$21="Yes",'02_Debt Engine'!$V$21>0,F$4='02_Debt Engine'!$I$21),'02_Debt Engine'!$V$21,0) -> 0 | G32: =IF(AND('02_Debt Engine'!$F$21="Yes",'02_Debt Engine'!$V$21>0,G$4='02_Debt Engine'!$I$21),'02_Debt Engine'!$V$21,0) -> 0 | H32: =IF(AND('02_Debt Engine'!$F$21="Yes",'02_Debt Engine'!$V$21>0,H$4='02_Debt Engine'!$I$21),'02_Debt Engine'!$V$21,0) -> 0 | I32: =IF(AND('02_Debt Engine'!$F$21="Yes",'02_Debt Engine'!$V$21>0,I$4='02_Debt Engine'!$I$21),'02_Debt Engine'!$V$21,0) -> 0 | J32: =IF(AND('02_Debt Engine'!$F$21="Yes",'02_Debt Engine'!$V$21>0,J$4='02_Debt Engine'!$I$21),'02_Debt Engine'!$V$21,0) -> 0 | ... W32: =IF(AND('02_Debt Engine'!$F$21="Yes",'02_Debt Engine'!$V$21>0,W$4='02_Debt Engine'!$I$21),'02_Debt Engine'!$V$21,0) -> 0
B33: Net Refinancing | C33: =C31+C32 -> 0 | D33: =D31+D32 -> 0 | E33: =E31+E32 -> 0 | F33: =F31+F32 -> 0 | G33: =G31+G32 -> 0 | H33: =H31+H32 -> 0 | I33: =I31+I32 -> 0 | J33: =J31+J32 -> 0 | ... W33: =W31+W32 -> 0
B34: Total Debt Service | C34: =C28+C29 -> 110563.68 | D34: =D28+D29 -> 110563.68 | E34: =E28+E29 -> 110563.68 | F34: =F28+F29 -> 110563.68 | G34: =G28+G29 -> 110563.68 | H34: =H28+H29 -> 110563.68 | I34: =I28+I29 -> 110563.68 | J34: =J28+J29 -> 110563.68 | ... W34: =W28+W29 -> 110563.68
B36: ='02_Debt Engine'!$B$22 -> Capilano House | C36: =_xlfn.LET(_xlpm.refiyr,INDEX('02_Debt Engine'!$I$19:$I$35,MATCH('02A_Debt Schedule'!$B36,'02_Debt Engine'!$B$19:$B$35,0)),IF(_xlpm.refiyr='02A_Debt Schedule'!C$4,"Refi Yr.","")) | D36: =_xlfn.LET(_xlpm.refiyr,INDEX('02_Debt Engine'!$I$19:$I$35,MATCH('02A_Debt Schedule'!$B36,'02_Debt Engine'!$B$19:$B$35,0)),IF(_xlpm.refiyr='02A_Debt Schedule'!D$4,"Refi Yr.","")) | E36: =_xlfn.LET(_xlpm.refiyr,INDEX('02_Debt Engine'!$I$19:$I$35,MATCH('02A_Debt Schedule'!$B36,'02_Debt Engine'!$B$19:$B$35,0)),IF(_xlpm.refiyr='02A_Debt Schedule'!E$4,"Refi Yr.","")) | F36: =_xlfn.LET(_xlpm.refiyr,INDEX('02_Debt Engine'!$I$19:$I$35,MATCH('02A_Debt Schedule'!$B36,'02_Debt Engine'!$B$19:$B$35,0)),IF(_xlpm.refiyr='02A_Debt Schedule'!F$4,"Refi Yr.","")) | G36: =_xlfn.LET(_xlpm.refiyr,INDEX('02_Debt Engine'!$I$19:$I$35,MATCH('02A_Debt Schedule'!$B36,'02_Debt Engine'!$B$19:$B$35,0)),IF(_xlpm.refiyr='02A_Debt Schedule'!G$4,"Refi Yr.","")) | H36: =_xlfn.LET(_xlpm.refiyr,INDEX('02_Debt Engine'!$I$19:$I$35,MATCH('02A_Debt Schedule'!$B36,'02_Debt Engine'!$B$19:$B$35,0)),IF(_xlpm.refiyr='02A_Debt Schedule'!H$4,"Refi Yr.","")) | I36: =_xlfn.LET(_xlpm.refiyr,INDEX('02_Debt Engine'!$I$19:$I$35,MATCH('02A_Debt Schedule'!$B36,'02_Debt Engine'!$B$19:$B$35,0)),IF(_xlpm.refiyr='02A_Debt Schedule'!I$4,"Refi Yr.","")) | J36: =_xlfn.LET(_xlpm.refiyr,INDEX('02_Debt Engine'!$I$19:$I$35,MATCH('02A_Debt Schedule'!$B36,'02_Debt Engine'!$B$19:$B$35,0)),IF(_xlpm.refiyr='02A_Debt Schedule'!J$4,"Refi Yr.","")) | ... W36: =_xlfn.LET(_xlpm.refiyr,INDEX('02_Debt Engine'!$I$19:$I$35,MATCH('02A_Debt Schedule'!$B36,'02_Debt Engine'!$B$19:$B$35,0)),IF(_xlpm.refiyr='02A_Debt Schedule'!W$4,"Refi Yr.",""))
B37: Beginning Balance | C37: =IF('02_Debt Engine'!$D$22="Active",'02_Debt Engine'!$N$22,'02_Debt Engine'!$O$22) -> 0 | D37: =IF(AND('02_Debt Engine'!$F$22="Yes",'02_Debt Engine'!$V$22>0,C$4='02_Debt Engine'!$I$22),'02_Debt Engine'!$V$22,C40) -> 0 | E37: =IF(AND('02_Debt Engine'!$F$22="Yes",'02_Debt Engine'!$V$22>0,D$4='02_Debt Engine'!$I$22),'02_Debt Engine'!$V$22,D40) -> 0 | F37: =IF(AND('02_Debt Engine'!$F$22="Yes",'02_Debt Engine'!$V$22>0,E$4='02_Debt Engine'!$I$22),'02_Debt Engine'!$V$22,E40) -> 0 | G37: =IF(AND('02_Debt Engine'!$F$22="Yes",'02_Debt Engine'!$V$22>0,F$4='02_Debt Engine'!$I$22),'02_Debt Engine'!$V$22,F40) -> 0 | H37: =IF(AND('02_Debt Engine'!$F$22="Yes",'02_Debt Engine'!$V$22>0,G$4='02_Debt Engine'!$I$22),'02_Debt Engine'!$V$22,G40) -> 0 | I37: =IF(AND('02_Debt Engine'!$F$22="Yes",'02_Debt Engine'!$V$22>0,H$4='02_Debt Engine'!$I$22),'02_Debt Engine'!$V$22,H40) -> 0 | J37: =IF(AND('02_Debt Engine'!$F$22="Yes",'02_Debt Engine'!$V$22>0,I$4='02_Debt Engine'!$I$22),'02_Debt Engine'!$V$22,I40) -> 0 | K37: =IF(AND('02_Debt Engine'!$F$22="Yes",'02_Debt Engine'!$V$22>0,J$4='02_Debt Engine'!$I$22),'02_Debt Engine'!$V$22,J40) -> 0 | ... W37: =IF(AND('02_Debt Engine'!$F$22="Yes",'02_Debt Engine'!$V$22>0,V$4='02_Debt Engine'!$I$22),'02_Debt Engine'!$V$22,V40) -> 0
B38: Interest PMT | C38: =IF(C37<=0,0,C37*IF(AND('02_Debt Engine'!$F$22="Yes",'02_Debt Engine'!$V$22>0,C$4>'02_Debt Engine'!$I$22),'02_Debt Engine'!$C$13,IF('02_Debt Engine'!$D$22="Active",'02_Debt Engine'!$H$22,'02_Debt Engine'!$C$7))) -> 0 | D38: =IF(D37<=0,0,D37*IF(AND('02_Debt Engine'!$F$22="Yes",'02_Debt Engine'!$V$22>0,D$4>'02_Debt Engine'!$I$22),'02_Debt Engine'!$C$13,IF('02_Debt Engine'!$D$22="Active",'02_Debt Engine'!$H$22,'02_Debt Engine'!$C$7))) -> 0 | E38: =IF(E37<=0,0,E37*IF(AND('02_Debt Engine'!$F$22="Yes",'02_Debt Engine'!$V$22>0,E$4>'02_Debt Engine'!$I$22),'02_Debt Engine'!$C$13,IF('02_Debt Engine'!$D$22="Active",'02_Debt Engine'!$H$22,'02_Debt Engine'!$C$7))) -> 0 | F38: =IF(F37<=0,0,F37*IF(AND('02_Debt Engine'!$F$22="Yes",'02_Debt Engine'!$V$22>0,F$4>'02_Debt Engine'!$I$22),'02_Debt Engine'!$C$13,IF('02_Debt Engine'!$D$22="Active",'02_Debt Engine'!$H$22,'02_Debt Engine'!$C$7))) -> 0 | G38: =IF(G37<=0,0,G37*IF(AND('02_Debt Engine'!$F$22="Yes",'02_Debt Engine'!$V$22>0,G$4>'02_Debt Engine'!$I$22),'02_Debt Engine'!$C$13,IF('02_Debt Engine'!$D$22="Active",'02_Debt Engine'!$H$22,'02_Debt Engine'!$C$7))) -> 0 | H38: =IF(H37<=0,0,H37*IF(AND('02_Debt Engine'!$F$22="Yes",'02_Debt Engine'!$V$22>0,H$4>'02_Debt Engine'!$I$22),'02_Debt Engine'!$C$13,IF('02_Debt Engine'!$D$22="Active",'02_Debt Engine'!$H$22,'02_Debt Engine'!$C$7))) -> 0 | I38: =IF(I37<=0,0,I37*IF(AND('02_Debt Engine'!$F$22="Yes",'02_Debt Engine'!$V$22>0,I$4>'02_Debt Engine'!$I$22),'02_Debt Engine'!$C$13,IF('02_Debt Engine'!$D$22="Active",'02_Debt Engine'!$H$22,'02_Debt Engine'!$C$7))) -> 0 | J38: =IF(J37<=0,0,J37*IF(AND('02_Debt Engine'!$F$22="Yes",'02_Debt Engine'!$V$22>0,J$4>'02_Debt Engine'!$I$22),'02_Debt Engine'!$C$13,IF('02_Debt Engine'!$D$22="Active",'02_Debt Engine'!$H$22,'02_Debt Engine'!$C$7))) -> 0 | ... W38: =IF(W37<=0,0,W37*IF(AND('02_Debt Engine'!$F$22="Yes",'02_Debt Engine'!$V$22>0,W$4>'02_Debt Engine'!$I$22),'02_Debt Engine'!$C$13,IF('02_Debt Engine'!$D$22="Active",'02_Debt Engine'!$H$22,'02_Debt Engine'!$C$7))) -> 0
B39: Principal PMT | C39: =IF(C37<=0,0,MIN(C37,IF(AND('02_Debt Engine'!$F$22="Yes",'02_Debt Engine'!$V$22>0,C$4>'02_Debt Engine'!$I$22),'02_Debt Engine'!$W$22,IF('02_Debt Engine'!$D$22="Active",'02_Debt Engine'!$K$22,'02_Debt Engine'!$P$22))-C38)) -> 0 | D39: =IF(D37<=0,0,MIN(D37,IF(AND('02_Debt Engine'!$F$22="Yes",'02_Debt Engine'!$V$22>0,D$4>'02_Debt Engine'!$I$22),'02_Debt Engine'!$W$22,IF('02_Debt Engine'!$D$22="Active",'02_Debt Engine'!$K$22,'02_Debt Engine'!$P$22))-D38)) -> 0 | E39: =IF(E37<=0,0,MIN(E37,IF(AND('02_Debt Engine'!$F$22="Yes",'02_Debt Engine'!$V$22>0,E$4>'02_Debt Engine'!$I$22),'02_Debt Engine'!$W$22,IF('02_Debt Engine'!$D$22="Active",'02_Debt Engine'!$K$22,'02_Debt Engine'!$P$22))-E38)) -> 0 | F39: =IF(F37<=0,0,MIN(F37,IF(AND('02_Debt Engine'!$F$22="Yes",'02_Debt Engine'!$V$22>0,F$4>'02_Debt Engine'!$I$22),'02_Debt Engine'!$W$22,IF('02_Debt Engine'!$D$22="Active",'02_Debt Engine'!$K$22,'02_Debt Engine'!$P$22))-F38)) -> 0 | G39: =IF(G37<=0,0,MIN(G37,IF(AND('02_Debt Engine'!$F$22="Yes",'02_Debt Engine'!$V$22>0,G$4>'02_Debt Engine'!$I$22),'02_Debt Engine'!$W$22,IF('02_Debt Engine'!$D$22="Active",'02_Debt Engine'!$K$22,'02_Debt Engine'!$P$22))-G38)) -> 0 | H39: =IF(H37<=0,0,MIN(H37,IF(AND('02_Debt Engine'!$F$22="Yes",'02_Debt Engine'!$V$22>0,H$4>'02_Debt Engine'!$I$22),'02_Debt Engine'!$W$22,IF('02_Debt Engine'!$D$22="Active",'02_Debt Engine'!$K$22,'02_Debt Engine'!$P$22))-H38)) -> 0 | I39: =IF(I37<=0,0,MIN(I37,IF(AND('02_Debt Engine'!$F$22="Yes",'02_Debt Engine'!$V$22>0,I$4>'02_Debt Engine'!$I$22),'02_Debt Engine'!$W$22,IF('02_Debt Engine'!$D$22="Active",'02_Debt Engine'!$K$22,'02_Debt Engine'!$P$22))-I38)) -> 0 | J39: =IF(J37<=0,0,MIN(J37,IF(AND('02_Debt Engine'!$F$22="Yes",'02_Debt Engine'!$V$22>0,J$4>'02_Debt Engine'!$I$22),'02_Debt Engine'!$W$22,IF('02_Debt Engine'!$D$22="Active",'02_Debt Engine'!$K$22,'02_Debt Engine'!$P$22))-J38)) -> 0 | ... W39: =IF(W37<=0,0,MIN(W37,IF(AND('02_Debt Engine'!$F$22="Yes",'02_Debt Engine'!$V$22>0,W$4>'02_Debt Engine'!$I$22),'02_Debt Engine'!$W$22,IF('02_Debt Engine'!$D$22="Active",'02_Debt Engine'!$K$22,'02_Debt Engine'!$P$22))-W38)) -> 0
B40: End Balance | C40: =C37-C39 -> 0 | D40: =D37-D39 -> 0 | E40: =E37-E39 -> 0 | F40: =F37-F39 -> 0 | G40: =G37-G39 -> 0 | H40: =H37-H39 -> 0 | I40: =I37-I39 -> 0 | J40: =J37-J39 -> 0 | ... W40: =W37-W39 -> 0
B41: Balloon Payment | C41: =IF(AND('02_Debt Engine'!$F$22="Yes",'02_Debt Engine'!$V$22>0,C$4='02_Debt Engine'!$I$22),-C40,0) -> 0 | D41: =IF(AND('02_Debt Engine'!$F$22="Yes",'02_Debt Engine'!$V$22>0,D$4='02_Debt Engine'!$I$22),-D40,0) -> 0 | E41: =IF(AND('02_Debt Engine'!$F$22="Yes",'02_Debt Engine'!$V$22>0,E$4='02_Debt Engine'!$I$22),-E40,0) -> 0 | F41: =IF(AND('02_Debt Engine'!$F$22="Yes",'02_Debt Engine'!$V$22>0,F$4='02_Debt Engine'!$I$22),-F40,0) -> 0 | G41: =IF(AND('02_Debt Engine'!$F$22="Yes",'02_Debt Engine'!$V$22>0,G$4='02_Debt Engine'!$I$22),-G40,0) -> 0 | H41: =IF(AND('02_Debt Engine'!$F$22="Yes",'02_Debt Engine'!$V$22>0,H$4='02_Debt Engine'!$I$22),-H40,0) -> 0 | I41: =IF(AND('02_Debt Engine'!$F$22="Yes",'02_Debt Engine'!$V$22>0,I$4='02_Debt Engine'!$I$22),-I40,0) -> 0 | J41: =IF(AND('02_Debt Engine'!$F$22="Yes",'02_Debt Engine'!$V$22>0,J$4='02_Debt Engine'!$I$22),-J40,0) -> 0 | ... W41: =IF(AND('02_Debt Engine'!$F$22="Yes",'02_Debt Engine'!$V$22>0,W$4='02_Debt Engine'!$I$22),-W40,0) -> 0
B42: Refinance Proceeds | C42: =IF(AND('02_Debt Engine'!$F$22="Yes",'02_Debt Engine'!$V$22>0,C$4='02_Debt Engine'!$I$22),'02_Debt Engine'!$V$22,0) -> 0 | D42: =IF(AND('02_Debt Engine'!$F$22="Yes",'02_Debt Engine'!$V$22>0,D$4='02_Debt Engine'!$I$22),'02_Debt Engine'!$V$22,0) -> 0 | E42: =IF(AND('02_Debt Engine'!$F$22="Yes",'02_Debt Engine'!$V$22>0,E$4='02_Debt Engine'!$I$22),'02_Debt Engine'!$V$22,0) -> 0 | F42: =IF(AND('02_Debt Engine'!$F$22="Yes",'02_Debt Engine'!$V$22>0,F$4='02_Debt Engine'!$I$22),'02_Debt Engine'!$V$22,0) -> 0 | G42: =IF(AND('02_Debt Engine'!$F$22="Yes",'02_Debt Engine'!$V$22>0,G$4='02_Debt Engine'!$I$22),'02_Debt Engine'!$V$22,0) -> 0 | H42: =IF(AND('02_Debt Engine'!$F$22="Yes",'02_Debt Engine'!$V$22>0,H$4='02_Debt Engine'!$I$22),'02_Debt Engine'!$V$22,0) -> 0 | I42: =IF(AND('02_Debt Engine'!$F$22="Yes",'02_Debt Engine'!$V$22>0,I$4='02_Debt Engine'!$I$22),'02_Debt Engine'!$V$22,0) -> 0 | J42: =IF(AND('02_Debt Engine'!$F$22="Yes",'02_Debt Engine'!$V$22>0,J$4='02_Debt Engine'!$I$22),'02_Debt Engine'!$V$22,0) -> 0 | ... W42: =IF(AND('02_Debt Engine'!$F$22="Yes",'02_Debt Engine'!$V$22>0,W$4='02_Debt Engine'!$I$22),'02_Debt Engine'!$V$22,0) -> 0
B43: Net Refinancing | C43: =C41+C42 -> 0 | D43: =D41+D42 -> 0 | E43: =E41+E42 -> 0 | F43: =F41+F42 -> 0 | G43: =G41+G42 -> 0 | H43: =H41+H42 -> 0 | I43: =I41+I42 -> 0 | J43: =J41+J42 -> 0 | ... W43: =W41+W42 -> 0
B44: Total Debt Service | C44: =C38+C39 -> 0 | D44: =D38+D39 -> 0 | E44: =E38+E39 -> 0 | F44: =F38+F39 -> 0 | G44: =G38+G39 -> 0 | H44: =H38+H39 -> 0 | I44: =I38+I39 -> 0 | J44: =J38+J39 -> 0 | ... W44: =W38+W39 -> 0
B46: ='02_Debt Engine'!$B$23 -> Constance Court | C46: =_xlfn.LET(_xlpm.refiyr,INDEX('02_Debt Engine'!$I$19:$I$35,MATCH('02A_Debt Schedule'!$B46,'02_Debt Engine'!$B$19:$B$35,0)),IF(_xlpm.refiyr='02A_Debt Schedule'!C$4,"Refi Yr.","")) | D46: =_xlfn.LET(_xlpm.refiyr,INDEX('02_Debt Engine'!$I$19:$I$35,MATCH('02A_Debt Schedule'!$B46,'02_Debt Engine'!$B$19:$B$35,0)),IF(_xlpm.refiyr='02A_Debt Schedule'!D$4,"Refi Yr.","")) | E46: =_xlfn.LET(_xlpm.refiyr,INDEX('02_Debt Engine'!$I$19:$I$35,MATCH('02A_Debt Schedule'!$B46,'02_Debt Engine'!$B$19:$B$35,0)),IF(_xlpm.refiyr='02A_Debt Schedule'!E$4,"Refi Yr.","")) -> Refi Yr. | F46: =_xlfn.LET(_xlpm.refiyr,INDEX('02_Debt Engine'!$I$19:$I$35,MATCH('02A_Debt Schedule'!$B46,'02_Debt Engine'!$B$19:$B$35,0)),IF(_xlpm.refiyr='02A_Debt Schedule'!F$4,"Refi Yr.","")) | G46: =_xlfn.LET(_xlpm.refiyr,INDEX('02_Debt Engine'!$I$19:$I$35,MATCH('02A_Debt Schedule'!$B46,'02_Debt Engine'!$B$19:$B$35,0)),IF(_xlpm.refiyr='02A_Debt Schedule'!G$4,"Refi Yr.","")) | H46: =_xlfn.LET(_xlpm.refiyr,INDEX('02_Debt Engine'!$I$19:$I$35,MATCH('02A_Debt Schedule'!$B46,'02_Debt Engine'!$B$19:$B$35,0)),IF(_xlpm.refiyr='02A_Debt Schedule'!H$4,"Refi Yr.","")) | I46: =_xlfn.LET(_xlpm.refiyr,INDEX('02_Debt Engine'!$I$19:$I$35,MATCH('02A_Debt Schedule'!$B46,'02_Debt Engine'!$B$19:$B$35,0)),IF(_xlpm.refiyr='02A_Debt Schedule'!I$4,"Refi Yr.","")) | J46: =_xlfn.LET(_xlpm.refiyr,INDEX('02_Debt Engine'!$I$19:$I$35,MATCH('02A_Debt Schedule'!$B46,'02_Debt Engine'!$B$19:$B$35,0)),IF(_xlpm.refiyr='02A_Debt Schedule'!J$4,"Refi Yr.","")) | ... W46: =_xlfn.LET(_xlpm.refiyr,INDEX('02_Debt Engine'!$I$19:$I$35,MATCH('02A_Debt Schedule'!$B46,'02_Debt Engine'!$B$19:$B$35,0)),IF(_xlpm.refiyr='02A_Debt Schedule'!W$4,"Refi Yr.",""))
B47: Beginning Balance | C47: =IF('02_Debt Engine'!$D$23="Active",'02_Debt Engine'!$N$23,'02_Debt Engine'!$O$23) -> 274036.81 | D47: =IF(AND('02_Debt Engine'!$F$23="Yes",'02_Debt Engine'!$V$23>0,C$4='02_Debt Engine'!$I$23),'02_Debt Engine'!$V$23,C50) -> 107120.77 | E47: =IF(AND('02_Debt Engine'!$F$23="Yes",'02_Debt Engine'!$V$23>0,D$4='02_Debt Engine'!$I$23),'02_Debt Engine'!$V$23,D50) -> 0 | F47: =IF(AND('02_Debt Engine'!$F$23="Yes",'02_Debt Engine'!$V$23>0,E$4='02_Debt Engine'!$I$23),'02_Debt Engine'!$V$23,E50) -> 0 | G47: =IF(AND('02_Debt Engine'!$F$23="Yes",'02_Debt Engine'!$V$23>0,F$4='02_Debt Engine'!$I$23),'02_Debt Engine'!$V$23,F50) -> 0 | H47: =IF(AND('02_Debt Engine'!$F$23="Yes",'02_Debt Engine'!$V$23>0,G$4='02_Debt Engine'!$I$23),'02_Debt Engine'!$V$23,G50) -> 0 | I47: =IF(AND('02_Debt Engine'!$F$23="Yes",'02_Debt Engine'!$V$23>0,H$4='02_Debt Engine'!$I$23),'02_Debt Engine'!$V$23,H50) -> 0 | J47: =IF(AND('02_Debt Engine'!$F$23="Yes",'02_Debt Engine'!$V$23>0,I$4='02_Debt Engine'!$I$23),'02_Debt Engine'!$V$23,I50) -> 0 | K47: =IF(AND('02_Debt Engine'!$F$23="Yes",'02_Debt Engine'!$V$23>0,J$4='02_Debt Engine'!$I$23),'02_Debt Engine'!$V$23,J50) -> 0 | ... W47: =IF(AND('02_Debt Engine'!$F$23="Yes",'02_Debt Engine'!$V$23>0,V$4='02_Debt Engine'!$I$23),'02_Debt Engine'!$V$23,V50) -> 0
B48: Interest PMT | C48: =IF(C47<=0,0,C47*IF(AND('02_Debt Engine'!$F$23="Yes",'02_Debt Engine'!$V$23>0,C$4>'02_Debt Engine'!$I$23),'02_Debt Engine'!$C$13,IF('02_Debt Engine'!$D$23="Active",'02_Debt Engine'!$H$23,'02_Debt Engine'!$C$7))) -> 11591.757 | D48: =IF(D47<=0,0,D47*IF(AND('02_Debt Engine'!$F$23="Yes",'02_Debt Engine'!$V$23>0,D$4>'02_Debt Engine'!$I$23),'02_Debt Engine'!$C$13,IF('02_Debt Engine'!$D$23="Active",'02_Debt Engine'!$H$23,'02_Debt Engine'!$C$7))) -> 4531.2084 | E48: =IF(E47<=0,0,E47*IF(AND('02_Debt Engine'!$F$23="Yes",'02_Debt Engine'!$V$23>0,E$4>'02_Debt Engine'!$I$23),'02_Debt Engine'!$C$13,IF('02_Debt Engine'!$D$23="Active",'02_Debt Engine'!$H$23,'02_Debt Engine'!$C$7))) -> 0 | F48: =IF(F47<=0,0,F47*IF(AND('02_Debt Engine'!$F$23="Yes",'02_Debt Engine'!$V$23>0,F$4>'02_Debt Engine'!$I$23),'02_Debt Engine'!$C$13,IF('02_Debt Engine'!$D$23="Active",'02_Debt Engine'!$H$23,'02_Debt Engine'!$C$7))) -> 0 | G48: =IF(G47<=0,0,G47*IF(AND('02_Debt Engine'!$F$23="Yes",'02_Debt Engine'!$V$23>0,G$4>'02_Debt Engine'!$I$23),'02_Debt Engine'!$C$13,IF('02_Debt Engine'!$D$23="Active",'02_Debt Engine'!$H$23,'02_Debt Engine'!$C$7))) -> 0 | H48: =IF(H47<=0,0,H47*IF(AND('02_Debt Engine'!$F$23="Yes",'02_Debt Engine'!$V$23>0,H$4>'02_Debt Engine'!$I$23),'02_Debt Engine'!$C$13,IF('02_Debt Engine'!$D$23="Active",'02_Debt Engine'!$H$23,'02_Debt Engine'!$C$7))) -> 0 | I48: =IF(I47<=0,0,I47*IF(AND('02_Debt Engine'!$F$23="Yes",'02_Debt Engine'!$V$23>0,I$4>'02_Debt Engine'!$I$23),'02_Debt Engine'!$C$13,IF('02_Debt Engine'!$D$23="Active",'02_Debt Engine'!$H$23,'02_Debt Engine'!$C$7))) -> 0 | J48: =IF(J47<=0,0,J47*IF(AND('02_Debt Engine'!$F$23="Yes",'02_Debt Engine'!$V$23>0,J$4>'02_Debt Engine'!$I$23),'02_Debt Engine'!$C$13,IF('02_Debt Engine'!$D$23="Active",'02_Debt Engine'!$H$23,'02_Debt Engine'!$C$7))) -> 0 | ... W48: =IF(W47<=0,0,W47*IF(AND('02_Debt Engine'!$F$23="Yes",'02_Debt Engine'!$V$23>0,W$4>'02_Debt Engine'!$I$23),'02_Debt Engine'!$C$13,IF('02_Debt Engine'!$D$23="Active",'02_Debt Engine'!$H$23,'02_Debt Engine'!$C$7))) -> 0
B49: Principal PMT | C49: =IF(C47<=0,0,MIN(C47,IF(AND('02_Debt Engine'!$F$23="Yes",'02_Debt Engine'!$V$23>0,C$4>'02_Debt Engine'!$I$23),'02_Debt Engine'!$W$23,IF('02_Debt Engine'!$D$23="Active",'02_Debt Engine'!$K$23,'02_Debt Engine'!$P$23))-C48)) -> 166916.04 | D49: =IF(D47<=0,0,MIN(D47,IF(AND('02_Debt Engine'!$F$23="Yes",'02_Debt Engine'!$V$23>0,D$4>'02_Debt Engine'!$I$23),'02_Debt Engine'!$W$23,IF('02_Debt Engine'!$D$23="Active",'02_Debt Engine'!$K$23,'02_Debt Engine'!$P$23))-D48)) -> 107120.77 | E49: =IF(E47<=0,0,MIN(E47,IF(AND('02_Debt Engine'!$F$23="Yes",'02_Debt Engine'!$V$23>0,E$4>'02_Debt Engine'!$I$23),'02_Debt Engine'!$W$23,IF('02_Debt Engine'!$D$23="Active",'02_Debt Engine'!$K$23,'02_Debt Engine'!$P$23))-E48)) -> 0 | F49: =IF(F47<=0,0,MIN(F47,IF(AND('02_Debt Engine'!$F$23="Yes",'02_Debt Engine'!$V$23>0,F$4>'02_Debt Engine'!$I$23),'02_Debt Engine'!$W$23,IF('02_Debt Engine'!$D$23="Active",'02_Debt Engine'!$K$23,'02_Debt Engine'!$P$23))-F48)) -> 0 | G49: =IF(G47<=0,0,MIN(G47,IF(AND('02_Debt Engine'!$F$23="Yes",'02_Debt Engine'!$V$23>0,G$4>'02_Debt Engine'!$I$23),'02_Debt Engine'!$W$23,IF('02_Debt Engine'!$D$23="Active",'02_Debt Engine'!$K$23,'02_Debt Engine'!$P$23))-G48)) -> 0 | H49: =IF(H47<=0,0,MIN(H47,IF(AND('02_Debt Engine'!$F$23="Yes",'02_Debt Engine'!$V$23>0,H$4>'02_Debt Engine'!$I$23),'02_Debt Engine'!$W$23,IF('02_Debt Engine'!$D$23="Active",'02_Debt Engine'!$K$23,'02_Debt Engine'!$P$23))-H48)) -> 0 | I49: =IF(I47<=0,0,MIN(I47,IF(AND('02_Debt Engine'!$F$23="Yes",'02_Debt Engine'!$V$23>0,I$4>'02_Debt Engine'!$I$23),'02_Debt Engine'!$W$23,IF('02_Debt Engine'!$D$23="Active",'02_Debt Engine'!$K$23,'02_Debt Engine'!$P$23))-I48)) -> 0 | J49: =IF(J47<=0,0,MIN(J47,IF(AND('02_Debt Engine'!$F$23="Yes",'02_Debt Engine'!$V$23>0,J$4>'02_Debt Engine'!$I$23),'02_Debt Engine'!$W$23,IF('02_Debt Engine'!$D$23="Active",'02_Debt Engine'!$K$23,'02_Debt Engine'!$P$23))-J48)) -> 0 | ... W49: =IF(W47<=0,0,MIN(W47,IF(AND('02_Debt Engine'!$F$23="Yes",'02_Debt Engine'!$V$23>0,W$4>'02_Debt Engine'!$I$23),'02_Debt Engine'!$W$23,IF('02_Debt Engine'!$D$23="Active",'02_Debt Engine'!$K$23,'02_Debt Engine'!$P$23))-W48)) -> 0
B50: End Balance | C50: =C47-C49 -> 107120.77 | D50: =D47-D49 -> 0 | E50: =E47-E49 -> 0 | F50: =F47-F49 -> 0 | G50: =G47-G49 -> 0 | H50: =H47-H49 -> 0 | I50: =I47-I49 -> 0 | J50: =J47-J49 -> 0 | ... W50: =W47-W49 -> 0
B51: Balloon Payment | C51: =IF(AND('02_Debt Engine'!$F$23="Yes",'02_Debt Engine'!$V$23>0,C$4='02_Debt Engine'!$I$23),-C50,0) -> 0 | D51: =IF(AND('02_Debt Engine'!$F$23="Yes",'02_Debt Engine'!$V$23>0,D$4='02_Debt Engine'!$I$23),-D50,0) -> 0 | E51: =IF(AND('02_Debt Engine'!$F$23="Yes",'02_Debt Engine'!$V$23>0,E$4='02_Debt Engine'!$I$23),-E50,0) -> 0 | F51: =IF(AND('02_Debt Engine'!$F$23="Yes",'02_Debt Engine'!$V$23>0,F$4='02_Debt Engine'!$I$23),-F50,0) -> 0 | G51: =IF(AND('02_Debt Engine'!$F$23="Yes",'02_Debt Engine'!$V$23>0,G$4='02_Debt Engine'!$I$23),-G50,0) -> 0 | H51: =IF(AND('02_Debt Engine'!$F$23="Yes",'02_Debt Engine'!$V$23>0,H$4='02_Debt Engine'!$I$23),-H50,0) -> 0 | I51: =IF(AND('02_Debt Engine'!$F$23="Yes",'02_Debt Engine'!$V$23>0,I$4='02_Debt Engine'!$I$23),-I50,0) -> 0 | J51: =IF(AND('02_Debt Engine'!$F$23="Yes",'02_Debt Engine'!$V$23>0,J$4='02_Debt Engine'!$I$23),-J50,0) -> 0 | ... W51: =IF(AND('02_Debt Engine'!$F$23="Yes",'02_Debt Engine'!$V$23>0,W$4='02_Debt Engine'!$I$23),-W50,0) -> 0
B52: Refinance Proceeds | C52: =IF(AND('02_Debt Engine'!$F$23="Yes",'02_Debt Engine'!$V$23>0,C$4='02_Debt Engine'!$I$23),'02_Debt Engine'!$V$23,0) -> 0 | D52: =IF(AND('02_Debt Engine'!$F$23="Yes",'02_Debt Engine'!$V$23>0,D$4='02_Debt Engine'!$I$23),'02_Debt Engine'!$V$23,0) -> 0 | E52: =IF(AND('02_Debt Engine'!$F$23="Yes",'02_Debt Engine'!$V$23>0,E$4='02_Debt Engine'!$I$23),'02_Debt Engine'!$V$23,0) -> 0 | F52: =IF(AND('02_Debt Engine'!$F$23="Yes",'02_Debt Engine'!$V$23>0,F$4='02_Debt Engine'!$I$23),'02_Debt Engine'!$V$23,0) -> 0 | G52: =IF(AND('02_Debt Engine'!$F$23="Yes",'02_Debt Engine'!$V$23>0,G$4='02_Debt Engine'!$I$23),'02_Debt Engine'!$V$23,0) -> 0 | H52: =IF(AND('02_Debt Engine'!$F$23="Yes",'02_Debt Engine'!$V$23>0,H$4='02_Debt Engine'!$I$23),'02_Debt Engine'!$V$23,0) -> 0 | I52: =IF(AND('02_Debt Engine'!$F$23="Yes",'02_Debt Engine'!$V$23>0,I$4='02_Debt Engine'!$I$23),'02_Debt Engine'!$V$23,0) -> 0 | J52: =IF(AND('02_Debt Engine'!$F$23="Yes",'02_Debt Engine'!$V$23>0,J$4='02_Debt Engine'!$I$23),'02_Debt Engine'!$V$23,0) -> 0 | ... W52: =IF(AND('02_Debt Engine'!$F$23="Yes",'02_Debt Engine'!$V$23>0,W$4='02_Debt Engine'!$I$23),'02_Debt Engine'!$V$23,0) -> 0
B53: Net Refinancing | C53: =C51+C52 -> 0 | D53: =D51+D52 -> 0 | E53: =E51+E52 -> 0 | F53: =F51+F52 -> 0 | G53: =G51+G52 -> 0 | H53: =H51+H52 -> 0 | I53: =I51+I52 -> 0 | J53: =J51+J52 -> 0 | ... W53: =W51+W52 -> 0
B54: Total Debt Service | C54: =C48+C49 -> 178507.8 | D54: =D48+D49 -> 111651.98 | E54: =E48+E49 -> 0 | F54: =F48+F49 -> 0 | G54: =G48+G49 -> 0 | H54: =H48+H49 -> 0 | I54: =I48+I49 -> 0 | J54: =J48+J49 -> 0 | ... W54: =W48+W49 -> 0
B56: ='02_Debt Engine'!$B$24 -> Evergreen Apartments | C56: =_xlfn.LET(_xlpm.refiyr,INDEX('02_Debt Engine'!$I$19:$I$35,MATCH('02A_Debt Schedule'!$B56,'02_Debt Engine'!$B$19:$B$35,0)),IF(_xlpm.refiyr='02A_Debt Schedule'!C$4,"Refi Yr.","")) | D56: =_xlfn.LET(_xlpm.refiyr,INDEX('02_Debt Engine'!$I$19:$I$35,MATCH('02A_Debt Schedule'!$B56,'02_Debt Engine'!$B$19:$B$35,0)),IF(_xlpm.refiyr='02A_Debt Schedule'!D$4,"Refi Yr.","")) | E56: =_xlfn.LET(_xlpm.refiyr,INDEX('02_Debt Engine'!$I$19:$I$35,MATCH('02A_Debt Schedule'!$B56,'02_Debt Engine'!$B$19:$B$35,0)),IF(_xlpm.refiyr='02A_Debt Schedule'!E$4,"Refi Yr.","")) | F56: =_xlfn.LET(_xlpm.refiyr,INDEX('02_Debt Engine'!$I$19:$I$35,MATCH('02A_Debt Schedule'!$B56,'02_Debt Engine'!$B$19:$B$35,0)),IF(_xlpm.refiyr='02A_Debt Schedule'!F$4,"Refi Yr.","")) | G56: =_xlfn.LET(_xlpm.refiyr,INDEX('02_Debt Engine'!$I$19:$I$35,MATCH('02A_Debt Schedule'!$B56,'02_Debt Engine'!$B$19:$B$35,0)),IF(_xlpm.refiyr='02A_Debt Schedule'!G$4,"Refi Yr.","")) | H56: =_xlfn.LET(_xlpm.refiyr,INDEX('02_Debt Engine'!$I$19:$I$35,MATCH('02A_Debt Schedule'!$B56,'02_Debt Engine'!$B$19:$B$35,0)),IF(_xlpm.refiyr='02A_Debt Schedule'!H$4,"Refi Yr.","")) | I56: =_xlfn.LET(_xlpm.refiyr,INDEX('02_Debt Engine'!$I$19:$I$35,MATCH('02A_Debt Schedule'!$B56,'02_Debt Engine'!$B$19:$B$35,0)),IF(_xlpm.refiyr='02A_Debt Schedule'!I$4,"Refi Yr.","")) | J56: =_xlfn.LET(_xlpm.refiyr,INDEX('02_Debt Engine'!$I$19:$I$35,MATCH('02A_Debt Schedule'!$B56,'02_Debt Engine'!$B$19:$B$35,0)),IF(_xlpm.refiyr='02A_Debt Schedule'!J$4,"Refi Yr.","")) | ... W56: =_xlfn.LET(_xlpm.refiyr,INDEX('02_Debt Engine'!$I$19:$I$35,MATCH('02A_Debt Schedule'!$B56,'02_Debt Engine'!$B$19:$B$35,0)),IF(_xlpm.refiyr='02A_Debt Schedule'!W$4,"Refi Yr.",""))
B57: Beginning Balance | C57: =IF('02_Debt Engine'!$D$24="Active",'02_Debt Engine'!$N$24,'02_Debt Engine'!$O$24) -> 5475821.3 | D57: =IF(AND('02_Debt Engine'!$F$24="Yes",'02_Debt Engine'!$V$24>0,C$4='02_Debt Engine'!$I$24),'02_Debt Engine'!$V$24,C60) -> 5408513.4 | E57: =IF(AND('02_Debt Engine'!$F$24="Yes",'02_Debt Engine'!$V$24>0,D$4='02_Debt Engine'!$I$24),'02_Debt Engine'!$V$24,D60) -> 5338371.8 | F57: =IF(AND('02_Debt Engine'!$F$24="Yes",'02_Debt Engine'!$V$24>0,E$4='02_Debt Engine'!$I$24),'02_Debt Engine'!$V$24,E60) -> 5265277.2 | G57: =IF(AND('02_Debt Engine'!$F$24="Yes",'02_Debt Engine'!$V$24>0,F$4='02_Debt Engine'!$I$24),'02_Debt Engine'!$V$24,F60) -> 5189105.4 | H57: =IF(AND('02_Debt Engine'!$F$24="Yes",'02_Debt Engine'!$V$24>0,G$4='02_Debt Engine'!$I$24),'02_Debt Engine'!$V$24,G60) -> 5109726.8 | I57: =IF(AND('02_Debt Engine'!$F$24="Yes",'02_Debt Engine'!$V$24>0,H$4='02_Debt Engine'!$I$24),'02_Debt Engine'!$V$24,H60) -> 5027006.2 | J57: =IF(AND('02_Debt Engine'!$F$24="Yes",'02_Debt Engine'!$V$24>0,I$4='02_Debt Engine'!$I$24),'02_Debt Engine'!$V$24,I60) -> 4940803.2 | K57: =IF(AND('02_Debt Engine'!$F$24="Yes",'02_Debt Engine'!$V$24>0,J$4='02_Debt Engine'!$I$24),'02_Debt Engine'!$V$24,J60) -> 4850971 | ... W57: =IF(AND('02_Debt Engine'!$F$24="Yes",'02_Debt Engine'!$V$24>0,V$4='02_Debt Engine'!$I$24),'02_Debt Engine'!$V$24,V60) -> 6302970.2
B58: Interest PMT | C58: =IF(C57<=0,0,C57*IF(AND('02_Debt Engine'!$F$24="Yes",'02_Debt Engine'!$V$24>0,C$4>'02_Debt Engine'!$I$24),'02_Debt Engine'!$C$13,IF('02_Debt Engine'!$D$24="Active",'02_Debt Engine'!$H$24,'02_Debt Engine'!$C$7))) -> 230532.08 | D58: =IF(D57<=0,0,D57*IF(AND('02_Debt Engine'!$F$24="Yes",'02_Debt Engine'!$V$24>0,D$4>'02_Debt Engine'!$I$24),'02_Debt Engine'!$C$13,IF('02_Debt Engine'!$D$24="Active",'02_Debt Engine'!$H$24,'02_Debt Engine'!$C$7))) -> 227698.41 | E58: =IF(E57<=0,0,E57*IF(AND('02_Debt Engine'!$F$24="Yes",'02_Debt Engine'!$V$24>0,E$4>'02_Debt Engine'!$I$24),'02_Debt Engine'!$C$13,IF('02_Debt Engine'!$D$24="Active",'02_Debt Engine'!$H$24,'02_Debt Engine'!$C$7))) -> 224745.45 | F58: =IF(F57<=0,0,F57*IF(AND('02_Debt Engine'!$F$24="Yes",'02_Debt Engine'!$V$24>0,F$4>'02_Debt Engine'!$I$24),'02_Debt Engine'!$C$13,IF('02_Debt Engine'!$D$24="Active",'02_Debt Engine'!$H$24,'02_Debt Engine'!$C$7))) -> 221668.17 | G58: =IF(G57<=0,0,G57*IF(AND('02_Debt Engine'!$F$24="Yes",'02_Debt Engine'!$V$24>0,G$4>'02_Debt Engine'!$I$24),'02_Debt Engine'!$C$13,IF('02_Debt Engine'!$D$24="Active",'02_Debt Engine'!$H$24,'02_Debt Engine'!$C$7))) -> 218461.34 | H58: =IF(H57<=0,0,H57*IF(AND('02_Debt Engine'!$F$24="Yes",'02_Debt Engine'!$V$24>0,H$4>'02_Debt Engine'!$I$24),'02_Debt Engine'!$C$13,IF('02_Debt Engine'!$D$24="Active",'02_Debt Engine'!$H$24,'02_Debt Engine'!$C$7))) -> 215119.5 | I58: =IF(I57<=0,0,I57*IF(AND('02_Debt Engine'!$F$24="Yes",'02_Debt Engine'!$V$24>0,I$4>'02_Debt Engine'!$I$24),'02_Debt Engine'!$C$13,IF('02_Debt Engine'!$D$24="Active",'02_Debt Engine'!$H$24,'02_Debt Engine'!$C$7))) -> 211636.96 | J58: =IF(J57<=0,0,J57*IF(AND('02_Debt Engine'!$F$24="Yes",'02_Debt Engine'!$V$24>0,J$4>'02_Debt Engine'!$I$24),'02_Debt Engine'!$C$13,IF('02_Debt Engine'!$D$24="Active",'02_Debt Engine'!$H$24,'02_Debt Engine'!$C$7))) -> 208007.82 | ... W58: =IF(W57<=0,0,W57*IF(AND('02_Debt Engine'!$F$24="Yes",'02_Debt Engine'!$V$24>0,W$4>'02_Debt Engine'!$I$24),'02_Debt Engine'!$C$13,IF('02_Debt Engine'!$D$24="Active",'02_Debt Engine'!$H$24,'02_Debt Engine'!$C$7))) -> 252118.81
B59: Principal PMT | C59: =IF(C57<=0,0,MIN(C57,IF(AND('02_Debt Engine'!$F$24="Yes",'02_Debt Engine'!$V$24>0,C$4>'02_Debt Engine'!$I$24),'02_Debt Engine'!$W$24,IF('02_Debt Engine'!$D$24="Active",'02_Debt Engine'!$K$24,'02_Debt Engine'!$P$24))-C58)) -> 67307.923 | D59: =IF(D57<=0,0,MIN(D57,IF(AND('02_Debt Engine'!$F$24="Yes",'02_Debt Engine'!$V$24>0,D$4>'02_Debt Engine'!$I$24),'02_Debt Engine'!$W$24,IF('02_Debt Engine'!$D$24="Active",'02_Debt Engine'!$K$24,'02_Debt Engine'!$P$24))-D58)) -> 70141.587 | E59: =IF(E57<=0,0,MIN(E57,IF(AND('02_Debt Engine'!$F$24="Yes",'02_Debt Engine'!$V$24>0,E$4>'02_Debt Engine'!$I$24),'02_Debt Engine'!$W$24,IF('02_Debt Engine'!$D$24="Active",'02_Debt Engine'!$K$24,'02_Debt Engine'!$P$24))-E58)) -> 73094.548 | F59: =IF(F57<=0,0,MIN(F57,IF(AND('02_Debt Engine'!$F$24="Yes",'02_Debt Engine'!$V$24>0,F$4>'02_Debt Engine'!$I$24),'02_Debt Engine'!$W$24,IF('02_Debt Engine'!$D$24="Active",'02_Debt Engine'!$K$24,'02_Debt Engine'!$P$24))-F58)) -> 76171.828 | G59: =IF(G57<=0,0,MIN(G57,IF(AND('02_Debt Engine'!$F$24="Yes",'02_Debt Engine'!$V$24>0,G$4>'02_Debt Engine'!$I$24),'02_Debt Engine'!$W$24,IF('02_Debt Engine'!$D$24="Active",'02_Debt Engine'!$K$24,'02_Debt Engine'!$P$24))-G58)) -> 79378.662 | H59: =IF(H57<=0,0,MIN(H57,IF(AND('02_Debt Engine'!$F$24="Yes",'02_Debt Engine'!$V$24>0,H$4>'02_Debt Engine'!$I$24),'02_Debt Engine'!$W$24,IF('02_Debt Engine'!$D$24="Active",'02_Debt Engine'!$K$24,'02_Debt Engine'!$P$24))-H58)) -> 82720.504 | I59: =IF(I57<=0,0,MIN(I57,IF(AND('02_Debt Engine'!$F$24="Yes",'02_Debt Engine'!$V$24>0,I$4>'02_Debt Engine'!$I$24),'02_Debt Engine'!$W$24,IF('02_Debt Engine'!$D$24="Active",'02_Debt Engine'!$K$24,'02_Debt Engine'!$P$24))-I58)) -> 86203.037 | J59: =IF(J57<=0,0,MIN(J57,IF(AND('02_Debt Engine'!$F$24="Yes",'02_Debt Engine'!$V$24>0,J$4>'02_Debt Engine'!$I$24),'02_Debt Engine'!$W$24,IF('02_Debt Engine'!$D$24="Active",'02_Debt Engine'!$K$24,'02_Debt Engine'!$P$24))-J58)) -> 89832.185 | ... W59: =IF(W57<=0,0,MIN(W57,IF(AND('02_Debt Engine'!$F$24="Yes",'02_Debt Engine'!$V$24>0,W$4>'02_Debt Engine'!$I$24),'02_Debt Engine'!$W$24,IF('02_Debt Engine'!$D$24="Active",'02_Debt Engine'!$K$24,'02_Debt Engine'!$P$24))-W58)) -> 145466.27
B60: End Balance | C60: =C57-C59 -> 5408513.4 | D60: =D57-D59 -> 5338371.8 | E60: =E57-E59 -> 5265277.2 | F60: =F57-F59 -> 5189105.4 | G60: =G57-G59 -> 5109726.8 | H60: =H57-H59 -> 5027006.2 | I60: =I57-I59 -> 4940803.2 | J60: =J57-J59 -> 4850971 | ... W60: =W57-W59 -> 6157503.9
